Workbook
Name AsOfDate: '00_前提・使い方'!$B$5
Name EvalIDs: '32_定義マスター'!$A$13:$A$30
Name EvalPlanKeys: '15_評価計画・品質ゲート'!$V$4:$V$103
Name RoleIDs: '06_ロール・要員計画'!$A$4:$A$23
Name SkillIDs: '07_スキル辞書'!$A$4:$A$109
Name TaskIDs: '02_工程タスク'!$A$4:$A$135

Sheet 00_前提・使い方
A1: AIシステム自社事業PJ 工程管理 v1.1
A2: 事業仮説 → 投資 → 利用者価値 → 公開 → 実績 → 継続／撤退｜添付改訂提案を実行用に整理
A3: 項目 | B3: 内容・案件入力 | C3: 運用上の注意
A4: 版 | B4: v1.1（敵対的レビュー27件反映） | C4: v1.0原本を保持した改訂版。132Task／106Skill／20Roleは継承。修正対応と検証は33。
A5: 管理基準日 | B5: 46271 | C5: 期限チェックはこの日付。運用時に更新する。
A6: 事業・サービス名 | C6: 案件開始時に必須入力
A7: 提供形態 | C7: B2B / B2C / 社内事業 / 複合
A8: 対象業界・用途 | C8: 高影響・規制業務を含めて記入
A9: 提供国・利用者所在国 | C9: 日本を自動前提にしない。法令判定12へ接続
A10: 処理・保存・送信国 | C10: 開発AI、評価SaaS、ログ基盤も含む
A11: Business Owner（実名） | C11: R01。投資・継続・撤退の最終責任
A12: Product / Service Owner | C12: R02とR18をそれぞれ記入
A13: 機能・モデル・配置 | C13: 非AI比較、RAG、Agent、学習、API/ローカル
A14: 主要データ・権利 | C14: 個人情報区分、利用目的、取扱いOwner
A15: Risk Tier（確定値） | C15: 03で判定し人が承認。T0〜T3は社内分類
A16: 規模・予算・期間 | C16: 小中大、概算予算、探索上限、対象期間
A17: 既存統合・利用者・SLO | C17: 容量、重要度、統合件数、サービス時間
... A19: 記録の正本 | C19: 仕様・コード・評価・承認の実際の保存先
A20: 使い始めの順序 | B20: 00 → 03/04 → 05/06/35 → 25/26 → 15/17 → 16/30 → 29/31 → 20 | C20: 最初に前提と意思決定者を埋める。全タスクの機械的実施は不要。
A21: 資料の責務 | B21: 02=標準定義、17=実行原票、15/16=評価、29=承認、25/26=事業仮説・投資 | C21: Excelは索引・点検。仕様／コード／評価／決裁は版管理された正本。Run・同期は34。
A22: 七工程 | B22: 企画→要件→設計→実装↔評価→運用→廃止 | C22: 順番の固定ではなく反復モデル。評価計画は要件で開始する。
A23: PoCの扱い | B23: 最大の不確実性を潰す最小実験 | C23: 独立した必須工程にはしない。失敗・停止も正当な成果。
A24: 色と入力 | B24: 薄黄＋青字=案件入力、濃色見出し=定義、黒字数式=自動計算 | C24: 値0と未測定の空欄を区別。数式セルは上書きしない。
A25: 習熟度 | B25: Lv0=関与なし、Lv1=指導下、Lv2=自律遂行、Lv3=設計・指導・例外判断 | C25: 人の能力は07/28、AgentのSkillパッケージは14/11で別管理。
A26: 根拠の扱い | B26: U01=添付提案、U02=受託版、U03=本資料で具体化、W*=一次資料再確認 | C26: 原文のレンジ・目標は参考。法令・任意指針・実践例を24で区別。
A27: 案件未確定 | B27: 実名、日時、金額、評価閾値、法適用、承認は未入力 | C27: テンプレートに完了承認済みの架空データは置いていない。
A28: 自動チェックの限界 | B28: 記録・参照・日時・定義整合を点検。真正な決裁・法令適合・実行権限・証拠内容は正本側で確認。 | C28: 実質的な品質、法令適合、URIの実在、循環依存、クリティカルパスは人が確認。
A29: 更新・反復 | B29: 17は初回132行。反復34、計画15・実績16・Gate29は予約行へ追加。上限外は正本管理とテンプレート改訂。 | C29: 検証スクリプトは循環・未知ID・数値・ID重複・同期仕様を補助検査。Excelの直接依存点検とは別。
A30: 重要な停止原則 | B30: 法的禁止、未承認の実データ送信、重大未対策、独立評価不合格は公開しない | C30: 事業責任者の予算承認で法務・安全の不合格を上書きしない。
A34: 記録ダッシュボード（品質・事業成果の合否ではありません）
A35: 指標 | B35: 自動集計 | C35: 意味
A36: 標準タスク数 | B36: =COUNTA('02_工程タスク'!A4:A135) -> 132 | C36: 初回ライフサイクルの定義数
A37: スキル数 | B37: =COUNTA('07_スキル辞書'!A4:A109) -> 106 | C37: 行動基準を持つ人の能力辞書
A38: 適用未判定 | B38: =COUNTIF('17_ロードマップ・案件実行管理'!E4:E135,"未判定") -> 132 | C38: 人による適用判定が必要な数
A39: 適用タスク | B39: =COUNTIF('17_ロードマップ・案件実行管理'!E4:E135,"適用") -> 0 | C39: 対象外は別承認が必要
A40: 完了記録・前提充足 | B40: =SUM('17_ロードマップ・案件実行管理'!AA4:AA135) -> 0 | C40: 証跡の内容まで自動審査しない
A41: 完了記録率 | B41: =IF(B39=0,"",B40/B39) | C41: 適用タスクに対する記録上の完了率
A42: 予定人時間 | B42: =IF(COUNT('17_ロードマップ・案件実行管理'!P4:P135)=0,"",SUM('17_ロードマップ・案件実行管理'!P4:P135)) | C42: 未入力を実績0と表示しない
A45: シートナビゲーション
A46: シート | B46: 役割 | C46: 推奨利用時点
A47: 01_事業ライフサイクル・ゲート | B47: 下記リンクから開く | C47: 標準定義／案件台帳の区別は各シートの説明を参照
A48: 02_工程タスク | B48: 下記リンクから開く | C48: 標準定義／案件台帳の区別は各シートの説明を参照
A49: 03_AIリスクTier・適用判定 | B49: 下記リンクから開く | C49: 標準定義／案件台帳の区別は各シートの説明を参照
A50: 04_規模・テーラリング | B50: 下記リンクから開く | C50: 標準定義／案件台帳の区別は各シートの説明を参照
A51: 05_意思決定・RACI | B51: 下記リンクから開く | C51: 標準定義／案件台帳の区別は各シートの説明を参照
A52: 06_ロール・要員計画 | B52: 下記リンクから開く | C52: 標準定義／案件台帳の区別は各シートの説明を参照
A53: 07_スキル辞書 | B53: 下記リンクから開く | C53: 標準定義／案件台帳の区別は各シートの説明を参照
A54: 08_タスク×ロール×スキル | B54: 下記リンクから開く | C54: 標準定義／案件台帳の区別は各シートの説明を参照
A55: 09_成果物・正本マップ | B55: 下記リンクから開く | C55: 標準定義／案件台帳の区別は各シートの説明を参照
A56: 10_データ台帳 | B56: 下記リンクから開く | C56: 標準定義／案件台帳の区別は各シートの説明を参照
A57: 11_モデル・外部AI・ベンダー台帳 | B57: 下記リンクから開く | C57: 標準定義／案件台帳の区別は各シートの説明を参照
... A84: v1.1の主要ビュー | B84: 仮説25 → 実行17/34 → 評価15/16/30 → 決裁29/31 → 公開20/運用21 | C84: 日常入力はこの流れに限定。定義の複製を避ける。
A85: 管理基準日Owner | C85: 担当者を記入。基準日B5を更新して期限とFTEを再計算。
A86: 基準日更新確認日 | C86: 監査スナップショットの日付を使い、現在日との違いを把握。
A87: 証拠連鎖 | B87: PlanID@版 → EvalRun → Release+Manifest → GateRun → Condition | C87: 異なる版の合格・承認の流用を防ぐ。
A88: 実装上の限界 | B88: テンプレート点検は本人認証・法令適合・実Agent制御・実行許可の代替ではない。 | C88: 14のAT試験は実サービスで別途実行。

Sheet 01_事業ライフサイクル・ゲート
A1: 事業ライフサイクルと投資・公開ゲート
A2: 七工程は反復・並行可能。契約は23へ分離。品質・法令の不合格を投資承認で上書きしない。
A3: ID | B3: 工程 | C3: 目的 | D3: 開始・前提 | E3: Gate | F3: 最終A | G3: 必要な証拠 | H3: 判断・戻り先 | I3: 根拠
A4: B0 | B4: 企画 | C4: 利用者課題・非AI比較・需要・採算・データ・リスクを検証 | D4: B0-01で限定探索枠を先に承認 | E4: G0 | F4: R01 | G4: Opportunity Brief、反証、Business Case、体制 | H4: 次の探索・要件投資を限定承認。需要不成立は停止 | I4: U01,U03
A5: B1 | B5: 要件 | C5: 価値・業務・AI境界・評価・データ・SLOを定義 | D5: G0。ただしデータ利用承認は実取得より前 | E5: G1 | F5: R01 | G5: Product Spec、Eval Plan、Privacy、予算・体制 | H5: スコープ・証拠計画承認。必要に応じ企画へ戻す | I5: U01,U03
A6: B2 | B6: 設計 | C6: 方式・データ・権限・UX・Harness・復旧・原価を設計 | D6: G1・必要な利用/外部送信条件 | E6: G2 | F6: R01 | G6: ADR、Threat Model、権限、運用、費用 | H6: 技術責任者の勧告＋次のBuild投資承認 | I6: U01,U03
A7: B3 | B7: 実装 | C7: 小さな縦切りで実装・自動検証・レビューを反復 | D7: G2。小変更は承認済み境界内で継続 | E7: G3への入力 | F7: R06 | G7: コード/構成manifest、CI、評価、PR | H7: 固定RCへ。評価を後工程へ先送りしない | I7: U01,U03
A8: B4 | B8: 評価 | C8: 独立品質・安全・運用評価→段階公開→Launch | D8: 固定RC。公開前にG3 | E8: G3 | F8: R18 | G8: 独立評価、Privacy/Security、運用、採算、停止 | H8: R19が品質判定。重大リスク受容はR01。公開後も監視 | I8: U01,U03
A9: B5 | B9: 運用 | C9: 価値・品質・SLO・費用を観測し実験・改善 | D9: G3・運用引継ぎ | E9: G4 | F9: R01 | G9: 事業KPI、継続率、原価、事故、変更、投資 | H9: Scale / Continue / Pivot / Shrink / Stop | I9: U01,U03
A10: B6 | B10: 廃止 | C10: 通知・移行・データ・権限・契約・費用を終了 | D10: 任意GateのStop／承認済み廃止判断。G3/G4未到達でも可。 | E10: G5 | F10: R01 | G10: Deletion/Retention、失効試験、解約、独立確認 | H10: 保全残件は期限付きOwnerへ。画面閉鎖だけで完了しない | I10: U01,U03
A13: ゲートに共通する判断ルール
A14: 観点 | B14: 定義 | C14: 必要な記録 | D14: 禁止事項 | E14: 関連シート
A15: Go | B15: 承認した範囲・版・予算のみ進行 | C15: 承認した範囲・版・予算のみ。条件は31のConditionIDで所有者・期限・解消・失効を追跡。 | D15: 全額投資・用途拡大の白紙委任 | E15: 29
A16: 条件付き | B16: 安全・法令の必須条件を満たす範囲に限定 | C16: 条件、Owner、期限、期限切れ時停止 | D16: 重大未対策や違法行為を条件付きで承認 | E16: 19,29
A17: 再検証 / Pivot | B17: 仮説と実験計画を改訂 | C17: 反証、追加費用、停止期限 | D17: 成功例だけを残す | E17: 25,26
A18: Stop / Shrink | B18: 新規公開を制限し縮小・廃止へ | C18: 利用者保護、移行、残件 | D18: 画面を閉じるだけで終了 | E18: 22
A19: 緊急変更 | B19: 被害抑止のための限定措置 | C19: 権限者、時刻、実施内容、事後審査期限 | D19: 恒久変更を緊急扱いで放置 | E19: 20,21

Sheet 02_工程タスク
A1: 工程タスク｜標準定義の正本
A2: 132タスク。S/M/Lで安全工程を自動省略しない。適用・実名・期限・証拠は17に記録。B-IDは自社事業版の独立ID。
A3: タスクID | B3: 工程 | C3: 作業区分 | D3: タスク名 | E3: 具体的な実施内容 | F3: 成果物・証拠群 | G3: 実施R | H3: 承認A | I3: 完了条件 | J3: 適用条件 | K3: S | L3: M | M3: L | N3: Gate | O3: 基本依存ID | P3: 必要スキルID | Q3: AI活用と人の境界 | R3: 旧v3 ID | S3: 記載区分 | T3: 根拠ID | U3: 確認用URL
A4: B0-01 | B4: 企画 | C4: 探索統制 | D4: 探索責任者・初期枠の設定 | E4: 誰が事業価値と損失に責任を持つかを確定し、G0以前の探索に使える人時間・費用・期間を限定する。公開情報調査を原則とし、未承認の実データ取得を禁止する。 | F4: 探索チャーター・初期予算枠 | G4: R02, R03 | H4: R01 | I4: 責任者、探索上限、意思決定日、停止権限が記録されている。 | J4: 全 | K4: 共通 | L4: 共通 | M4: 共通 | N4: G0 | P4: S001,S006,S082 | Q4: AIで調査・仮説・質問を草案化。人が一次情報・実行動・投資判断を確認。 | R4: P0-06,P1-03 | S4: 添付提案の具体化／旧版再編 | T4: U01,U02
A5: B0-02 | B5: 企画 | C5: 市場調査 | D5: 市場・競合・規制候補の調査 | E5: 市場、代替サービス、既存業務、対象国と規制業種を一次情報で確認する。AIで草案化しても事実・推定・未確認を分離する。 | F5: 調査メモ・根拠一覧 | G5: R02, R04, R16 | H5: R02 | I5: 対象市場、利用者、競合、情報の確認日と不確実性がある。 | J5: 全 | K5: 共通 | L5: 共通 | M5: 共通 | N5: G0 | O5: B0-01 | P5: S002,S007,S008 | Q5: AIで調査・仮説・質問を草案化。人が一次情報・実行動・投資判断を確認。 | R5: P0-01 | S5: 添付提案の具体化／旧版再編 | T5: U01,W01 | U5: https://www.meti.go.jp/shingikai/mono_info_service/ai_shakai_jisso/
A6: B0-03 | B6: 企画 | C6: 課題探索 | D6: 利用者・購買者の仮説分解 | E6: B2Bは利用者・決裁者・管理者、B2Cは利用者・支払者を区別し、社内利用は受益部門を特定する。調査参加同意と記録の扱いを決める。 | F6: 対象セグメント・調査計画 | G6: R02, R05 | H6: R02 | I6: 対象者、募集条件、質問、個人情報取扱いが明確。 | J6: 全 | K6: 共通 | L6: 共通 | M6: 共通 | N6: G0 | O6: B0-02 | P6: S004,S082,S085 | Q6: AIで調査・仮説・質問を草案化。人が一次情報・実行動・投資判断を確認。 | R6: P0-02 | S6: 添付提案の具体化／旧版再編 | T6: U01
A7: B0-04 | B7: 企画 | C7: 課題探索 | D7: インタビュー・現場観察 | E7: 現行行動、困りごとの頻度・損失、回避策を調べる。AIへの期待だけを需要の証拠にせず、発言と実行行動を分ける。 | F7: JTBD・観察記録 | G7: R05, R04 | H7: R02 | I7: 現行の代替行動と未解決課題を記録し、反証も保存。 | J7: 全 | K7: 共通 | L7: 共通 | M7: 共通 | N7: G0 | O7: B0-03 | P7: S004,S019,S082 | Q7: AIで調査・仮説・質問を草案化。人が一次情報・実行動・投資判断を確認。 | R7: P0-03,P1-01 | S7: 添付提案の具体化／旧版再編 | T7: U01
A8: B0-05 | B8: 企画 | C8: 価値仮説 | D8: 課題・価値・差別化の定義 | E8: 誰のどの業務成果をどれだけ改善するかを定義する。AI搭載自体を価値とせず、解決しない問題と競争優位の仮説を明記する。 | F8: Opportunity Brief | G8: R02, R04 | H8: R01 | I8: 価値仮説、非対象、代替手段との違いを説明できる。 | J8: 全 | K8: 共通 | L8: 共通 | M8: 共通 | N8: G0 | O8: B0-04 | P8: S008,S009,S082 | Q8: AIで調査・仮説・質問を草案化。人が一次情報・実行動・投資判断を確認。 | R8: P1-02 | S8: 添付提案の具体化／旧版再編 | T8: U01
A9: B0-06 | B9: 企画 | C9: 方式探索 | D9: 非AI・Build/Buy/Partnerの比較 | E9: 業務変更、ルール、既製SaaS、モデルAPI、RAG、学習、自律Agentを比較する。最も単純に価値を満たす案から試す。 | F9: 方式比較・仮ADR | G9: R06, R08, R20 | H9: R01 | I9: 品質、運用責任、権利、総費用、切替可能性を比較。 | J9: 全 | K9: 共通 | L9: 共通 | M9: 共通 | N9: G0 | O9: B0-05 | P9: S018,S030,S053,S054 | Q9: AIで調査・仮説・質問を草案化。人が一次情報・実行動・投資判断を確認。 | R9: P0-04,P1-04 | S9: 添付提案の具体化／旧版再編 | T9: U01,W04 | U9: https://www.anthropic.com/engineering/building-effective-agents
A10: B0-07 | B10: 企画 | C10: データ戦略 | D10: データ資産・権利の棚卸し | E10: 所在、Owner、利用権、品質、取得費、更新性をメタデータから把握する。サンプル取得は利用可否承認後に行う。 | F10: 初期Data Asset候補 | G10: R09, R10, R14 | H10: R10 | I10: 必要データと不足、権利未確認部分、取得計画がある。 | J10: 全 | K10: 共通 | L10: 共通 | M10: 共通 | N10: G0 | O10: B0-05 | P10: S003,S055,S056 | Q10: AIで調査・仮説・質問を草案化。人が一次情報・実行動・投資判断を確認。 | R10: P1-05,P1-19 | S10: 添付提案の具体化／旧版再編 | T10: U01,W02,W03 | U10: https://www.ppc.go.jp/personalinfo/legal/guidelines_anonymous/ https://www.ppc.go.jp/personalinfo/legal/guidelines_offshore/
A11: B0-08 | B11: 企画 | C11: リスク | D11: 製品AI・開発AIの初期リスク分類 | E11: 危害、データ、自律度、書込み、対象者、国を確認する。T0〜T3は社内区分であり法的分類とは分離する。 | F11: 初期Risk Tier・法令スコープ | G11: R02, R13, R14, R11 | H11: R01 | I11: 製品と開発Agentを別境界で評価し未確定条件を記録。 | J11: 全 | K11: 共通 | L11: 共通 | M11: 共通 | N11: G0 | O11: B0-06,B0-07 | P11: S002,S017,S078 | Q11: AIで調査・仮説・質問を草案化。人が一次情報・実行動・投資判断を確認。 | R11: P1-07 | S11: 添付提案の具体化／旧版再編 | T11: U01,W01,W10 | U11: https://www.meti.go.jp/shingikai/mono_info_service/ai_shakai_jisso/ https://www.nist.gov/publications/artificial-intelligence-risk-management-framework-generative-artificial-intelligence
A12: B0-09 | B12: 企画 | C12: 収益仮説 | D12: 価格・支払意思・提供形態の仮説 | E12: 課金単位、支払意思、無償範囲、利用上限、B2B導入条件を検討する。社内事業は売上でなく内部価値と費用負担を定める。 | F12: 価格仮説・価値交換モデル | G12: R02, R15, R16 | H12: R01 | I12: 誰が何に支払うか、代替価格、検証方法がある。 | J12: 全 | K12: 共通 | L12: 共通 | M12: 共通 | N12: G0 | O12: B0-05 | P12: S083,S084,S093 | Q12: AIで調査・仮説・質問を草案化。人が一次情報・実行動・投資判断を確認。 | R12: P1-17 | S12: 添付提案の具体化／旧版再編 | T12: U01
A13: B0-10 | B13: 企画 | C13: 投資計画 | D13: 単位経済性・TCO・感度分析 | E13: AI費、検索、保存、再試行、人手確認、CS、固定費を分け、成功タスク当たり原価を試算する。利用増・単価変更・低成功率を含むシナリオを置く。 | F13: Business Case・原価仮説 | G13: R15, R08, R12 | H13: R01 | I13: 費用境界と仮定が明確で、AI一律削減を含まない。 | J13: 全 | K13: 共通 | L13: 共通 | M13: 共通 | N13: G0 | O13: B0-06,B0-09 | P13: S010,S012,S050,S093 | Q13: AIで調査・仮説・質問を草案化。人が一次情報・実行動・投資判断を確認。 | R13: P1-06,P2-15 | S13: 添付提案の具体化／旧版再編 | T13: U01,W08 | U13: https://dora.dev/ai/roi/calculator/
A14: B0-11 | B14: 企画 | C14: 実験計画 | D14: 最大不確実性と検証順の設定 | E14: 需要・実現性・安全性・採算の仮説ごとに、反証条件、最小実験、予算・期限を決める。PoCは必要な仮説にのみ置く。 | F14: 仮説・実験バックログ | G14: R02, R08, R11 | H14: R02 | I14: 成功だけでなく再検証・縮小・停止条件が事前定義。 | J14: 全 | K14: 共通 | L14: 共通 | M14: 共通 | N14: G0 | O14: B0-08,B0-10 | P14: S062,S087,S104 | Q14: AIで調査・仮説・質問を草案化。人が一次情報・実行動・投資判断を確認。 | R14: P1-20 | S14: 添付提案の具体化／旧版再編 | T14: U01,W04 | U14: https://www.anthropic.com/engineering/building-effective-agents
A15: B0-12 | B15: 企画 | C15: 需要検証 | D15: コンセプト・手動代替による需要検証 | E15: モックや人手サービスで利用意思と現実の行動を確認する。誤認を招く未実装機能の宣伝や、無承認の高影響用途での試験を避ける。 | F15: 需要検証記録 | G15: R05, R02, R16 | H15: R02 | I15: 募集条件、観察結果、反証、次の判断がある。 | J15: 条件:需要不確実 | K15: 条件 | L15: 条件 | M15: 条件 | N15: G0 | O15: B0-11 | P15: S021,S082,S087 | Q15: AIで調査・仮説・質問を草案化。人が一次情報・実行動・投資判断を確認。 | R15: P2-14 | S15: 添付提案の具体化／旧版再編 | T15: U01
A16: B0-13 | B16: 企画 | C16: 実現性検証 | D16: 限定プロトタイプ・非AIベースライン | E16: 合成・公開・承認済みデータで核心機能だけを試す。RAGは検索、Agentはread-onlyから試し、本番品質と同一視しない。 | F16: 最小実験・ベースライン | G16: R08, R07, R11 | H16: R06 | I16: データ許可、比較条件、限界、再現手順が残る。 | J16: 条件:技術不確実 | K16: 条件 | L16: 条件 | M16: 条件 | N16: G0 | O16: B0-07,B0-08,B0-11 | P16: S033,S062,S068 | Q16: AIで調査・仮説・質問を草案化。人が一次情報・実行動・投資判断を確認。 | R16: P2-02,P2-09,P2-10 | S16: 添付提案の具体化／旧版再編 | T16: U01,W04 | U16: https://www.anthropic.com/engineering/building-effective-agents
A17: B0-14 | B17: 企画 | C17: 事業計画 | D17: 提供・販売・サポート経路の仮設計 | E17: 獲得経路、導入負荷、セキュリティ審査、販売リードタイム、問い合わせ窓口を検討し、営業と運用の費用を含める。 | F17: GTM・導入仮説 | G17: R16, R17, R02 | H17: R01 | I17: 利用開始までの障壁と検証予定を記録。 | J17: 全 | K17: 共通 | L17: 共通 | M17: 共通 | N17: G0 | O17: B0-09 | P17: S085,S086,S089 | Q17: AIで調査・仮説・質問を草案化。人が一次情報・実行動・投資判断を確認。 | R17: P4-21 | S17: 添付提案の具体化／旧版再編 | T17: U01
A18: B0-15 | B18: 企画 | C18: 体制 | D18: ロール・能力ギャップ・要員計画 | E18: 事業責任、PdM、実装、評価、本番、データ、法務の担当を決める。兼務時も自己承認を避け、必要な外部専門家を確保する。 | F18: RACI・スキル充足計画 | G18: R03, R06, R11 | H18: R01 | I18: 実名、稼働枠、独立評価、代行、不足対策がある。 | J18: 全 | K18: 共通 | L18: 共通 | M18: 共通 | N18: G0 | O18: B0-08 | P18: S006,S016,S088 | Q18: AIで調査・仮説・質問を草案化。人が一次情報・実行動・投資判断を確認。 | R18: P1-03,P1-15 | S18: 添付提案の具体化／旧版再編 | T18: U01
A19: B0-16 | B19: 企画 | C19: 計画 | D19: 規模・適用・段階投資の設定 | E19: 工程の深さを機能・危害で決め、各実験への投資上限を設定する。工数レンジは添付案の未較正値として参考表示し自動見積に使わない。 | F19: 適用判定・段階予算 | G19: R03, R15 | H19: R01 | I19: 除外理由、代替証拠、再判定条件を承認。 | J19: 全 | K19: 共通 | L19: 共通 | M19: 共通 | N19: G0 | O19: B0-11,B0-15 | P19: S016,S018,S081 | Q19: AIで調査・仮説・質問を草案化。人が一次情報・実行動・投資判断を確認。 | R19: P1-08,P1-14 | S19: 添付提案の具体化／旧版再編 | T19: U01
A20: B0-17 | B20: 企画 | C20: 実験判断 | D20: 探索証拠と反証の整理 | E20: 需要・技術・採算・安全の未解決を比較し、追加検証の価値を判断する。うまくいかなかった実験結果も削除しない。 | F20: 探索レビュー | G20: R02, R08, R15 | H20: R01 | I20: 最重要仮説に対する証拠と残存不確実性がある。 25の検証状態・必要行動証拠を確認し、未検証の持越しには理由・次実験・上限・再判断日・停止条件を記録。 | J20: 全 | K20: 共通 | L20: 共通 | M20: 共通 | N20: G0 | O20: B0-11,B0-16 | P20: S009,S062,S087,S005 | Q20: AIで調査・仮説・質問を草案化。人が一次情報・実行動・投資判断を確認。 | R20: P2-17,P2-19 | S20: 添付提案の具体化／旧版再編 | T20: U01
A21: B0-18 | B21: 企画 | C21: G0 | D21: 事業探索・予算枠承認 | E21: G0で次の探索・要件の範囲、予算、成功・停止条件を承認する。承認は未解決リスクの免責や全額投資の一括許可としない。 | F21: G0判断記録 | G21: R02, R03 | H21: R01 | I21: Go/条件付き/再検証/停止、条件期限、責任者を記録。 25の検証状態・必要行動証拠を確認し、未検証の持越しには理由・次実験・上限・再判断日・停止条件を記録。 | J21: 全 | K21: 共通 | L21: 共通 | M21: 共通 | N21: G0 | O21: B0-17,B0-10,B0-15 | P21: S001,S081,S104 | Q21: AIで調査・仮説・質問を草案化。人が一次情報・実行動・投資判断を確認。 | R21: P0-06,P2-19,P1-18 | S21: 添付提案の具体化／旧版再編 | T21: U01
A22: B1-01 | B22: 要件 | C22: 価値要件 | D22: Product Goal・KPIツリー | E22: 価値仮説から業務成果、利用行動、品質・安全ガードレールを定義し、分母、観測期間、Ownerを定める。 | F22: Product Goal・KPI定義 | G22: R02, R15 | H22: R01 | I22: 主要指標と悪化させてはいけない指標を承認。 | J22: 全 | K22: 共通 | L22: 共通 | M22: 共通 | N22: G1 | O22: B0-18 | P22: S009,S090 | Q22: 仕様・異常系・評価を草案化。人が業務正解・禁止事項・閾値・利用許可を承認。 | R22: P1-16 | S22: 添付提案の具体化／旧版再編 | T22: U01
A23: B1-02 | B23: 要件 | C23: 業務要件 | D23: As-Is/To-BeとHuman-AI分担 | E23: 通常、例外、承認待ち、誤回答、失敗時を含めて業務を設計する。人間の確認負荷・権限と責任も見積もる。 | F23: 業務フロー・介入設計 | G23: R04, R05, R02 | H23: R02 | I23: 利用者、AI、人の責任と戻り経路が明確。 | J23: 全 | K23: 共通 | L23: 共通 | M23: 共通 | N23: G1 | O23: B1-01 | P23: S019,S032,S095 | Q23: 仕様・異常系・評価を草案化。人が業務正解・禁止事項・閾値・利用許可を承認。 | R23: P1-09 | S23: 添付提案の具体化／旧版再編 | T23: U01
A24: B1-03 | B24: 要件 | C24: スコープ | D24: User Story・受入条件・禁止事項 | E24: Issueごとに利用者、価値、操作範囲、禁止操作、受入観点、評価IDを付ける。要望を機能量で優先順位付けしない。 | F24: Product Spec・Issue | G24: R02, R04, R11 | H24: R02 | I24: 追跡可能な要件IDと評価ID、非対象がある。 | J24: 全 | K24: 共通 | L24: 共通 | M24: 共通 | N24: G1 | O24: B1-02 | P24: S020,S076,S087 | Q24: 仕様・異常系・評価を草案化。人が業務正解・禁止事項・閾値・利用許可を承認。 | R24: P1-10,P1-16 | S24: 添付提案の具体化／旧版再編 | T24: U01
A25: B1-04 | B25: 要件 | C25: データ利用 | D25: データ取得・目的・法令適用判定 | E25: 目的、取得根拠、仮名/匿名区分、委託/第三者提供、外国提供を別々に確認する。実データ受領・調査記録外部送信の前に条件を確定する。 | F25: Privacy Gate・Data許可 | G25: R10, R14, R13 | H25: R14 | I25: 対象Asset、送信先、用途、保持・削除条件を承認。 | J25: 全 | K25: 共通 | L25: 共通 | M25: 共通 | N25: G1 | O25: B0-07,B0-08 | P25: S003,S015,S094 | Q25: 仕様・異常系・評価を草案化。人が業務正解・禁止事項・閾値・利用許可を承認。 | R25: P1-19,P2-03 | S25: 添付提案の具体化／旧版再編 | T25: U01,W02,W03 | U25: https://www.ppc.go.jp/personalinfo/legal/guidelines_anonymous/ https://www.ppc.go.jp/personalinfo/legal/guidelines_offshore/
A26: B1-05 | B26: 要件 | C26: データ要件 | D26: 品質・鮮度・権限・ラベル要件 | E26: 必要範囲、欠損許容、アクセス制御、更新頻度、ラベル基準、評価との分離をデータ要件にする。 | F26: Data Requirement | G26: R09, R10, R11 | H26: R10 | I26: Owner、出所、権利、品質基準、派生資産が定義済。 | J26: 全 | K26: 共通 | L26: 共通 | M26: 共通 | N26: G1 | O26: B1-04 | P26: S031,S055,S056,S058 | Q26: 仕様・異常系・評価を草案化。人が業務正解・禁止事項・閾値・利用許可を承認。 | R26: P1-12,P2-04 | S26: 添付提案の具体化／旧版再編 | T26: U01
A27: B1-06 | B27: 要件 | C27: AI要件 | D27: AI機能境界・自律性・不確実性 | E27: AIに任せる判断、ツール、実行時間、許容失敗、人間承認と非AIフォールバックを定義する。モデルの確信表現を確率と同一視しない。 | F27: AI動作要件 | G27: R08, R04, R11 | H27: R02 | I27: 機能別に期待・禁止・失敗時挙動を記録。 | J27: 全 | K27: 共通 | L27: 共通 | M27: 共通 | N27: G1 | O27: B1-03 | P27: S054,S065,S069 | Q27: 仕様・異常系・評価を草案化。人が業務正解・禁止事項・閾値・利用許可を承認。 | R27: P1-11 | S27: 添付提案の具体化／旧版再編 | T27: U01,W04 | U27: https://www.anthropic.com/engineering/building-effective-agents
A28: B1-07 | B28: 要件 | C28: 評価要件 | D28: 評価母集団・指標・閾値・失敗定義 | E28: 現実の利用分布、重要slice、反復、判定者、標本の限界を決める。万能な精度閾値を置かず重大失敗を別条件にする。 | F28: Eval Plan | G28: R11, R04, R08 | H28: R19 | I28: 指標ごとの分母・閾値・重大条件・根拠がある。 | J28: 全 | K28: 共通 | L28: 共通 | M28: 共通 | N28: G1 | O28: B1-03,B1-05,B1-06 | P28: S052,S067,S070,S077 | Q28: 仕様・異常系・評価を草案化。人が業務正解・禁止事項・閾値・利用許可を承認。 | R28: P1-11,P2-05 | S28: 添付提案の具体化／旧版再編 | T28: U01,W05,W10 | U28: https://www.anthropic.com/engineering/demystifying-evals-for-ai-agents https://www.nist.gov/publications/artificial-intelligence-risk-management-framework-generative-artificial-intelligence
A29: B1-08 | B29: 要件 | C29: 非機能 | D29: SLO・容量・可用性・費用要件 | E29: 利用量、ピーク、遅延、可用性、復旧目標、コスト上限をサービス特性から決める。予算超過時は安全に縮退・停止する。 | F29: NFR・SLO初版 | G29: R12, R08, R15 | H29: R18 | I29: 測定点、時間窓、費用境界、復旧目標を合意。 | J29: 全 | K29: 共通 | L29: 共通 | M29: 共通 | N29: G1 | O29: B1-01,B1-06 | P29: S023,S029,S050 | Q29: 仕様・異常系・評価を草案化。人が業務正解・禁止事項・閾値・利用許可を承認。 | R29: P1-13 | S29: 添付提案の具体化／旧版再編 | T29: U01
A30: B1-09 | B30: 要件 | C30: UX要件 | D30: 透明性・アクセシビリティ・救済 | E30: AI利用表示、根拠・限界、取消・訂正、問い合わせ、必要な人への移管を決める。アクセシビリティと誤信頼を検証対象にする。 | F30: Human-AI UX要件 | G30: R05, R17, R14 | H30: R02 | I30: 重要操作の確認・失敗時案内・救済導線がある。 | J30: 全 | K30: 共通 | L30: 共通 | M30: 共通 | N30: G1 | O30: B1-02 | P30: S032,S095,S096 | Q30: 仕様・異常系・評価を草案化。人が業務正解・禁止事項・閾値・利用許可を承認。 | R30: P2-14,P3-05 | S30: 添付提案の具体化／旧版再編 | T30: U01
A31: B1-10 | B31: 要件 | C31: リスク要件 | D31: Risk Tier確定・独立性の設計 | E31: 用途と影響によりT0〜T3を人が確定する。独立評価者、品質停止権、禁止用途、例外を定め、法的分類は別台帳に置く。 | F31: Risk Tier・評価独立性 | G31: R11, R13, R14 | H31: R01 | I31: 実装・評価・公開承認の利益相反が解消。 | J31: 全 | K31: 共通 | L31: 共通 | M31: 共通 | N31: G1 | O31: B1-04,B1-06,B1-07 | P31: S017,S071,S077,S081 | Q31: 仕様・異常系・評価を草案化。人が業務正解・禁止事項・閾値・利用許可を承認。 | R31: P1-07,P2-16 | S31: 添付提案の具体化／旧版再編 | T31: U01,W01,W10 | U31: https://www.meti.go.jp/shingikai/mono_info_service/ai_shakai_jisso/ https://www.nist.gov/publications/artificial-intelligence-risk-management-framework-generative-artificial-intelligence
A32: B1-11 | B32: 要件 | C32: GTM要件 | D32: オンボーディング・提供条件 | E32: 利用開始、権限設定、初回価値到達、教育、サポート、契約・表示条件を定義する。企業向けの管理者・購買要件も扱う。 | F32: 提供・導入要件 | G32: R16, R17, R05 | H32: R02 | I32: 利用開始と継続の障壁、責任範囲が定義済。 | J32: 全 | K32: 共通 | L32: 共通 | M32: 共通 | N32: G1 | O32: B0-14,B1-09 | P32: S022,S085,S089 | Q32: 仕様・異常系・評価を草案化。人が業務正解・禁止事項・閾値・利用許可を承認。 | R32: P3-23 | S32: 添付提案の具体化／旧版再編 | T32: U01
A33: B1-12 | B33: 要件 | C33: 収益要件 | D33: 価格・課金・利用制限の設計 | E33: 課金メーター、無料枠、上限、返金、過大請求防止を定義する。商用提供しない場合は内部配賦と予算制御で代替する。 | F33: 価格・課金仕様 | G33: R02, R15, R16 | H33: R01 | I33: 課金イベントと原価、説明、返金・取消条件を承認。 | J33: 条件:外販・課金 | K33: 条件 | L33: 条件 | M33: 条件 | N33: G1 | O33: B0-09,B0-10 | P33: S083,S091,S093 | Q33: 仕様・異常系・評価を草案化。人が業務正解・禁止事項・閾値・利用許可を承認。 | S33: 添付提案の具体化／旧版再編 | T33: U01
A34: B1-13 | B34: 要件 | C34: 調達要件 | D34: モデル・クラウド・委託先の条件 | E34: 外部サービスのデータ利用、保存、地域、再委託、EOL、監査、障害通知、SLA、退出条件を調達要件にする。 | F34: 調達・依存条件 | G34: R20, R14, R08 | H34: R20 | I34: 許容できない条件と代替案を記録。 | J34: 条件:外部依存 | K34: 条件 | L34: 条件 | M34: 条件 | N34: G1 | O34: B1-04,B1-08 | P34: S014,S015,S094,S092 | Q34: 仕様・異常系・評価を草案化。人が業務正解・禁止事項・閾値・利用許可を承認。 | R34: P0-05,P2-20 | S34: 添付提案の具体化／旧版再編 | T34: U01
A35: B1-14 | B35: 要件 | C35: AI開発統制 | D35: 開発Agent利用・送信・権限の承認 | E35: 投入可能情報、コード・ログ送信、MCP、実行コマンド、ネットワーク、秘密情報、承認境界を定義する。 | F35: 開発AI利用ポリシー | G35: R06, R13, R14 | H35: R06 | I35: 承認済みツールと送信先、停止・監査の担当が明確。 | J35: 条件:開発AI | K35: 条件 | L35: 条件 | M35: 条件 | N35: G1 | O35: B1-04,B1-10 | P35: S028,S078,S099 | Q35: 仕様・異常系・評価を草案化。人が業務正解・禁止事項・閾値・利用許可を承認。 | R35: P1-23 | S35: 添付提案の具体化／旧版再編 | T35: U01,W06,W12 | U35: https://openai.com/index/harness-engineering/ https://genai.owasp.org/resource/a-practical-guide-for-secure-mcp-server-development/
A36: B1-15 | B36: 要件 | C36: 実験運営 | D36: Evidence Plan・学習ループ設計 | E36: PoCを別契約フェーズにせず、各仮説の最小実験・予算・打切りをIssueにする。必要データと独立評価を先行準備する。 | F36: 実験計画・判定条件 | G36: R02, R08, R11 | H36: R02 | I36: 仮説から実験・評価・判断までID連結済。 | J36: 全 | K36: 共通 | L36: 共通 | M36: 共通 | N36: G1 | O36: B1-07,B1-10 | P36: S062,S087,S104 | Q36: 仕様・異常系・評価を草案化。人が業務正解・禁止事項・閾値・利用許可を承認。 | R36: P1-20,P1-22,P2-01 | S36: 添付提案の具体化／旧版再編 | T36: U01
A37: B1-16 | B37: 要件 | C37: 計画 | D37: ロードマップ・依存・スキル充足 | E37: 価値とリスク低減で優先順位を決め、薄い縦切り実装単位に分割する。工数と経過時間を分け、レビュー容量を制約に含める。 | F37: ロードマップ・要員計画 | G37: R03, R02, R06 | H37: R01 | I37: 担当、依存、予算枠、能力不足、意思決定日がある。 | J37: 全 | K37: 共通 | L37: 共通 | M37: 共通 | N37: G1 | O37: B1-15,B0-15 | P37: S016,S088,S106 | Q37: 仕様・異常系・評価を草案化。人が業務正解・禁止事項・閾値・利用許可を承認。 | R37: P3-02 | S37: 添付提案の具体化／旧版再編 | T37: U01
A38: B1-17 | B38: 要件 | C38: 継続改善 | D38: 変更・廃止・データ権利の要件 | E38: 用途拡大、Provider変更、データ更新、書込み追加を再審査トリガーにする。終了時の移管、保持・削除、通知も要件化する。 | F38: 変更・退出要件 | G38: R18, R10, R14 | H38: R18 | I38: 重大変更と廃止の責任者、条件、再ゲートがある。 | J38: 全 | K38: 共通 | L38: 共通 | M38: 共通 | N38: G1 | O38: B1-10,B1-13 | P38: S080,S081,S103 | Q38: 仕様・異常系・評価を草案化。人が業務正解・禁止事項・閾値・利用許可を承認。 | R38: P4-15,P4-22 | S38: 添付提案の具体化／旧版再編 | T38: U01
A39: B1-18 | B39: 要件 | C39: 計測 | D39: 事業・開発・AIコスト計測の仕様 | E39: 利用者価値と品質、AI人時間、レビュー・手戻り、elapsed time、費用の観測方法を定義する。個人監視を目的にしない。 | F39: 計測計画・同等比較ルール | G39: R15, R03, R11 | H39: R02 | I39: 比較範囲、分母、期間、取得権利、欠測扱いを合意。 | J39: 全 | K39: 共通 | L39: 共通 | M39: 共通 | N39: G1 | O39: B1-01,B1-14 | P39: S079,S090,S093 | Q39: 仕様・異常系・評価を草案化。人が業務正解・禁止事項・閾値・利用許可を承認。 | R39: P1-17,P4-19 | S39: 添付提案の具体化／旧版再編 | T39: U01,W07,W08 | U39: https://metr.org/blog/2026-02-24-uplift-update/ https://dora.dev/ai/roi/calculator/
A40: B1-19 | B40: 要件 | C40: G1 | D40: スコープ・Evidence Plan承認 | E40: 価値、要件、禁止事項、データ利用、評価、予算、体制を承認する。未確定項目は責任者・期限・公開制限を付ける。 | F40: G1判断記録 | G40: R02, R03 | H40: R01 | I40: 受入条件と投資条件が承認され、必要な法令判定済。 | J40: 全 | K40: 共通 | L40: 共通 | M40: 共通 | N40: G1 | O40: B1-07,B1-10,B1-16,B1-17 | P40: S001,S081 | Q40: 仕様・異常系・評価を草案化。人が業務正解・禁止事項・閾値・利用許可を承認。 | R40: P1-21,P2-18 | S40: 添付提案の具体化／旧版再編 | T40: U01
A41: B2-01 | B41: 設計 | C41: 構成設計 | D41: 最小構成・方式のADR | E41: 非AI、単一モデル、RAG、ワークフロー、Agentを比較し不要な複雑性を排除する。方式の変更条件も定義する。 | F41: 方式ADR | G41: R06, R08 | H41: R06 | I41: 品質・費用・運用・安全を比較し選定根拠がある。 | J41: 全 | K41: 共通 | L41: 共通 | M41: 共通 | N41: G2 | O41: B1-19 | P41: S030,S039,S054,S026 | Q41: ADR・脅威・テストの骨子を生成。人が権限・送信・方式・復旧を設計承認。 | R41: P3-03 | S41: 添付提案の具体化／旧版再編 | T41: U01,W04 | U41: https://www.anthropic.com/engineering/building-effective-agents
A42: B2-02 | B42: 設計 | C42: モデル選定 | D42: モデル・Provider比較と退出設計 | E42: 同一評価条件で候補を比較し、版固定可否、EOL、料金変更、データ取扱い、代替Providerを確認する。 | F42: モデル台帳・選定評価 | G42: R08, R20, R11 | H42: R06 | I42: 評価結果と規約・地域・変更監視を記録。 | J42: 条件:外部モデル | K42: 条件 | L42: 条件 | M42: 条件 | N42: G2 | O42: B2-01,B1-13 | P42: S054,S062,S094 | Q42: ADR・脅威・テストの骨子を生成。人が権限・送信・方式・復旧を設計承認。 | R42: P1-04,P2-10 | S42: 添付提案の具体化／旧版再編 | T42: U01
A43: B2-03 | B43: 設計 | C43: データ設計 | D43: Data Flow・権限・保存・派生設計 | E43: データ、Vector DB、索引、キャッシュ、ログ、バックアップ、評価データの流れを描き、Ownerと削除経路を定める。 | F43: Data Flow・資産設計 | G43: R09, R10, R13 | H43: R10 | I43: 全送信先と派生物に利用目的・保持・削除が対応。 | J43: 全 | K43: 共通 | L43: 共通 | M43: 共通 | N43: G2 | O43: B1-05,B1-17 | P43: S003,S025,S031,S036 | Q43: ADR・脅威・テストの骨子を生成。人が権限・送信・方式・復旧を設計承認。 | R43: P3-04 | S43: 添付提案の具体化／旧版再編 | T43: U01,W02,W03 | U43: https://www.ppc.go.jp/personalinfo/legal/guidelines_anonymous/ https://www.ppc.go.jp/personalinfo/legal/guidelines_offshore/
A44: B2-04 | B44: 設計 | C44: RAG設計 | D44: 検索・文書更新・ACLの設計 | E44: 分割、検索、rerank、引用、版、有効日、削除反映を設計する。GraphRAGは関係探索の必要性が実験で示された部分だけ採用する。 | F44: RAG ADR・検索評価仕様 | G44: R08, R09, R11 | H44: R06 | I44: 検索品質、権限漏洩、更新・削除の試験が定義済。 | J44: 条件:RAG | K44: 条件 | L44: 条件 | M44: 条件 | N44: G2 | O44: B2-03,B2-02 | P44: S061,S056,S070 | Q44: ADR・脅威・テストの骨子を生成。人が権限・送信・方式・復旧を設計承認。 | R44: P2-08 | S44: 添付提案の具体化／旧版再編 | T44: U01
A45: B2-05 | B45: 設計 | C45: 学習設計 | D45: 学習・特徴量・データ分割の設計 | E45: 追加学習が必要な根拠、権利、時系列/群分割、学習予算、再現性、停止条件を設計する。基盤モデルの大規模事前学習は別計画とする。 | F45: 学習・分割プロトコル | G45: R08, R09, R11 | H45: R06 | I45: リーク防止、独立評価、比較モデル、予算がある。 | J45: 条件:学習 | K45: 条件 | L45: 条件 | M45: 条件 | N45: G2 | O45: B2-03,B1-07 | P45: S053,S057,S060,S063 | Q45: ADR・脅威・テストの骨子を生成。人が権限・送信・方式・復旧を設計承認。 | R45: P2-05,P2-07,P2-08 | S45: 添付提案の具体化／旧版再編 | T45: U01
A46: B2-06 | B46: 設計 | C46: Agent設計 | D46: ツール・状態・行動権限の設計 | E46: read-onlyから開始し、書込みは最小権限で分離する。状態遷移、承認、再実行、副作用、取消、委譲先を設計する。 | F46: Agent状態図・Tool契約 | G46: R08, R07, R13 | H46: R06 | I46: 金銭・権限・削除・外部送信の安全境界がある。 | J46: 条件:Agent | K46: 条件 | L46: 条件 | M46: 条件 | N46: G2 | O46: B1-06,B2-01 | P46: S065,S037,S099 | Q46: ADR・脅威・テストの骨子を生成。人が権限・送信・方式・復旧を設計承認。 | R46: P3-10 | S46: 添付提案の具体化／旧版再編 | T46: U01,W04,W12 | U46: https://www.anthropic.com/engineering/building-effective-agents https://genai.owasp.org/resource/a-practical-guide-for-secure-mcp-server-development/
A47: B2-07 | B47: 設計 | C47: 脅威設計 | D47: 製品AI・開発Agentの別脅威モデル | E47: 外部文書、Issue、依存パッケージ、Tool結果を非信頼入力として扱う。注入・権限逸脱・漏洩・供給網を分けて対策する。 | F47: 二境界Threat Model | G47: R13, R08, R06 | H47: R13 | I47: 攻撃経路、制御、テスト、残存リスクを対応付け。 | J47: 全 | K47: 共通 | L47: 共通 | M47: 共通 | N47: G2 | O47: B1-10,B1-14,B2-03 | P47: S043,S044,S078,S099 | Q47: ADR・脅威・テストの骨子を生成。人が権限・送信・方式・復旧を設計承認。 | R47: P2-13,P3-06 | S47: 添付提案の具体化／旧版再編 | T47: U01,W11,W12,W13 | U47: https://csrc.nist.gov/pubs/sp/800/218/a/final https://genai.owasp.org/resource/a-practical-guide-for-secure-mcp-server-development/ https://genai.owasp.org/resource/agent-control-standard-acs/
A48: B2-08 | B48: 設計 | C48: UX設計 | D48: 安全な対話・根拠提示・人への移管 | E48: 根拠、更新日、不明・保留、取消、承認対象の見やすさ、誤操作防止を設計する。利用者の監督責任を過大にしない。 | F48: UXプロトタイプ | G48: R05, R04, R17 | H48: R02 | I48: 通常・失敗・拒否・人手対応を利用者確認済。 | J48: 全 | K48: 共通 | L48: 共通 | M48: 共通 | N48: G2 | O48: B1-09,B2-06 | P48: S032,S095,S096 | Q48: ADR・脅威・テストの骨子を生成。人が権限・送信・方式・復旧を設計承認。 | R48: P3-05 | S48: 添付提案の具体化／旧版再編 | T48: U01
A49: B2-09 | B49: 設計 | C49: サービス設計 | D49: API・認証・テナント分離 | E49: 認証認可、スキーマ、レート制限、冪等性、課金ID、テナント境界を設計する。LLMの指示に権限判定を任せない。 | F49: API仕様・権限設計 | G49: R07, R06, R13 | H49: R06 | I49: 境界と不正アクセス・再試行時の期待挙動が明確。 | J49: 全 | K49: 共通 | L49: 共通 | M49: 共通 | N49: G2 | O49: B2-01,B2-07 | P49: S037,S039,S091 | Q49: ADR・脅威・テストの骨子を生成。人が権限・送信・方式・復旧を設計承認。 | R49: P3-09,P3-12 | S49: 添付提案の具体化／旧版再編 | T49: U01
A50: B2-10 | B50: 設計 | C50: 評価設計 | D50: Eval Harness・凍結セットの設計 | E50: 要件ID、母集団、slice、判定器、人手較正を結び、開発用と非公開の最終評価を分離する。Agentが最終評価を編集・閲覧できないようにする。 | F50: 評価基盤設計・権限 | G50: R11, R08, R13 | H50: R19 | I50: 対象版、反復、採点規則、独立権限が定義済。 | J50: 全 | K50: 共通 | L50: 共通 | M50: 共通 | N50: G2 | O50: B1-07,B2-07 | P50: S059,S070,S077 | Q50: ADR・脅威・テストの骨子を生成。人が権限・送信・方式・復旧を設計承認。 | R50: P2-21,P2-12 | S50: 添付提案の具体化／旧版再編 | T50: U01,W05 | U50: https://www.anthropic.com/engineering/demystifying-evals-for-ai-agents
A51: B2-11 | B51: 設計 | C51: 開発ハーネス | D51: Repo正本・仕様・機械的制約 | E51: 短い指示ファイルから仕様、ADR、テストへ到達できる構造を設計する。禁止依存や構造ルールはlint/CIで検査する。 | F51: Repo標準・構造テスト | G51: R06, R07, R11 | H51: R06 | I51: 正本、鮮度責任者、テストコマンドが一意。 | J51: 全 | K51: 共通 | L51: 共通 | M51: 共通 | N51: G2 | O51: B1-14,B2-10 | P51: S076,S098,S100 | Q51: ADR・脅威・テストの骨子を生成。人が権限・送信・方式・復旧を設計承認。 | R51: P1-23,P2-21 | S51: 添付提案の具体化／旧版再編 | T51: U01,W06,W09 | U51: https://openai.com/index/harness-engineering/ https://www.anthropic.com/engineering/effective-harnesses-for-long-running-agents
A52: B2-12 | B52: 設計 | C52: Agent Skills | D52: 再利用Skillの仕様・審査設計 | E52: 人の習熟度辞書と、Agentの手順パッケージを区別する。Skillのトリガー、入出力、依存、Owner、版、回帰試験、廃止を定義する。 | F52: Skill台帳・審査基準 | G52: R06, R08, R13 | H52: R06 | I52: 第三者Skillのコード・権限・ライセンス審査がある。 | J52: 条件:開発AI・Skill | K52: 条件 | L52: 条件 | M52: 条件 | N52: G2 | O52: B2-11,B2-07 | P52: S015,S097,S078 | Q52: ADR・脅威・テストの骨子を生成。人が権限・送信・方式・復旧を設計承認。 | S52: 添付提案の具体化／旧版再編 | T52: U01,W14 | U52: https://agentskills.io/specification
A53: B2-13 | B53: 設計 | C53: 実行環境 | D53: Sandbox・worktree・秘密情報境界 | E53: タスク単位に作業領域とIDを分離し、通信・ツール・コマンド・リソースを制限する。実行環境の制御を自然言語指示で代替しない。 | F53: 隔離環境・権限Policy | G53: R12, R13, R07 | H53: R13 | I53: 許可/拒否、資格情報失効、エグレス制御を試験可能。 | J53: 条件:開発AI・Agent | K53: 条件 | L53: 条件 | M53: 条件 | N53: G2 | O53: B2-07,B2-11 | P53: S033,S078,S099 | Q53: ADR・脅威・テストの骨子を生成。人が権限・送信・方式・復旧を設計承認。 | R53: P2-02 | S53: 添付提案の具体化／旧版再編 | T53: U01,W06,W12 | U53: https://openai.com/index/harness-engineering/ https://genai.owasp.org/resource/a-practical-guide-for-secure-mcp-server-development/
A54: B2-14 | B54: 設計 | C54: 開発ループ | D54: 有界ループ・再開・並列の設計 | E54: 仕様→計画→実装→機械検証→レビューを時間・回数・費用上限内で反復する。状態保存、再開検証、作業所有権、統合責任を定める。 | F54: Loop契約・handoff仕様 | G54: R06, R07, R08 | H54: R06 | I54: 停止・承認・チェックポイント・競合処理がある。 | J54: 条件:開発AI・Agent | K54: 条件 | L54: 条件 | M54: 条件 | N54: G2 | O54: B2-11,B2-13 | P54: S028,S100,S101 | Q54: ADR・脅威・テストの骨子を生成。人が権限・送信・方式・復旧を設計承認。 | S54: 添付提案の具体化／旧版再編 | T54: U01,W04,W09 | U54: https://www.anthropic.com/engineering/building-effective-agents https://www.anthropic.com/engineering/effective-harnesses-for-long-running-agents
A55: B2-15 | B55: 設計 | C55: 運用設計 | D55: 観測・監査・プライバシー | E55: モデル、prompt、tool、data、権限、結果を追跡し、機密や不要な思考過程を収集しない。ログの保存、マスキング、アクセス制御を設計する。 | F55: Observability・監査設計 | G55: R12, R13, R10 | H55: R18 | I55: 原因追跡可能性とログ最小化を両立。 | J55: 全 | K55: 共通 | L55: 共通 | M55: 共通 | N55: G2 | O55: B2-03,B2-09 | P55: S041,S045,S050 | Q55: ADR・脅威・テストの骨子を生成。人が権限・送信・方式・復旧を設計承認。 | R55: P3-14,P3-21 | S55: 添付提案の具体化／旧版再編 | T55: U01,W13 | U55: https://genai.owasp.org/resource/agent-control-standard-acs/
A56: B2-16 | B56: 設計 | C56: 復旧設計 | D56: 構成一式のrollback・縮退 | E56: モデルだけでなくprompt、索引、ツール、権限、スキーマの互換を含め復旧する。外部副作用は補償手順と再実行制御を持つ。 | F56: 復旧・縮退Runbook設計 | G56: R12, R08, R07 | H56: R18 | I56: 停止・手動移管・復旧の安全条件がある。 | J56: 全 | K56: 共通 | L56: 共通 | M56: 共通 | N56: G2 | O56: B2-06,B2-09,B2-15 | P56: S039,S048,S080 | Q56: ADR・脅威・テストの骨子を生成。人が権限・送信・方式・復旧を設計承認。 | R56: P3-25 | S56: 添付提案の具体化／旧版再編 | T56: U01
A57: B2-17 | B57: 設計 | C57: 費用設計 | D57: 予算制御・メータリング・成功原価 | E57: retry、検索、保存、評価、人の介入を含むcost/successを計測する。上限超過時の経路、顧客別制限、課金照合を定義する。 | F57: FinOps・利用量設計 | G57: R15, R08, R12 | H57: R01 | I57: AI成功率低下・過剰利用・価格変更を評価可能。 | J57: 全 | K57: 共通 | L57: 共通 | M57: 共通 | N57: G2 | O57: B1-12,B1-18,B2-02 | P57: S050,S091,S093 | Q57: ADR・脅威・テストの骨子を生成。人が権限・送信・方式・復旧を設計承認。 | R57: P4-09 | S57: 添付提案の具体化／旧版再編 | T57: U01,W08 | U57: https://dora.dev/ai/roi/calculator/
A58: B2-18 | B58: 設計 | C58: 供給・公開設計 | D58: 依存契約・公開・切替計画 | E58: ベンダー受入と製品公開を分離し、モデルEOL、DPA、SLA、署名・部品表、段階公開、顧客通知を計画する。 | F58: 依存・リリース計画 | G58: R20, R14, R18 | H58: R18 | I58: 必要な契約と移行、公開条件、通知対象がある。 | J58: 全 | K58: 共通 | L58: 共通 | M58: 共通 | N58: G2 | O58: B1-13,B2-16 | P58: S014,S048,S094,S105 | Q58: ADR・脅威・テストの骨子を生成。人が権限・送信・方式・復旧を設計承認。 | R58: P2-20,P3-26 | S58: 添付提案の具体化／旧版再編 | T58: U01
A59: B2-19 | B59: 設計 | C59: 設計レビュー | D59: 非機能・安全・採算・実現性レビュー | E59: 代表的な縦切りケースと失敗ケースを設計で追跡し、評価可能性と運用負荷を確認する。残存不確実性は実験へ戻す。 | F59: 設計レビュー・残件 | G59: R06, R11, R13, R15 | H59: R06 | I59: 重大未対策がなく、残件にOwner・期限がある。 | J59: 全 | K59: 共通 | L59: 共通 | M59: 共通 | N59: G2 | O59: B2-10,B2-15,B2-16,B2-17 | P59: S030,S043,S081 | Q59: ADR・脅威・テストの骨子を生成。人が権限・送信・方式・復旧を設計承認。 | R59: P3-01 | S59: 添付提案の具体化／旧版再編 | T59: U01
A60: B2-20 | B60: 設計 | C60: G2 | D60: Architecture/Build承認 | E60: 構成、データ・外部送信、評価、実行権限、運用、次の投資枠を承認する。契約と法的許可の未完了を投資承認で代替しない。 | F60: G2判断記録 | G60: R03, R06 | H60: R01 | I60: 実装範囲、品質条件、権限、予算が承認済。 | J60: 全 | K60: 共通 | L60: 共通 | M60: 共通 | N60: G2 | O60: B2-19,B2-18 | P60: S001,S081,S104 | Q60: ADR・脅威・テストの骨子を生成。人が権限・送信・方式・復旧を設計承認。 | R60: P3-01,P2-20 | S60: 添付提案の具体化／旧版再編 | T60: U01
A61: B3-01 | B61: 実装 | C61: 基盤 | D61: Repo・CI・IaCの最小実装 | E61: コード、仕様、評価定義、構造制約を同じ変更フローで管理し、小さな縦切り変更からCIを動かす。 | F61: Repo・CI・IaC | G61: R07, R12 | H61: R06 | I61: 再構築とテストを新規環境で実行できる。 | J61: 全 | K61: 共通 | L61: 共通 | M61: 共通 | N61: G3 | O61: B2-20,B2-11 | P61: S027,S033,S034,S076 | Q61: 承認済みsandboxで計画→実装→テスト→修復。重要な実行・マージは権限者が確認。 | R61: P3-07,P3-20 | S61: 添付提案の具体化／旧版再編 | T61: U01,W06 | U61: https://openai.com/index/harness-engineering/
A62: B3-02 | B62: 実装 | C62: 権限実装 | D62: 開発AgentのID・Sandbox・通信制御 | E62: 短命・最小権限の資格情報、独立workspace、コマンド・ネットワークallowlist、資源上限と停止を実装する。 | F62: 開発Agent実行基盤 | G62: R12, R13 | H62: R13 | I62: 禁止操作と秘密情報アクセスを拒否する試験が通る。 | J62: 条件:開発AI | K62: 条件 | L62: 条件 | M62: 条件 | N62: G3 | O62: B3-01,B2-13 | P62: S078,S099,S100 | Q62: 承認済みsandboxで計画→実装→テスト→修復。重要な実行・マージは権限者が確認。 | R62: P1-23 | S62: 添付提案の具体化／旧版再編 | T62: U01,W12 | U62: https://genai.owasp.org/resource/a-practical-guide-for-secure-mcp-server-development/
A63: B3-03 | B63: 実装 | C63: Skill実装 | D63: Agent Skillの作成・検証・登録 | E63: SKILL.mdと必要なscripts/references/assetsを版管理し、呼出し条件、正常・異常、非呼出しを試験する。Skill宣言のみをセキュリティ境界にしない。 | F63: 審査済みSkill package | G63: R07, R08, R13 | H63: R06 | I63: Owner、版、依存、権限、実行結果、rollbackがある。 | J63: 条件:Skill | K63: 条件 | L63: 条件 | M63: 条件 | N63: G3 | O63: B3-02,B2-12 | P63: S097,S042,S078 | Q63: 承認済みsandboxで計画→実装→テスト→修復。重要な実行・マージは権限者が確認。 | S63: 添付提案の具体化／旧版再編 | T63: U01,W14 | U63: https://agentskills.io/specification
A64: B3-04 | B64: 実装 | C64: ループ実装 | D64: 計画・実装・検証・修復ループ | E64: タスクを限定して計画を承認し、コード変更後に機械テストと自己レビューを実行する。回数・時間・費用・同一失敗で停止し人に戻す。 | F64: Loop設定・実行証跡 | G64: R07, R08 | H64: R06 | I64: 成功申告ではなくテスト結果で完了を判定。 | J64: 条件:開発AI | K64: 条件 | L64: 条件 | M64: 条件 | N64: G3 | O64: B3-02,B2-14 | P64: S028,S100,S101 | Q64: 承認済みsandboxで計画→実装→テスト→修復。重要な実行・マージは権限者が確認。 | R64: P2-10 | S64: 添付提案の具体化／旧版再編 | T64: U01,W04,W09 | U64: https://www.anthropic.com/engineering/building-effective-agents https://www.anthropic.com/engineering/effective-harnesses-for-long-running-agents
A65: B3-05 | B65: 実装 | C65: 並列開発 | D65: 分割・worktree・handoff・統合 | E65: 並列化は独立タスクに限り、ファイル所有、契約テスト、共有資源制限、統合責任を定める。並列数と人のactive timeを記録する。 | F65: 分割計画・統合ログ | G65: R03, R07 | H65: R06 | I65: 競合・重複実行・取りこぼしを統合テストで確認。 | J65: 条件:並列Agent | K65: 条件 | L65: 条件 | M65: 条件 | N65: G3 | O65: B3-04 | P65: S016,S101,S079 | Q65: 承認済みsandboxで計画→実装→テスト→修復。重要な実行・マージは権限者が確認。 | S65: 添付提案の具体化／旧版再編 | T65: U01,W09 | U65: https://www.anthropic.com/engineering/effective-harnesses-for-long-running-agents
A66: B3-06 | B66: 実装 | C66: データ | D66: 承認済みデータの取得・品質処理 | E66: 利用承認後に最小データを取得し、品質、出所、加工、schema、削除条件を検査する。例外は隔離し、本番へ流さない。 | F66: データ取込・品質Pipeline | G66: R09, R10 | H66: R10 | I66: 権利・品質検査・lineage・取込記録がある。 | J66: 全 | K66: 共通 | L66: 共通 | M66: 共通 | N66: G3 | O66: B3-01,B1-04,B2-03 | P66: S024,S025,S055,S056 | Q66: 承認済みsandboxで計画→実装→テスト→修復。重要な実行・マージは権限者が確認。 | R66: P2-03,P2-04,P2-06 | S66: 添付提案の具体化／旧版再編 | T66: U01
A67: B3-07 | B67: 実装 | C67: 評価データ | D67: 開発・回帰・凍結評価セットの実装 | E67: 分割プロトコルを適用し、ラベルと判定基準を較正する。最終評価は実装Agentと開発者の調整用データから隔離する。 | F67: 版付き評価セット | G67: R11, R04, R09 | H67: R19 | I67: 重複・リーク確認、版、権限、ラベル一致度がある。 | J67: 全 | K67: 共通 | L67: 共通 | M67: 共通 | N67: G3 | O67: B3-06,B2-10 | P67: S057,S058,S059,S077 | Q67: 承認済みsandboxで計画→実装→テスト→修復。重要な実行・マージは権限者が確認。 | R67: P2-05,P2-07 | S67: 添付提案の具体化／旧版再編 | T67: U01,W05 | U67: https://www.anthropic.com/engineering/demystifying-evals-for-ai-agents
A68: B3-08 | B68: 実装 | C68: RAG | D68: 検索・引用・ACL・更新の実装 | E68: データ権限を検索前後で保証し、引用、鮮度、欠落時の保留、文書更新・削除の反映を実装する。 | F68: RAG機能・更新テスト | G68: R08, R09, R07 | H68: R06 | I68: 権限外参照と削除済み情報の再出現を試験。 | J68: 条件:RAG | K68: 条件 | L68: 条件 | M68: 条件 | N68: G3 | O68: B3-06,B2-04 | P68: S061,S037,S056 | Q68: 承認済みsandboxで計画→実装→テスト→修復。重要な実行・マージは権限者が確認。 | R68: P2-08,P3-10 | S68: 添付提案の具体化／旧版再編 | T68: U01
A69: B3-09 | B69: 実装 | C69: 学習 | D69: 特徴量・学習・比較実験 | E69: 権利確認済みデータで再現可能な学習を実行する。学習・推論費用、seed/環境、バイアス、比較結果を記録する。 | F69: 学習実験・モデル候補 | G69: R08, R09 | H69: R06 | I69: 独立セット未使用、比較・停止条件を満たす。 | J69: 条件:学習 | K69: 条件 | L69: 条件 | M69: 条件 | N69: G3 | O69: B3-06,B3-07,B2-05 | P69: S060,S063,S066 | Q69: 承認済みsandboxで計画→実装→テスト→修復。重要な実行・マージは権限者が確認。 | R69: P2-08,P2-10,P3-10 | S69: 添付提案の具体化／旧版再編 | T69: U01
A70: B3-10 | B70: 実装 | C70: AI統合 | D70: prompt・構造化出力・モデル統合 | E70: prompt、schema、モデル版、温度等の設定を管理し、タイムアウト・異常出力・根拠不足を処理する。 | F70: AI機能・構成manifest | G70: R08, R07 | H70: R06 | I70: 正常・拒否・不正形式・障害の挙動が試験済。 | J70: 全 | K70: 共通 | L70: 共通 | M70: 共通 | N70: G3 | O70: B3-01,B2-02 | P70: S035,S038,S064 | Q70: 承認済みsandboxで計画→実装→テスト→修復。重要な実行・マージは権限者が確認。 | R70: P3-10,P3-11 | S70: 添付提案の具体化／旧版再編 | T70: U01
A71: B3-11 | B71: 実装 | C71: Agent | D71: Tool/MCP・権限・副作用制御 | E71: ツールごとの認可とパラメータ検証、承認、冪等性、期限、取り消し、回数制限を実装する。LLMが直接権限を付与しない。 | F71: Agent runtime・Tool実装 | G71: R08, R07, R13 | H71: R13 | I71: 権限逸脱・二重実行・承認回避を阻止する。 | J71: 条件:Agent | K71: 条件 | L71: 条件 | M71: 条件 | N71: G3 | O71: B3-10,B2-06,B2-07 | P71: S065,S037,S099 | Q71: 承認済みsandboxで計画→実装→テスト→修復。重要な実行・マージは権限者が確認。 | R71: P3-10,P3-12 | S71: 添付提案の具体化／旧版再編 | T71: U01,W12,W13 | U71: https://genai.owasp.org/resource/a-practical-guide-for-secure-mcp-server-development/ https://genai.owasp.org/resource/agent-control-standard-acs/
A72: B3-12 | B72: 実装 | C72: アプリ | D72: API・業務ロジック・認証の実装 | E72: DB・API・業務ロジックを実装し、AI結果を未検証入力として扱う。認可、出力検証、監査ID、エラー処理を実装する。 | F72: Backend・統合API | G72: R07 | H72: R06 | I72: 重要業務操作とテナント境界の試験が通る。 | J72: 全 | K72: 共通 | L72: 共通 | M72: 共通 | N72: G3 | O72: B3-10,B2-09 | P72: S037,S039,S042 | Q72: 承認済みsandboxで計画→実装→テスト→修復。重要な実行・マージは権限者が確認。 | R72: P3-09,P3-12,P3-08 | S72: 添付提案の具体化／旧版再編 | T72: U01
A73: B3-13 | B73: 実装 | C73: UX | D73: UI・承認・説明・アクセシビリティ | E73: 根拠、AI利用表示、不確実性、取消、人への移管を実装し、支援技術を含む主要ユーザーフローを確認する。 | F73: Frontend・UX証拠 | G73: R07, R05 | H73: R02 | I73: 誤操作防止と利用者理解を確認できる。 | J73: 全 | K73: 共通 | L73: 共通 | M73: 共通 | N73: G3 | O73: B3-12,B2-08 | P73: S040,S032,S096 | Q73: 承認済みsandboxで計画→実装→テスト→修復。重要な実行・マージは権限者が確認。 | R73: P3-13 | S73: 添付提案の具体化／旧版再編 | T73: U01
A74: B3-14 | B74: 実装 | C74: 収益 | D74: 課金・利用制限・返金の実装 | E74: 成功/失敗課金条件、利用メーター、二重請求防止、予算上限、返金・取消、料金表示を実装する。 | F74: 課金・メータリング | G74: R07, R15 | H74: R01 | I74: 請求と実利用が照合され過大請求が検出可能。 | J74: 条件:外販・課金 | K74: 条件 | L74: 条件 | M74: 条件 | N74: G3 | O74: B3-12,B2-17 | P74: S091,S093,S037 | Q74: 承認済みsandboxで計画→実装→テスト→修復。重要な実行・マージは権限者が確認。 | S74: 添付提案の具体化／旧版再編 | T74: U01
A75: B3-15 | B75: 実装 | C75: 観測 | D75: trace・監査・品質・原価の計測実装 | E75: 実行IDからモデル/prompt/data/tool/権限へ追跡する。秘匿化、アクセス、保持・削除を適用し品質と費用を観測する。 | F75: Dashboard・監査ログ | G75: R12, R07, R08 | H75: R18 | I75: 必要な版と判断経路を再構成でき、秘密を漏らさない。 | J75: 全 | K75: 共通 | L75: 共通 | M75: 共通 | N75: G3 | O75: B3-12,B2-15 | P75: S041,S045,S050 | Q75: 承認済みsandboxで計画→実装→テスト→修復。重要な実行・マージは権限者が確認。 | R75: P3-14,P3-21 | S75: 添付提案の具体化／旧版再編 | T75: U01,W13 | U75: https://genai.owasp.org/resource/agent-control-standard-acs/
A76: B3-16 | B76: 実装 | C76: 自動品質 | D76: 単体・結合・契約・構造テスト | E76: 生成テストだけを正解とせず、要件と失敗パターンに基づくテストを人が確認する。依存・型・schema違反をCIで止める。 | F76: CI Test Suite | G76: R07, R11 | H76: R06 | I76: 主要要件のテスト対応と失敗検知を確認。 | J76: 全 | K76: 共通 | L76: 共通 | M76: 共通 | N76: G3 | O76: B3-12,B3-13 | P76: S042,S072,S076 | Q76: 承認済みsandboxで計画→実装→テスト→修復。重要な実行・マージは権限者が確認。 | R76: P3-15 | S76: 添付提案の具体化／旧版再編 | T76: U01,W06 | U76: https://openai.com/index/harness-engineering/
A77: B3-17 | B77: 実装 | C77: 継続評価 | D77: 回帰・adversarial・grader較正 | E77: 変更ごとに業務・安全・コストの回帰を実行し、採点AIを人手判定と較正する。失敗ケースの追加は評価セットの用途を区別する。 | F77: Continuous Eval結果 | G77: R11, R08 | H77: R19 | I77: 評価対象版、採点版、回帰差分と限界を記録。 | J77: 全 | K77: 共通 | L77: 共通 | M77: 共通 | N77: G3 | O77: B3-07,B3-10,B3-16 | P77: S068,S070,S072,S077 | Q77: 承認済みsandboxで計画→実装→テスト→修復。重要な実行・マージは権限者が確認。 | R77: P2-11,P2-21,P3-16 | S77: 添付提案の具体化／旧版再編 | T77: U01,W05 | U77: https://www.anthropic.com/engineering/demystifying-evals-for-ai-agents
A78: B3-18 | B78: 実装 | C78: レビュー | D78: 独立レビュー・供給網・機密検査 | E78: 別Agentレビューだけを独立品質承認としない。秘密・脆弱性・ライセンス・設計逸脱を機械と人で検査。外注成果物はR20が契約受入を別記録し、G3と混同しない。 | F78: PR承認・部品表・診断・外注受入証拠 | G78: R07, R11, R13, R20 | H78: R06 | I78: 生成者以外の確認と高影響差分の人の承認がある。 | J78: 全 | K78: 共通 | L78: 共通 | M78: 共通 | N78: G3 | O78: B3-16,B3-17 | P78: S015,S042,S078,S014,S105 | Q78: 承認済みsandboxで計画→実装→テスト→修復。重要な実行・マージは権限者が確認。 | R78: P3-18 | S78: 添付提案の具体化／旧版再編 | T78: U01,W11 | U78: https://csrc.nist.gov/pubs/sp/800/218/a/final
A79: B3-19 | B79: 実装 | C79: 復旧実装 | D79: rollback・停止・削除の実装 | E79: 構成manifest、feature flag、バックアップ、restore、資格情報失効、データ削除を実装し試験する。 | F79: 復旧・停止・削除機能 | G79: R12, R09, R13 | H79: R18 | I79: 実環境相当で復旧と停止を実証。 | J79: 全 | K79: 共通 | L79: 共通 | M79: 共通 | N79: G3 | O79: B3-15,B2-16 | P79: S036,S048,S080,S103 | Q79: 承認済みsandboxで計画→実装→テスト→修復。重要な実行・マージは権限者が確認。 | R79: P3-25 | S79: 添付提案の具体化／旧版再編 | T79: U01
A80: B3-20 | B80: 実装 | C80: 提供準備 | D80: 利用者資料・CS・GTM実装 | E80: 機能・限界、オンボーディング、価格・利用条件、ヘルプ、問い合わせ・事故窓口を用意する。営業資料の未実証主張を排除する。 | F80: 公開・導入・支援資料 | G80: R16, R17, R05 | H80: R02 | I80: 製品挙動と表示、サポート回答が一致。 | J80: 全 | K80: 共通 | L80: 共通 | M80: 共通 | N80: G3 | O80: B3-13,B1-11 | P80: S022,S051,S085,S089 | Q80: 承認済みsandboxで計画→実装→テスト→修復。重要な実行・マージは権限者が確認。 | R80: P3-23,P3-24 | S80: 添付提案の具体化／旧版再編 | T80: U01
A81: B3-21 | B81: 実装 | C81: 資産化 | D81: 実行知見を仕様・Skillへ還流 | E81: 再発した失敗の原因を制約、テスト、Runbook、Skillへ反映する。各資産の所有者・期限・版を付け、陳腐化を検知する。 | F81: 更新済み正本・Skill | G81: R06, R08, R11 | H81: R06 | I81: 改善の根拠と回帰試験が紐付き、重複指示を整理。 | J81: 全 | K81: 共通 | L81: 共通 | M81: 共通 | N81: G3 | O81: B3-17,B3-18 | P81: S051,S076,S097,S098 | Q81: 承認済みsandboxで計画→実装→テスト→修復。重要な実行・マージは権限者が確認。 | R81: P4-21 | S81: 添付提案の具体化／旧版再編 | T81: U01,W06,W09 | U81: https://openai.com/index/harness-engineering/ https://www.anthropic.com/engineering/effective-harnesses-for-long-running-agents
A82: B3-22 | B82: 実装 | C82: 効果測定 | D82: 人時間・レビュー・手戻り・費用測定 | E82: 同等品質・スコープの作業を比較し、Harness準備、レビュー、検証、手戻り、事故、並列の経過時間を分ける。 | F82: AI効果測定記録 | G82: R03, R15, R11 | H82: R06 | I82: 品質条件と比較妥当性を明示し、未測定を0にしない。 | J82: 条件:開発AI | K82: 条件 | L82: 条件 | M82: 条件 | N82: G3 | O82: B3-04,B1-18 | P82: S079,S052,S093 | Q82: 承認済みsandboxで計画→実装→テスト→修復。重要な実行・マージは権限者が確認。 | R82: P1-17,P4-19 | S82: 添付提案の具体化／旧版再編 | T82: U01,W07,W08 | U82: https://metr.org/blog/2026-02-24-uplift-update/ https://dora.dev/ai/roi/calculator/
A83: B3-23 | B83: 実装 | C83: RC作成 | D83: 変更固定・RC manifestの作成 | E83: コード、model、prompt、data/index、tool、権限、評価設定を固定し、独立評価に渡す。以降の変更は影響評価と再評価を行う。 | F83: Release Candidate manifest | G83: R06, R12 | H83: R06 | I83: 評価対象を特定でき、未解決事項と再評価条件がある。 | J83: 全 | K83: 共通 | L83: 共通 | M83: 共通 | N83: G3 | O83: B3-18,B3-19,B3-20 | P83: S027,S048,S080,S075 | Q83: 承認済みsandboxで計画→実装→テスト→修復。重要な実行・マージは権限者が確認。 | R83: P3-24 | S83: 添付提案の具体化／旧版再編 | T83: U01
A84: B4-01 | B84: 評価 | C84: 独立評価 | D84: 評価環境・対象版・アクセスの確認 | E84: RCと凍結評価を独立担当が確認し、事前に合意した判定方法で実行する。最終評価の結果を見た調整は新しい評価として管理する。 | F84: 独立評価開始記録 | G84: R11 | H84: R19 | I84: 対象hash、データ・grader版、閲覧権限が一致。 | J84: 全 | K84: 共通 | L84: 共通 | M84: 共通 | N84: G3 | O84: B3-23,B3-07 | P84: S057,S070,S077 | Q84: 回帰・攻撃ケース・集計を支援。凍結評価隔離と人の独立合否を維持。 | R84: P2-12 | S84: 添付提案の具体化／旧版再編 | T84: U01,W05 | U84: https://www.anthropic.com/engineering/demystifying-evals-for-ai-agents
A85: B4-02 | B85: 評価 | C85: 性能 | D85: 業務・AI性能・重要slice評価 | E85: 非AIベースラインと比較し、成功率、誤りコスト、重要slice、信頼区間・反復変動を記録する。平均点だけで公開しない。 | F85: 業務・AI性能評価 | G85: R11, R04, R08 | H85: R19 | I85: 事前閾値、分母、失敗事例、限界を明記。 | J85: 全 | K85: 共通 | L85: 共通 | M85: 共通 | N85: G3 | O85: B4-01 | P85: S052,S067,S068,S069 | Q85: 回帰・攻撃ケース・集計を支援。凍結評価隔離と人の独立合否を維持。 | R85: P2-11,P2-12 | S85: 添付提案の具体化／旧版再編 | T85: U01
A86: B4-03 | B86: 評価 | C86: 検索品質 | D86: RAG検索・引用・鮮度・削除評価 | E86: 検索と回答を分けて測定し、根拠整合、誤引用、権限外文書、文書更新、削除反映を評価する。 | F86: RAG評価結果 | G86: R11, R09 | H86: R19 | I86: 主要sliceとACL・鮮度・削除試験が合格。 | J86: 条件:RAG | K86: 条件 | L86: 条件 | M86: 条件 | N86: G3 | O86: B4-01,B3-08 | P86: S061,S070,S072 | Q86: 回帰・攻撃ケース・集計を支援。凍結評価隔離と人の独立合否を維持。 | R86: P3-16 | S86: 添付提案の具体化／旧版再編 | T86: U01
A87: B4-04 | B87: 評価 | C87: 行動品質 | D87: Agent完了・副作用・停止の評価 | E87: 最終成果と状態変化を検証し、権限、承認、二重実行、再開、予算超過、ツール障害を評価する。 | F87: Agent trajectory評価 | G87: R11, R13, R04 | H87: R19 | I87: 成果物の実状態と危険行動・停止を検証。 | J87: 条件:Agent | K87: 条件 | L87: 条件 | M87: 条件 | N87: G3 | O87: B4-01,B3-11 | P87: S065,S070,S099 | Q87: 回帰・攻撃ケース・集計を支援。凍結評価隔離と人の独立合否を維持。 | R87: P3-16 | S87: 添付提案の具体化／旧版再編 | T87: U01,W05,W12 | U87: https://www.anthropic.com/engineering/demystifying-evals-for-ai-agents https://genai.owasp.org/resource/a-practical-guide-for-secure-mcp-server-development/
A88: B4-05 | B88: 評価 | C88: 安全性 | D88: 安全・公平性・誤信頼・透明性 | E88: 用途の危害を基に重大失敗、属性/言語等の重要slice、根拠・限界表示を確認する。0件観測をリスク0とは扱わない。 | F88: Responsible AI評価 | G88: R11, R04, R05 | H88: R19 | I88: 危害とサンプル限界、未解決リスクが明記。 | J88: 全 | K88: 共通 | L88: 共通 | M88: 共通 | N88: G3 | O88: B4-01 | P88: S071,S072,S095 | Q88: 回帰・攻撃ケース・集計を支援。凍結評価隔離と人の独立合否を維持。 | R88: P2-16,P3-17 | S88: 添付提案の具体化／旧版再編 | T88: U01,W10 | U88: https://www.nist.gov/publications/artificial-intelligence-risk-management-framework-generative-artificial-intelligence
A89: B4-06 | B89: 評価 | C89: Security | D89: 二境界の攻撃・漏洩・供給網試験 | E89: 製品AIと開発Agent双方に対し、注入、Tool改ざん、機密取得、権限回避、外部送信を許可された試験環境で確認する。 | F89: Security・Red Team報告 | G89: R13, R11 | H89: R13 | I89: 重大権限逸脱・秘密漏洩が未解決なら公開停止。 | J89: 全 | K89: 共通 | L89: 共通 | M89: 共通 | N89: G3 | O89: B4-01,B2-07,B3-18 | P89: S043,S044,S078 | Q89: 回帰・攻撃ケース・集計を支援。凍結評価隔離と人の独立合否を維持。 | R89: P3-18 | S89: 添付提案の具体化／旧版再編 | T89: U01,W11,W12,W13 | U89: https://csrc.nist.gov/pubs/sp/800/218/a/final https://genai.owasp.org/resource/a-practical-guide-for-secure-mcp-server-development/ https://genai.owasp.org/resource/agent-control-standard-acs/
A90: B4-07 | B90: 評価 | C90: Privacy | D90: 実データフロー・削除・規約整合確認 | E90: 設定と契約・表示が一致するか、ログ、評価、サブプロセサ、国外処理、削除・保持、利用者権利を実際の経路で確認する。 | F90: Privacy Gate最終確認 | G90: R14, R10, R13 | H90: R14 | I90: 未承認送信・用途外利用がなく証拠がある。 | J90: 全 | K90: 共通 | L90: 共通 | M90: 共通 | N90: G3 | O90: B4-01,B1-04,B3-19 | P90: S003,S015,S094 | Q90: 回帰・攻撃ケース・集計を支援。凍結評価隔離と人の独立合否を維持。 | R90: P3-14,P3-18 | S90: 添付提案の具体化／旧版再編 | T90: U01,W02,W03 | U90: https://www.ppc.go.jp/personalinfo/legal/guidelines_anonymous/ https://www.ppc.go.jp/personalinfo/legal/guidelines_offshore/
A91: B4-08 | B91: 評価 | C91: 信頼性 | D91: 負荷・障害・再試行・費用評価 | E91: ピーク、遅延、Provider障害、レート制限、繰り返し呼出し、容量枯渇を検証し、SLOと原価上限を確認する。 | F91: 負荷・障害・費用報告 | G91: R12, R11, R15 | H91: R18 | I91: SLO、cost/success、縮退の合否と観測条件がある。 | J91: 全 | K91: 共通 | L91: 共通 | M91: 共通 | N91: G3 | O91: B4-01,B3-15 | P91: S023,S029,S045,S050 | Q91: 回帰・攻撃ケース・集計を支援。凍結評価隔離と人の独立合否を維持。 | R91: P3-19 | S91: 添付提案の具体化／旧版再編 | T91: U01
A92: B4-09 | B92: 評価 | C92: UX | D92: 利用者タスク・アクセシビリティ評価 | E92: 代表ユーザーで完了率、理解、過信、承認負担、手動移管を検証する。社内デモの好評だけを成功としない。 | F92: ユーザー受入・UX評価 | G92: R05, R11, R04 | H92: R02 | I92: 重要な業務フローと例外を利用者が遂行できる。 | J92: 全 | K92: 共通 | L92: 共通 | M92: 共通 | N92: G3 | O92: B4-01,B3-13 | P92: S021,S095,S096 | Q92: 回帰・攻撃ケース・集計を支援。凍結評価隔離と人の独立合否を維持。 | R92: P2-14,P3-19 | S92: 添付提案の具体化／旧版再編 | T92: U01
A93: B4-10 | B93: 評価 | C93: 採算 | D93: 価格・課金・単位経済性の検証 | E93: 請求照合、成功単位原価、CS負荷、無料枠の悪用、粗利のシナリオを評価する。利益とキャッシュ、余力を分離する。 | F93: 採算・課金評価 | G93: R15, R11, R16 | H93: R01 | I93: 決済・返金・原価計算と継続投資条件を確認。 | J93: 全 | K93: 共通 | L93: 共通 | M93: 共通 | N93: G3 | O93: B4-08,B3-14 | P93: S010,S083,S091,S093 | Q93: 回帰・攻撃ケース・集計を支援。凍結評価隔離と人の独立合否を維持。 | R93: P2-15 | S93: 添付提案の具体化／旧版再編 | T93: U01,W08 | U93: https://dora.dev/ai/roi/calculator/
A94: B4-11 | B94: 評価 | C94: 復旧 | D94: 停止・復旧・移管のリハーサル | E94: モデル・索引・Tool・スキーマの整合を含め、停止・復旧・手動代替を演習する。不可逆な外部副作用は補償手順で扱う。 | F94: 復旧演習・RTO/RPO実績 | G94: R12, R13, R17 | H94: R18 | I94: 権限者が手順で復旧でき、再実行事故を防ぐ。 | J94: 全 | K94: 共通 | L94: 共通 | M94: 共通 | N94: G3 | O94: B4-01,B3-19 | P94: S048,S049,S080 | Q94: 回帰・攻撃ケース・集計を支援。凍結評価隔離と人の独立合否を維持。 | R94: P3-25 | S94: 添付提案の具体化／旧版再編 | T94: U01
A95: B4-12 | B95: 評価 | C95: 運用準備 | D95: Service Owner・当番・CS・通知確認 | E95: 運用権限、当番、アラート、エスカレーション、顧客通知、サポート時間、費用負担を確定する。 | F95: 運用Ready Check | G95: R18, R12, R17 | H95: R18 | I95: 稼働後の責任・連絡・予算・停止条件が成立。 | J95: 全 | K95: 共通 | L95: 共通 | M95: 共通 | N95: G3 | O95: B3-20,B4-11 | P95: S046,S051,S089,S102 | Q95: 回帰・攻撃ケース・集計を支援。凍結評価隔離と人の独立合否を維持。 | R95: P3-25,P3-26 | S95: 添付提案の具体化／旧版再編 | T95: U01
A96: B4-13 | B96: 評価 | C96: 独立合否 | D96: 評価報告・残存リスク・公開勧告 | E96: 各指標、重大失敗、法務、安全、未解決事項を統合する。採点AIや実装担当だけで最終合否を確定しない。 | F96: 独立品質判定 | G96: R11, R13, R14 | H96: R19 | I96: 適用機能の必須評価を30へ列挙し、評価Run・Manifest・独立判定を照合。RAG/Agent未使用は承認済み対象外だけを許容。 | J96: 全 | K96: 共通 | L96: 共通 | M96: 共通 | N96: G3 | O96: B4-02,B4-03,B4-04,B4-05,B4-06,B4-07,B4-08,B4-09 | P96: S070,S077,S081 | Q96: 回帰・攻撃ケース・集計を支援。凍結評価隔離と人の独立合否を維持。 | R96: P2-12,P3-19 | S96: 添付提案の具体化／旧版再編 | T96: U01
A97: B4-14 | B97: 評価 | C97: G3 | D97: Release Candidate・本番公開承認 | E97: 品質・安全・法務・運用・採算・公開範囲を確認し、Service Ownerが公開可否を承認する。重大度に応じ事業責任者のリスク受容を添付する。 | F97: G3 Release判断記録 | G97: R03, R18 | H97: R18 | I97: 対象RC、独立合否、監視・停止・復旧条件を承認。 | J97: 全 | K97: 共通 | L97: 共通 | M97: 共通 | N97: G3 | O97: B4-13,B4-10,B4-12 | P97: S048,S077,S081 | Q97: 回帰・攻撃ケース・集計を支援。凍結評価隔離と人の独立合否を維持。 | R97: P3-26 | S97: 添付提案の具体化／旧版再編 | T97: U01
A98: B4-15 | B98: 評価 | C98: 段階公開 | D98: 限定公開・canary・実利用確認 | E98: 承認済み範囲にのみ展開し、露出、停止条件、比較対象、データ利用を守る。実利用で危害が見えたら速度より停止を優先する。 | F98: 限定公開・計測記録 | G98: R12, R02, R11 | H98: R18 | I98: 展開量、期間、品質・事故・原価と判断が残る。 | J98: 全 | K98: 共通 | L98: 共通 | M98: 共通 | N98: G3 | O98: B4-14 | P98: S048,S074,S087 | Q98: 回帰・攻撃ケース・集計を支援。凍結評価隔離と人の独立合否を維持。 | R98: P3-22,P4-18 | S98: 添付提案の具体化／旧版再編 | T98: U01
A99: B4-16 | B99: 評価 | C99: 市場投入 | D99: ローンチ・価格・営業・導入開始 | E99: 技術公開と営業公開を分け、利用条件、課金、導入、サポート、告知の準備を確認して販売・利用を開始する。 | F99: Launch記録 | G99: R16, R17, R02 | H99: R01 | I99: 承認された機能・価格・限界と提供実態が一致。 | J99: 全 | K99: 共通 | L99: 共通 | M99: 共通 | N99: G3 | O99: B4-15,B4-10,B4-12 | P99: S083,S085,S089,S013 | Q99: 回帰・攻撃ケース・集計を支援。凍結評価隔離と人の独立合否を維持。 | R99: P3-23 | S99: 添付提案の具体化／旧版再編 | T99: U01
A100: B4-17 | B100: 評価 | C100: 移行 | D100: 初期実績・運用移管・残件の引継ぎ | E100: 初期利用、障害、継続率、手動負荷、費用を確認し、残件と変更候補を運用バックログに移す。納品検収で責任を終了しない。 | F100: 初期レビュー・運用引継ぎ | G100: R18, R02, R03 | H100: R18 | I100: 本番Ownerと次のG4日、残件責任者が決定。 | J100: 全 | K100: 共通 | L100: 共通 | M100: 共通 | N100: G3 | O100: B4-15,B4-16 | P100: S011,S046,S089 | Q100: 回帰・攻撃ケース・集計を支援。凍結評価隔離と人の独立合否を維持。 | R100: P3-27,P4-01 | S100: 添付提案の具体化／旧版再編 | T100: U01
...

Sheet 03_AIリスクTier・適用判定
A1: AIリスクTier・機能・適用判定
A2: T0〜T3は添付案の社内管理区分。製品AIと開発Agentを別々に判断し、法令上の分類は12で管理。
A3: Tier | B3: 名称 | C3: 典型的な影響・用途 | D3: 評価・承認強度 | E3: 注意 | F3: 根拠
A4: T0 | B4: 最小 | C4: 公開情報中心・限定された社内補助・重要判断/書込みなし | D4: 実装者以外のpeer review＋回帰 | E4: 公開情報でも危害・権限によって上位へ | F4: U01
A5: T1 | B5: 通常 | C5: 顧客FAQ/RAG等。重要な判断や自律書込みなし | D5: 実装から分離したEvaluator＋Frozen Set | E5: 社内/小規模だからT0とはしない | F5: U01
A6: T2 | B6: 高 | C6: 個人情報・取引・外部書込み・金銭/契約等の影響 | D6: 独立QA/Safety、Security、Red Team、停止権 | E6: 個人情報の有無だけで法的分類と同一視しない | F6: U01
A7: T3 | B7: 重大 | C7: 生命・身体・権利の重大影響・規制業務・高度自律 | D7: 組織的独立性＋必要に応じ外部専門評価＋経営受容 | E7: 禁止用途はTierにかかわらず実施しない | F7: U01
A11: 案件判定（両境界を記入）
A12: 判定軸 | B12: 確認事項 | C12: 製品AI（入力） | D12: 開発Agent（入力） | E12: 根拠・承認URI（入力） | F12: 確認状態
A13: 対象と境界 | B13: 製品AI / 開発Agent / 評価AI / 運用Agentを区別 | F13: 未判定
A14: 危害と対象者 | B14: 生命・権利・金銭・未成年・脆弱な利用者 | F14: 未判定
A15: データ | B15: 個人情報、機密、仮名/匿名、権利、外部送信 | F15: 未判定
A16: 自律度・副作用 | B16: read-only、承認付き書込み、自律書込み、取り消し可能性 | F16: 未判定
A17: Tool/MCP・委譲 | B17: 認可範囲、chain、ID、ネットワーク、秘密 | F17: 未判定
A18: 取得・配置 | B18: 外部API、ローカルモデル、クラウド、閉域 | F18: 未判定
A19: RAG・学習 | B19: RAG、GraphRAG、追加学習、自前学習、不要な複雑性 | F19: 未判定
A20: 地域・法的役割 | B20: 提供国、利用者、処理国、AI Act等のactor role | F20: 未判定
A21: 残存リスク | B21: 重大未対策、利用禁止、例外期限、停止方法 | F21: 未判定
A22: 確定Tier・承認 | B22: 根拠、A実名、日付、見直しトリガー | F22: 未判定
A24: 機能判定：方式・配置・学習を独立に判定する（AR02/04）
A26: 機能／境界 | B26: 採用判定 | C26: 具体的な実施形態 | D26: 必須評価・能力 | E26: 判断者 | F26: 承認URI
A27: RAG | B27: 未判定 | C27: 検索拡張。API／ローカルを問わない | D27: B4-03、E03/E04、S061
A28: Agent | B28: 未判定 | C28: 外部ツール操作。read-onlyも成否を評価 | D28: B4-04、E05、S065
A29: 子Agent | B29: 未判定 | C29: 親子委譲・共有状態がある場合 | D29: 14の親子試験。単独Agentには強制しない
A30: 追加学習 | B30: 未判定 | C30: 微調整／独自学習を行う場合 | D30: データ来歴・学習／評価分離・重み処理
A31: 外部API | B31: 未判定 | C31: API型のモデル／評価／ログ送信 | D31: 認証・送信・レート・費用・切替
A32: 自己ホスト | B32: 未判定 | C32: モデルを自社管理の実行基盤で提供 | D32: 配備・容量・モデル権利・復元
A35: 外部APIのみ | B35: RAG/Agentを自動適用しない | C35: S034/S035・送信判定。機能は別途判定
A36: ローカルRAG | B36: RAG=使用、自己ホスト=使用 | C36: S061、B4-03、E03/E04は必要
A37: 追加学習 | B37: 追加学習=使用 | C37: S066等。RAGとは別の軸
A38: 書込みAgent | B38: Agent=使用、書込みを03で高影響判定 | C38: S065、B4-04/E05。小規模でも権限・復旧を省略しない

Sheet 04_規模・テーラリング
A1: 規模とテーラリング｜人数・工数は案件で較正
A2: 原稿の参考値を保存しつつ、実行予算・人数には自動転記しない。AI効果は実測後に反映する。
A3: 区分 | B3: 観点 | C3: 適用の考え方 | D3: 具体的な運用 | E3: 留保・禁止する短絡 | F3: 根拠
A4: S | B4: 参考構成 | C4: 機能1〜2、統合2〜4、外部基盤モデル中心 | D4: 文書を統合・兼務可。必要な評価独立性は残す | E4: 添付のコア4〜6FTEとロール別合計は一致しないため自動人数採用しない | F4: U01
A5: M | B5: 参考構成 | C5: 複数機能、統合5〜10、RAG/限定Agent | D5: 依存と共有基盤、QA/支援容量を明示 | E5: 個人情報や書込みは人数でなく危害により審査 | F5: U01
A6: L | B6: 参考構成 | C6: 多事業・多地域・高影響・多数統合 | D6: ポートフォリオ、チーム間依存、独立評価の仕組み | E6: 大規模事前学習の研究/GPU費は別計画 | F6: U01
A7: 全 | B7: 省略不可の原則 | C7: 責任・利用許可・安全境界・受入評価・公開判断 | D7: 不要な機能は除外可、必要な統制は代替証拠で維持 | E7: 法令や重大な品質停止条件を例外承認で無効化しない | F7: U01
A8: 全 | B8: 工程テーラリング | C8: 適用 / 対象外 / 未判定を17で記録 | D8: 理由、代替、A、日付、変更トリガーが必要 | E8: 物理構成数の合理化と安全な境界の省略は別。本番秘密・データ・権限を開発Agentから分離し、必要な独立検証・復旧試験を確保。 | F8: U01
A9: 全 | B9: 管理単位 | C9: 標準タスクは工程の枠、実行単位はIssue/Run | D9: 反復は新しいIssue・評価Run・Release版を残す | E9: 同じ評価記録を上書きして成功扱いしない | F9: U01,U03
A13: 添付原稿の参考工数（未較正・AI削減控除なし）
A14: 工程 | B14: S下限 | C14: S上限 | D14: M下限 | E14: M上限 | F14: L下限 | G14: L上限 | H14: 単位・範囲
A15: 企画 | B15: 10 | C15: 20 | D15: 25 | E15: 50 | F15: 50 | G15: 100 | H15: 人日／初期計画レンジ
A16: 要件 | B16: 15 | C16: 30 | D16: 35 | E16: 75 | F16: 80 | G16: 160 | H16: 同上
A17: 設計 | B17: 20 | C17: 45 | D17: 50 | E17: 110 | F17: 120 | G17: 250 | H17: 同上
A18: 実装 | B18: 45 | C18: 110 | D18: 140 | E18: 350 | F18: 350 | G18: 900 | H18: 同上
A19: 評価 | B19: 25 | C19: 60 | D19: 80 | E19: 180 | F19: 200 | G19: 500 | H19: 同上
A20: 運用立上げ | B20: 20 | C20: 45 | D20: 60 | E20: 140 | F20: 150 | G20: 350 | H20: 継続運用は含めない
A21: 廃止 | B21: 5 | C21: 15 | D21: 15 | E21: 40 | F21: 40 | G21: 100 | H21: 将来の一時作業。初期Buildと同一時期ではない
A22: 継続運用/月 | B22: 5 | C22: 12 | D22: 15 | E22: 40 | F22: 40 | G22: 100 | H22: L上限は原稿100+。100は上限保証ではない

Sheet 05_意思決定・RACI
A1: 意思決定・RACI｜承認Aを一意にする
A2: R=実施責任、A=最終承認、C=必須相談、I=共有。実名と代行は06、承認の実記録は29へ。
A3: 判断ID | B3: 判断対象 | C3: R | D3: A（原則1） | E3: C | F3: I | G3: 判断時点 | H3: 必要な証拠・独立性
A4: D01 | B4: 探索・事業開始/投資 | C4: R02,R03 | D4: R01 | E4: R15,R06,R14 | F4: R18,R16 | G4: G0/G1/G2 | H4: 仮説・予算・停止条件
A5: D02 | B5: AI利用・Tier | C5: R02,R08 | D5: R01 | E5: R13,R14,R11 | F5: R18,R20 | G5: G0/G1・重大変更 | H5: 用途・危害・残存リスク
A6: D03 | B6: 個人データ・外国送信 | C6: R10 | D6: R14 | E6: R13,R02 | F6: R09,R08,R20 | G6: 取得・送信より前 | H6: Data Flow・根拠・目的・条件
A7: D04 | B7: Architecture/Harness | C7: R06 | D7: R06 | E7: R08,R09,R12,R13,R11 | F7: R03,R18 | G7: G2技術勧告 | H7: 独立レビュー証跡を添付
A8: D05 | B8: 評価合否 | C8: R11 | D8: R19 | E8: R04,R13,R14 | F8: R02,R18 | G8: G3・重大変更 | H8: Frozen Eval・grader・限界
A9: D06 | B9: 本番公開・停止/復旧 | C9: R12 | D9: R18 | E9: R19,R13,R14,R02 | F9: R01,R17,R16 | G9: G3・変更公開 | H9: 品質合否・Runbook・対象版
A10: D07 | B10: 重大リスクの受容 | C10: R18 | D10: R01 | E10: R19,R13,R14 | F10: R02,R03 | G10: G3等 | H10: 不合格の上書きではない
A11: D08 | B11: 外部成果物受入 | C11: R20 | D11: R20 | E11: R06,R11,R14 | F11: R03,R18 | G11: 契約別 | H11: ここにだけ契約検収を置く
A12: D09 | B12: Scale/Continue/Pivot/Stop | C12: R02,R15 | D12: R01 | E12: R18,R19,R16 | F12: R03,R17 | G12: G4 | H12: 価値・安全・継続・採算
A13: D10 | B13: 廃止完了 | C13: R18 | D13: R01 | E13: R10,R13,R14,R19 | F13: R17,R20 | G13: G5 | H13: 削除・保全・失効・請求
A14: D11 | B14: Skill公開・権限変更 | C14: R07,R08 | D14: R06 | E14: R13,R11 | F14: R03,R12 | G14: Skill変更時 | H14: 供給網・回帰・実行Policy

Sheet 06_ロール・要員計画
A1: ロール・要員計画｜必要能力と実名・稼働を分離
A2: Roleは専任人数ではない。PersonIDで兼務を束ね、管理基準日時点の合計FTEを点検。期間全体の最大負荷は別途計画。
A3: Role ID | B3: ロール | C3: 主要責任 | D3: 関与・判断 | E3: 兼務・独立性の注意 | F3: 中核Skill | G3: 担当実名（入力） | H3: 所属（入力） | I3: 対象期間（入力） | J3: 必要FTE（入力） | K3: 割当FTE（入力） | L3: 不足FTE | M3: 代行（入力） | N3: 補充/外部活用（入力） | O3: 証拠URI（入力） | P3: PersonID | Q3: 配置開始 | R3: 配置終了 | S3: 当日合計FTE | T3: 当人の当日上限FTE | U3: 稼働点検
A4: R01 | B4: Business Owner / Executive Sponsor | C4: 事業P/L、段階投資、リスク受容、拡大・撤退 | D4: G0/G1/G2/G4/G5。G3は重大リスク受容を支援 | E4: 評価の不合格や法的禁止を事業判断で上書きしない | F4: S008,S009,S010,S081,S104 | L4: =IF(COUNT(J4:K4)<2,"",MAX(0,J4-K4)) | S4: =IF(OR(P4="",COUNT(Q4:R4)<2),"",SUMIFS($K$4:$K$23,$P$4:$P$23,P4,$Q$4:$Q$23,"<="&AsOfDate,$R$4:$R$23,">="&AsOfDate)) | T4: 1 | U4: =IF(P4="","Person未割当",IF(OR(G4="",COUNT(Q4,R4,K4,T4)<4),"配置期間・FTE不足",IF(OR(Q4>R4,K4<0,T4<0),"配置値不正",IF(S4>T4,"当日FTE超過","当日稼働記録あり")))) -> Person未割当
A5: R02 | B5: Product Manager / Product Owner | C5: 顧客課題、価値、Product Goal、優先順位、UX受入 | D5: 企画〜運用の価値と要件の責任 | E5: 納期管理のPMと区別。事業・品質の自己承認を避ける | F5: S004,S009,S020,S082,S087 | L5: =IF(COUNT(J5:K5)<2,"",MAX(0,J5-K5)) | S5: =IF(OR(P5="",COUNT(Q5:R5)<2),"",SUMIFS($K$4:$K$23,$P$4:$P$23,P5,$Q$4:$Q$23,"<="&AsOfDate,$R$4:$R$23,">="&AsOfDate)) | T5: 1 | U5: =IF(P5="","Person未割当",IF(OR(G5="",COUNT(Q5,R5,K5,T5)<4),"配置期間・FTE不足",IF(OR(Q5>R5,K5<0,T5<0),"配置値不正",IF(S5>T5,"当日FTE超過","当日稼働記録あり")))) -> Person未割当
A6: R03 | B6: Delivery PM / Project Manager | C6: 計画、依存、予算枠、進捗、変更、承認証跡 | D6: 全工程の実行調整 | E6: PdM兼務可。ただし事業仮説と実行進捗を混同しない | F6: S006,S016,S079,S106 | L6: =IF(COUNT(J6:K6)<2,"",MAX(0,J6-K6)) | S6: =IF(OR(P6="",COUNT(Q6:R6)<2),"",SUMIFS($K$4:$K$23,$P$4:$P$23,P6,$Q$4:$Q$23,"<="&AsOfDate,$R$4:$R$23,">="&AsOfDate)) | T6: 1 | U6: =IF(P6="","Person未割当",IF(OR(G6="",COUNT(Q6,R6,K6,T6)<4),"配置期間・FTE不足",IF(OR(Q6>R6,K6<0,T6<0),"配置値不正",IF(S6>T6,"当日FTE超過","当日稼働記録あり")))) -> Person未割当
A7: R04 | B7: Domain SME | C7: 業務正解、例外、誤りの被害、ラベル判断 | D7: 要件・評価・顧客業務 | E7: 実装者の期待に合わせて正解を変更しない | F7: S007,S019,S058,S071 | L7: =IF(COUNT(J7:K7)<2,"",MAX(0,J7-K7)) | S7: =IF(OR(P7="",COUNT(Q7:R7)<2),"",SUMIFS($K$4:$K$23,$P$4:$P$23,P7,$Q$4:$Q$23,"<="&AsOfDate,$R$4:$R$23,">="&AsOfDate)) | T7: 1 | U7: =IF(P7="","Person未割当",IF(OR(G7="",COUNT(Q7,R7,K7,T7)<4),"配置期間・FTE不足",IF(OR(Q7>R7,K7<0,T7<0),"配置値不正",IF(S7>T7,"当日FTE超過","当日稼働記録あり")))) -> Person未割当
A8: R05 | B8: UX Research / Product Designer | C8: 調査、Human-AI UX、利用者理解、アクセシビリティ | D8: 探索〜利用定着 | E8: ユーザー研究と営業の希望的解釈を分離 | F8: S021,S032,S082,S095,S096 | L8: =IF(COUNT(J8:K8)<2,"",MAX(0,J8-K8)) | S8: =IF(OR(P8="",COUNT(Q8:R8)<2),"",SUMIFS($K$4:$K$23,$P$4:$P$23,P8,$Q$4:$Q$23,"<="&AsOfDate,$R$4:$R$23,">="&AsOfDate)) | T8: 1 | U8: =IF(P8="","Person未割当",IF(OR(G8="",COUNT(Q8,R8,K8,T8)<4),"配置期間・FTE不足",IF(OR(Q8>R8,K8<0,T8<0),"配置値不正",IF(S8>T8,"当日FTE超過","当日稼働記録あり")))) -> Person未割当
A9: R06 | B9: Engineering Owner / Tech Lead | C9: 技術設計、実装品質、Harness、技術投資 | D9: G2技術勧告、実装と保守 | E9: 独立品質の最終判定はR19。少人数時は外部レビューを手配 | F9: S030,S034,S076,S097,S100 | L9: =IF(COUNT(J9:K9)<2,"",MAX(0,J9-K9)) | S9: =IF(OR(P9="",COUNT(Q9:R9)<2),"",SUMIFS($K$4:$K$23,$P$4:$P$23,P9,$Q$4:$Q$23,"<="&AsOfDate,$R$4:$R$23,">="&AsOfDate)) | T9: 1 | U9: =IF(P9="","Person未割当",IF(OR(G9="",COUNT(Q9,R9,K9,T9)<4),"配置期間・FTE不足",IF(OR(Q9>R9,K9<0,T9<0),"配置値不正",IF(S9>T9,"当日FTE超過","当日稼働記録あり")))) -> Person未割当
A10: R07 | B10: Application Engineer | C10: API、UI、業務ロジック、テスト、Tool実装 | D10: 設計・実装・保守 | E10: AI生成物にも通常と同じ実装責任を負う | F10: S024,S037,S039,S040,S042 | L10: =IF(COUNT(J10:K10)<2,"",MAX(0,J10-K10)) | S10: =IF(OR(P10="",COUNT(Q10:R10)<2),"",SUMIFS($K$4:$K$23,$P$4:$P$23,P10,$Q$4:$Q$23,"<="&AsOfDate,$R$4:$R$23,">="&AsOfDate)) | T10: 1 | U10: =IF(P10="","Person未割当",IF(OR(G10="",COUNT(Q10,R10,K10,T10)<4),"配置期間・FTE不足",IF(OR(Q10>R10,K10<0,T10<0),"配置値不正",IF(S10>T10,"当日FTE超過","当日稼働記録あり")))) -> Person未割当
A11: R08 | B11: AI / ML Engineer | C11: モデル選定、RAG、Agent、学習、AI評価・改善 | D11: 要件〜運用 | E11: 凍結評価セットをモデル調整に流用しない | F11: S054,S061,S064,S065,S068 | L11: =IF(COUNT(J11:K11)<2,"",MAX(0,J11-K11)) | S11: =IF(OR(P11="",COUNT(Q11:R11)<2),"",SUMIFS($K$4:$K$23,$P$4:$P$23,P11,$Q$4:$Q$23,"<="&AsOfDate,$R$4:$R$23,">="&AsOfDate)) | T11: 1 | U11: =IF(P11="","Person未割当",IF(OR(G11="",COUNT(Q11,R11,K11,T11)<4),"配置期間・FTE不足",IF(OR(Q11>R11,K11<0,T11<0),"配置値不正",IF(S11>T11,"当日FTE超過","当日稼働記録あり")))) -> Person未割当
A12: R09 | B12: Data Engineer / Steward | C12: 取得、品質、パイプライン、権限・削除伝播 | D12: 全データライフサイクル | E12: Data Ownerの利用許可を技術者判断で代替しない | F12: S025,S031,S055,S056,S080 | L12: =IF(COUNT(J12:K12)<2,"",MAX(0,J12-K12)) | S12: =IF(OR(P12="",COUNT(Q12:R12)<2),"",SUMIFS($K$4:$K$23,$P$4:$P$23,P12,$Q$4:$Q$23,"<="&AsOfDate,$R$4:$R$23,">="&AsOfDate)) | T12: 1 | U12: =IF(P12="","Person未割当",IF(OR(G12="",COUNT(Q12,R12,K12,T12)<4),"配置期間・FTE不足",IF(OR(Q12>R12,K12<0,T12<0),"配置値不正",IF(S12>T12,"当日FTE超過","当日稼働記録あり")))) -> Person未割当
A13: R10 | B13: Data Owner | C13: データ利用目的、権利、品質、保存削除責任 | D13: 取得前から廃止後保全まで | E13: 法的判断はR14。個人データ処理の根拠を残す | F13: S003,S055,S056,S103 | L13: =IF(COUNT(J13:K13)<2,"",MAX(0,J13-K13)) | S13: =IF(OR(P13="",COUNT(Q13:R13)<2),"",SUMIFS($K$4:$K$23,$P$4:$P$23,P13,$Q$4:$Q$23,"<="&AsOfDate,$R$4:$R$23,">="&AsOfDate)) | T13: 1 | U13: =IF(P13="","Person未割当",IF(OR(G13="",COUNT(Q13,R13,K13,T13)<4),"配置期間・FTE不足",IF(OR(Q13>R13,K13<0,T13<0),"配置値不正",IF(S13>T13,"当日FTE超過","当日稼働記録あり")))) -> Person未割当
A14: R11 | B14: QA / AI Evaluation Engineer | C14: 評価計画、独立セット、統計、回帰、敵対的評価 | D14: 要件から継続評価 | E14: 実装とは別に評価データを管理し、品質停止を勧告 | F14: S052,S059,S067,S070,S077 | L14: =IF(COUNT(J14:K14)<2,"",MAX(0,J14-K14)) | S14: =IF(OR(P14="",COUNT(Q14:R14)<2),"",SUMIFS($K$4:$K$23,$P$4:$P$23,P14,$Q$4:$Q$23,"<="&AsOfDate,$R$4:$R$23,">="&AsOfDate)) | T14: 1 | U14: =IF(P14="","Person未割当",IF(OR(G14="",COUNT(Q14,R14,K14,T14)<4),"配置期間・FTE不足",IF(OR(Q14>R14,K14<0,T14<0),"配置値不正",IF(S14>T14,"当日FTE超過","当日稼働記録あり")))) -> Person未割当
A15: R12 | B15: SRE / Platform Engineer | C15: 基盤、監視、SLO、配備、復旧、費用計測 | D15: 設計〜廃止 | E15: 運用Agentも最小権限。重大な実行は承認対象 | F15: S023,S033,S045,S048,S049 | L15: =IF(COUNT(J15:K15)<2,"",MAX(0,J15-K15)) | S15: =IF(OR(P15="",COUNT(Q15:R15)<2),"",SUMIFS($K$4:$K$23,$P$4:$P$23,P15,$Q$4:$Q$23,"<="&AsOfDate,$R$4:$R$23,">="&AsOfDate)) | T15: 1 | U15: =IF(P15="","Person未割当",IF(OR(G15="",COUNT(Q15,R15,K15,T15)<4),"配置期間・FTE不足",IF(OR(Q15>R15,K15<0,T15<0),"配置値不正",IF(S15>T15,"当日FTE超過","当日稼働記録あり")))) -> Person未割当
... A23: R20 | B23: Procurement / Vendor Owner | C23: 調達、DPA・SOW・SLA、外注受入、解約 | D23: 外部依存を横断管理 | E23: 外注受入と自社製品の公開判断は別 | F23: S014,S092,S094 | L23: =IF(COUNT(J23:K23)<2,"",MAX(0,J23-K23)) | S23: =IF(OR(P23="",COUNT(Q23:R23)<2),"",SUMIFS($K$4:$K$23,$P$4:$P$23,P23,$Q$4:$Q$23,"<="&AsOfDate,$R$4:$R$23,">="&AsOfDate)) | T23: 1 | U23: =IF(P23="","Person未割当",IF(OR(G23="",COUNT(Q23,R23,K23,T23)<4),"配置期間・FTE不足",IF(OR(Q23>R23,K23<0,T23<0),"配置値不正",IF(S23>T23,"当日FTE超過","当日稼働記録あり")))) -> Person未割当
A26: 人数・FTEの読み方
A27: 項目 | B27: 説明 | C27: 注意
A28: 専任人数とは別 | B28: 1人が複数ロールを兼務可能。ただし稼働は重複計上しない | C28: 全ロールのFTE足し算を採用人数に変換しない
A29: 元資料のレンジ | B29: 添付にはコアFTEとロール別必要FTEの両方がある | C29: 総量の整合が未確定のため本表は入力から開始
A30: 独立性 | B30: R19の最終品質承認と実装担当は分離 | C30: 不足時は横断組織や外部レビューを明示

Sheet 07_スキル辞書
A1: スキル辞書｜Lv1〜3の行動と証拠
A2: 106スキル。Lv0=当該業務に関与なし、Lv1=指導下、Lv2=自律遂行、Lv3=設計・指導・例外判断。人の習熟度を評価する。
A3: Skill ID | B3: 軸 | C3: 分類 | D3: スキル名 | E3: 定義 | F3: Lv1 | G3: Lv2 | H3: Lv3 | I3: 判定エビデンス | J3: 関連B-ID | K3: 旧v3 Skill | L3: 根拠ID | M3: 再編・適用メモ
A4: S001 | B4: ビジネス | C4: 共通基礎 | D4: 七工程と事業投資・公開ゲートの運用 | E4: 企画〜廃止とG0〜G5で価値・投資・公開・継続判断を運営し、外注品質受入を分離する。 | F4: 各Gateの判断者と必要証拠を説明できる。 | G4: Evidenceと予算枠を確認し、未承認の本番公開や投資を止められる。 | H4: 事業段階とリスクに応じてGateを設計し、重大変更の再審査を主導できる。 | I4: G0〜G5判断記録・再Gate計画 | J4: B0-01,B0-18,B1-19,B2-20,B6-10 | K4: SK01 | L4: U01,U02 | M4: 受託契約中心の定義を事業投資・プロダクト責任へ明示的に変更。
A5: S002 | B5: ビジネス | C5: 法務・ガバナンス | D5: AIガバナンスと関連法規の適用 | E5: 法令と非拘束的な指針を区別し、業種・用途・提供地域・処理地域から適用法を確認する。AI事業者ガイドライン1.2を参照し、根拠版・確認日・再審査条件を管理する。 | F5: AI事業者ガイドラインの共通の指針（人間中心／安全性／公平性／プライバシー保護／セキュリティ確保／透明性／アカウンタビリティ／教育・リテラシー／公正競争確保／イノベーション）を列挙し、指示のもとで担当タスクとの対応表に記入できる。 | G5: 案件のリスク特性から適用枠組み（AI事業者ガイドライン／ISO/IEC 42001／NIST AI RMF／EU AI Actの適用有無）を選定し、リスク管理台帳と責任あるAI評価レポートにガバナンス観点を反映できる。技術障害と区別したAIインシデントの定義を作成できる。 | H5: 対象事業の業種・利用形態に応じたガバナンス方針を設計し、EU AI Actの高リスク該当性や海外案件の枠組み選択の判断根拠を文書化できる。AIインシデント発生時の本人通知・当局報告・対外説明の手順を策定し、判断を主導できる。 | I5: リサーチ資料、リスク管理台帳 v1、責任あるAI評価レポート、モデルカード、AIインシデント対応手順書 | J5: B0-02,B0-08,B5-20,B5-22 | K5: SK02 | L5: U02 | M5: 受託版の行動基準を自社事業向けに再編。関連タスクは本版B-IDで再定義。
A6: S003 | B6: ビジネス | C6: 法務・ガバナンス | D6: 個人情報保護法の適用判定とデータガバナンス | E6: 取得・保有する個人データについて委託か第三者提供かを判定フローで確定し、法的区分と取扱い条件（保管・マスキング・保持期間・越境・外部API送信可否）を決める。 | F6: 個人情報・個人データ・仮名加工情報・匿名加工情報の区別を説明できる。ハッシュ化だけで法定の仮名加工情報/匿名加工情報になるとは判断しない。 | G6: 利用目的・委託/第三者提供・外国提供・外部AI利用を分けて判定し、法務とデータ利用条件を合意できる。仮名加工情報の第三者提供禁止と法定例外を区別し、同意だけで一般に提供可能としない。 | H6: 越境移転・再委託・仮名加工情報の内部利用など非定型の論点を法務と協議して方針化し、データ提供・利用契約の条項に落とせる。「匿名化」の誤用や目的外利用のリスクを他メンバーの成果物からレビューで検出し指導できる。 | I6: 個人情報取扱い判定書、データ提供・利用契約、データ要件定義書、データ受領記録、アクセス制御設定 | J6: B0-07,B1-04,B2-03,B4-07,B5-20,B6-04,B6-11 | K6: SK03 | L6: U02 | M6: 受託版の行動基準を自社事業向けに再編。関連タスクは本版B-IDで再定義。
A7: S004 | B7: ビジネス | C7: 顧客折衝 | D7: ヒアリングと課題定義 | E7: 対象事業の表面的な要望の奥にある業務課題を対話で引き出し、課題・目標・制約・リソースに分類して優先順位を付ける。 | F7: 標準ヒアリングリストの8カテゴリで質問を用意し、同席したヒアリングの記録を作成して課題候補を抽出できる。 | G7: 60〜120分のヒアリングを単独で実施し、解決策の要望（「チャットボットが欲しい」）を業務課題に翻訳して、重要度・緊急度・実現可能性で優先順位を付けた課題リストを完成させられる。 | H7: 経営層を含む複数階層へのヒアリングを設計し、「なぜそれが必要か」まで掘り下げて課題定義書と価値仮説ステートメントに結実させられる。ヒアリング設計を指導し、質問リストの社内標準を改訂できる。 | I7: ヒアリングリスト、ヒアリング記録、課題リスト（優先順位付き）、ヒアリング議事録、課題定義書 | J7: B0-03,B0-04 | K7: SK04 | L7: U02 | M7: 受託版の行動基準を自社事業向けに再編。関連タスクは本版B-IDで再定義。
A8: S005 | B8: ビジネス | C8: 顧客折衝 | D8: ファシリテーション・交渉・合意形成 | E8: ワークショップ・会議体で意見を引き出し時間内に結論へ導く。利害が対立する場面で合意点を作り、決定を議事録として残す。 | F8: アジェンダとタイムラインを準備し、議事録を決定事項・保留事項・宿題に分けて作成できる。 | G8: 業務フローワークショップやキックオフを単独で進行し、発散と収束を制御して合意事項を議事録に確定できる。反対意見が出た場合に論点を整理して次アクションに変換できる。 | H8: ステアリングコミッティやQBRなど経営層を含む会議を設計・進行し、Go/No-Goのような重い判断を根拠付きで合意に導ける。会議設計を指導し、難航する交渉を引き取れる。 | I8: キックオフ議事録、意思決定議事録（判断根拠を明記）、QBR資料、UATフィードバックリストと対応計画 | J8: B0-17 | K8: SK05 | L8: U02 | M8: 受託版の行動基準を自社事業向けに再編。関連タスクは本版B-IDで再定義。
A9: S006 | B9: ビジネス | C9: 顧客折衝 | D9: ステークホルダー分析とRACI運用 | E9: 意思決定者・業務部門・情報システム部門・エンドユーザー・法務を特定し、期待・関心・影響力・懸念をマッピングしてRACIで役割の曖昧さを排除する。 | F9: 組織図からステークホルダーを列挙し、関心度と影響力の2軸マップに配置できる。R/A/C/Iの定義を区別して既存チャートを読める。 | G9: 利用部門側関与者（事業責任者／業務責任者／SME／IT担当／法務／データ管理者）と自社ロール（R1〜R5）を分けてRACIチャート v1を完成させ、利用部門側責任一覧に担当者・期限・数値を落とし込める。 | H9: 少人数体制の兼務マップを設計し、兼務時の分離ルール（本番デプロイ承認は実装者以外、モデル評価は学習実施者以外がレビュー）を定めてRACI v2に反映できる。キーパーソンの抵抗を早期に検知して対処方針を決められる。 | I9: ステークホルダーマップ、RACIチャート v1、RACIチャート v2、利用部門の責任・権限一覧、運用体制図 | J9: B0-01,B0-15,B5-01 | K9: SK06 | L9: U02 | M9: 受託版の行動基準を自社事業向けに再編。関連タスクは本版B-IDで再定義。
A10: S007 | B10: ビジネス | C10: 顧客折衝 | D10: ドメイン知識の獲得と活用 | E10: 対象業界・業務の構造、専門用語、規制、KPIを短期間で把握し、現実的で価値のあるAIソリューションを構想する。 | F10: 業界レポートと顧客公開資料から事業構造・主要業務プロセス・関連規制をA4 1〜2枚に整理できる。業務担当者の用語を用語集にまとめられる。 | G10: 業務担当者と対等に議論できる水準で業務を理解し、As-Is業務フロー図を自力で作成して例外処理まで記述できる。データの業務的意味（外れ値が実在の事象か）をSMEに確認して判断できる。 | H10: 複数案件で蓄積した業界知見から顧客が気づいていない課題や適用領域を提案できる。新規業界への参入時に調査観点を設計し、チームの学習を主導できる。 | I10: リサーチ資料、As-Is業務フロー図、業務適合性評価レポート、ヒアリング議事録 | J10: B0-02 | K10: SK07 | L10: U02 | M10: 受託版の行動基準を自社事業向けに再編。関連タスクは本版B-IDで再定義。
A11: S008 | B11: ビジネス | C11: 事業価値 | D11: 事業戦略理解とビジネス分析フレームワークの活用 | E11: 対象事業の経営戦略・市場環境を3C・SWOT等で構造化し、AIプロジェクトの位置づけと投資判断の文脈を説明する。 | F11: 3C・SWOTの枠組みに顧客情報を当てはめ、指示のもとで分析シートの下書きを作成できる。 | G11: 分析結果から「このAI投資が対象事業のどの戦略目標に貢献するか」を説明し、実現可能性評価レポートの財務・運用観点に接続できる。市場性を評価すべき案件（対外サービス提供型）とそうでない案件を区別できる。 | H11: 複数のAI施策候補を経営戦略への貢献度で比較評価し、優先順位と投資配分を提言できる。QBRで次期の戦略提案を主導できる。 | I11: リサーチ資料、実現可能性評価レポート、QBR資料、次期提案、提案書 | J11: B0-02,B0-05 | K11: SK08 | L11: U02 | M11: 受託版の行動基準を自社事業向けに再編。関連タスクは本版B-IDで再定義。
A12: S009 | B12: ビジネス | C12: 事業価値 | D12: 価値仮説の定義とKPI設計 | E12: 「誰の・どんな課題を・どのように解決し・どのような価値を提供するか」を言語化し、SMART原則に沿った目標とPoCのKPI・アクション基準を設計する。 | F12: 価値仮説のテンプレートに顧客情報を当てはめて下書きし、既存KPIがSMARTの5要素を満たすかをチェックリストで判定できる。 | G12: 定量的な期待効果を含む価値仮説ステートメントとSMART目標を作成し、In-Scope/Out-of-Scopeを具体的に列挙したスコープ定義書を完成させられる。PoC計画書に技術KPIとビジネスKPIを両方定義できる。 | H12: KPI達成度別のネクストアクション（移行／追加PoC／中止）をルール化して事前に関係責任者と合意できる。AI導入自体が目的化した案件を検知し、価値仮説から再定義するよう顧客を導ける。 | I12: 価値仮説ステートメント、課題定義書、SMART目標、スコープ定義書、PoC計画書（実験計画・承認の別紙） | J12: B0-05,B0-17,B1-01,B5-02 | K12: SK09 | L12: U02 | M12: 受託版の行動基準を自社事業向けに再編。関連タスクは本版B-IDで再定義。
A13: S010 | B13: ビジネス | C13: 事業価値 | D13: ROI・TCO試算と感度分析 | E13: 開発・評価・レビュー・手戻り・運用・外部依存を含むTCOと便益を、案件に合う期間で比較する。現金支出削減と余力創出・収益仮説を区別し、対照・前提・感度・不確実性を示す。 | F13: 与えられた前提（人件費単価、現行コスト、想定削減時間）を試算シートに入力し、指示のもとで回収期間を計算できる。 | G13: 便益を3区分に分けて稼働開始月で按分し（初年度は立ち上げ係数）、収益仮説を悲観・標準・楽観の3シナリオで示し、回収期間を定義式（累積純キャッシュフローが0を超える時点）で再計算できるROI試算シートを完成させられる。 | H13: 感度分析の変数選定と前提の妥当性を関係責任者と交渉して合意させ、運用の変動費（トークン消費等）を織り込んだTCOを設計できる。ROI前提と実測値の乖離を分析して次期投資判断に接続できる。 | I13: ROI試算シート（感度分析付き）、実現可能性評価レポート、コストダッシュボード | J13: B0-10,B4-10,B6-09 | K13: SK10 | L13: U02 | M13: 受託版の行動基準を自社事業向けに再編。関連タスクは本版B-IDで再定義。
A14: S011 | B14: ビジネス | C14: 事業価値 | D14: ビジネス価値の可視化と定例レポーティング・QBR運営 | E14: 事業価値・品質・費用・継続利用の実測を仮説と比較し、継続・拡大・ピボット・縮小・停止の判断につなげる。 | F14: 監視ダッシュボードとインシデント記録から、指示された項目を月次レポートのフォーマットに転記して作成できる。 | G14: SLA遵守状況・モデル性能推移・検知したドリフト・実施した改善を月次／四半期レポートにまとめ、技術指標を金額換算のビジネス価値に翻訳して示せる（「適合率99.2%」ではなく「不正取引をX円分防止した」）。効果測定レポートをROI前提と比較できる。 | H14: 事業レビューを設計・主導し、反証と不確実性を含めて次期投資・継続／停止を判断できる。B2B販売契約の更新は該当時だけ外部契約台帳で別に扱う。 | I14: 効果測定レポート、月次／四半期パフォーマンスレポート、ビジネス価値貢献レポート、QBR資料、次期提案 | J14: B4-17,B5-21,B6-09 | K14: SK11 | L14: U02 | M14: 受託版の行動基準を自社事業向けに再編。関連タスクは本版B-IDで再定義。
... A84: S081 | B84: ビジネス | C84: 継続ガバナンス | D84: リスク比例の投資・公開・継続・変更判断 | E84: 事業性と安全性を別軸で確認し、継続・拡大・転換・停止と再Gateを運用する。 | F84: 判断のOwner、禁止条件、証拠を説明できる。 | G84: 残存リスクに期限・責任者を付け、重大変更を要件・設計・評価へ戻せる。 | H84: 組織の投資ポートフォリオと危害を整合させ、事業都合の品質上書きを防げる。 | I84: 投資・Release・例外・継続判断記録 | J84: B0-16,B0-18,B1-10,B1-17,B1-19,B2-19,B2-20,B4-13,B4-14,B5-10,B5-12,B5-17,B5-20,B5-21,B5-22,B6-10 | K84: SK81 | L84: U01,U02 | M84: 受託契約中心の定義を事業投資・プロダクト責任へ明示的に変更。
A85: S082 | B85: 事業・Product | C85: Discovery | D85: 課題発見と需要の反証 | E85: JTBD、利用者・購買者、代替行動を調べ、需要の裏付けと反証を整理する。 | F85: 誘導しない質問で観察を記録できる。 | G85: 行動証拠から課題・優先セグメントを定義し最小実験できる。 | H85: 複数の機会を比較し、探索の停止・転換を主導できる。 | I85: 観察記録・Opportunity Brief | J85: B0-01,B0-03,B0-04,B0-05,B0-12,B5-13 | L85: U01 | M85: 添付提案を実行・スキル評価に具体化。U03は本資料の追加設計。
A86: S083 | B86: 事業・Product | C86: 収益 | D86: 価格・支払意思・パッケージ | E86: 価格単位、無償枠、支払意思、差別的影響を検証し提供条件へ落とす。 | F86: 利用者と支払者、料金単位を区別できる。 | G86: 価格仮説とテストを設計し原価・価値から判断できる。 | H86: 複数顧客群の価格、解約、粗利、誤課金リスクを統合できる。 | I86: 価格実験・提供条件 | J86: B0-09,B1-12,B4-10,B4-16,B5-14 | L86: U01 | M86: 添付提案を実行・スキル評価に具体化。U03は本資料の追加設計。
A87: S084 | B87: 事業・Product | C87: 事業モデル | D87: 収益・価値交換モデル | E87: 売切り、従量、定額、成果型、社内価値の仮説と制約を整理する。 | F87: 収益源と費用・リスクの帰属を説明できる。 | G87: 価値指標と課金指標の不一致を検出できる。 | H87: 市場・パートナー・事業戦略に適合するモデルを選べる。 | I87: Business Model・感度分析 | J87: B0-09 | L87: U01 | M87: 添付提案を実行・スキル評価に具体化。U03は本資料の追加設計。
A88: S085 | B88: 事業・Product | C88: GTM | D88: 市場投入・販売・導入設計 | E88: 獲得経路、購買審査、導入、公開機能、販売資料を実装と接続する。 | F88: ユーザー導入の主要な障壁を記録できる。 | G88: 価格、営業、サポート、Releaseを揃えLaunchできる。 | H88: 異なる市場・地域のGTMとリスク再審査を設計できる。 | I88: Launch計画・販売資料・導入実績 | J88: B0-03,B0-14,B1-11,B3-20,B4-16,B5-22 | L88: U01 | M88: 添付提案を実行・スキル評価に具体化。U03は本資料の追加設計。
A89: S086 | B89: 事業・Product | C89: Growth | D89: ファネル・コホート・継続改善 | E89: 利用開始、価値到達、継続、解約を同じ定義で観測し改善する。 | F89: 登録数と利用価値・継続率を区別できる。 | G89: コホートと分母を定義し失敗箇所を分析できる。 | H89: 長期価値と安全guardrailを満たすGrowthを設計できる。 | I89: ファネル・継続分析・実験 | J89: B0-14,B5-02,B5-14 | L89: U01 | M89: 添付提案を実行・スキル評価に具体化。U03は本資料の追加設計。
A90: S087 | B90: 事業・Product | C90: 実験 | D90: 仮説・実験・反証・意思決定 | E90: 実験の成功・中止条件を先に定め、学びを次の投資へ接続する。 | F90: 仮説と検証観測を分けられる。 | G90: 交絡、期間、サンプル、費用を考慮して実験できる。 | H90: 複数実験の探索価値と誤判定コストを統合できる。 | I90: 実験台帳・判断・学習ログ | J90: B0-11,B0-12,B0-17,B1-03,B1-15,B4-15,B5-13,B5-14 | L90: U01 | M90: 添付提案を実行・スキル評価に具体化。U03は本資料の追加設計。
A91: S088 | B91: 組織・Delivery | C91: 体制 | D91: スキルギャップ・兼務・要員設計 | E91: 必要能力、稼働、独立性を分け、採用・育成・外部活用を選ぶ。 | F91: 必要スキルと人の保有能力を区別できる。 | G91: 行動証拠で不足を判定し担当・期限を設けられる。 | H91: 単独依存・利益相反・レビュー能力を含む体制を設計できる。 | I91: 能力評価・要員・育成計画 | J91: B0-15,B1-16,B5-19 | L91: U01 | M91: 添付提案を実行・スキル評価に具体化。U03は本資料の追加設計。
A92: S089 | B92: 事業運営 | C92: CS | D92: 導入・顧客成功・救済 | E92: 利用定着、問い合わせ、誤回答、返金、苦情を継続改善へつなぐ。 | F92: 通常質問と危害・事故を分類できる。 | G92: 導入・エスカレーション・救済手順を運用できる。 | H92: サービス拡大時の支援容量と品質、安全を設計できる。 | I92: CS記録・導入指標・救済記録 | J92: B0-14,B1-11,B3-20,B4-12,B4-16,B4-17,B5-07,B6-02 | L92: U01 | M92: 添付提案を実行・スキル評価に具体化。U03は本資料の追加設計。
A93: S090 | B93: 事業・分析 | C93: Analytics | D93: 価値指標・計測・意思決定分析 | E93: KPIの分母、期間、イベント、欠測、コホートを統一する。 | F93: イベントと事業指標の関係を説明できる。 | G93: プライバシーを守り計測・集計・検証できる。 | H93: 指標の歪み、交絡、Goodhart化を検出し計測体系を改善できる。 | I93: KPI定義・計測試験・意思決定 | J93: B1-01,B1-18,B5-02,B5-14 | L93: U01 | M93: 添付提案を実行・スキル評価に具体化。U03は本資料の追加設計。
A94: S091 | B94: エンジニアリング | C94: 収益基盤 | D94: 利用量計測・課金・返金 | E94: 利用量と価格を結び、二重請求・過大請求・無料枠悪用を防ぐ。 | F94: 課金イベントと成功条件を説明できる。 | G94: 冪等な課金、照合、上限、取消を実装できる。 | H94: 複数料金体系・遡及修正・事故時救済を設計できる。 | I94: 課金仕様・照合テスト・精算 | J94: B1-12,B2-09,B2-17,B3-14,B4-10,B5-06 | L94: U03 | M94: 添付提案を実行・スキル評価に具体化。U03は本資料の追加設計。
A95: S092 | B95: 事業運営 | C95: 調達 | D95: Build/Buy/Partnerと調達判断 | E95: 外部依存の総費用、権利、供給継続、切替を比較する。 | F95: 比較項目と情報不足を整理できる。 | G95: ベンダー評価・受入条件・退出計画を作れる。 | H95: 調達集中・ロックインと内製能力を戦略的に調整できる。 | I95: 調達ADR・契約・代替計画 | J95: B1-13 | L95: U01 | M95: 添付提案を実行・スキル評価に具体化。U03は本資料の追加設計。
A96: S093 | B96: 事業・FinOps | C96: 単位経済性 | D96: 成功単位原価・限界利益・費用境界 | E96: AI、検索、再試行、手動介入、CSを含む成功当たり原価を計測する。 | F96: 費用、粗利、キャッシュ、能力余力を区別できる。 | G96: 料金・成功率・利用量の感度を計算できる。 | H96: 利益改善と品質劣化のtrade-offを統合し投資判断できる。 | I96: cost/success・収支・感度分析 | J96: B0-09,B0-10,B1-12,B1-18,B2-17,B3-14,B3-22,B4-10,B5-06 | L96: U01,W08 | M96: 添付提案を実行・スキル評価に具体化。U03は本資料の追加設計。
... A109: S106 | B109: 組織・Delivery | C109: Flow | D109: レビュー容量・WIP・品質調整済み速度 | E109: 実装速度でなく価値提供の待ち・手戻り・品質を含む流れを改善する。 | F109: 生成量と完了価値、工数とリードタイムを区別できる。 | G109: レビュー待ち・障害・再作業を計測しWIPを調整できる。 | H109: 同等品質での投資効果と組織ボトルネックを改善できる。 | I109: Flow指標・能力計画・E2E比較 | J109: B1-16,B5-19 | L109: U01,W07,W08 | M109: 添付提案を実行・スキル評価に具体化。U03は本資料の追加設計。

Sheet 08_タスク×ロール×スキル
A1: タスク×ロール×スキル｜必要能力の割当
A2: 1行=標準Task×Skill（候補Role）。案件のTask×Role×Skill×Personは35で確定。全員に全Skillを要求しない。
A3: Task ID | B3: タスク名（参照） | C3: 実施R | D3: 承認A | E3: Skill ID | F3: スキル名（参照） | G3: 必要Lv | H3: 確認する証拠 | I3: 割当方針
A4: B0-01 | B4: =IF(COUNTIF('02_工程タスク'!$A$4:$A$135,A4)<>1,"参照ID不正",IF(INDEX('02_工程タスク'!$D$4:$D$135,MATCH(A4,'02_工程タスク'!$A$4:$A$135,0))="","",INDEX('02_工程タスク'!$D$4:$D$135,MATCH(A4,'02_工程タスク'!$A$4:$A$135,0)))) -> 探索責任者・初期枠の設定 | C4: =IF(COUNTIF('02_工程タスク'!$A$4:$A$135,A4)<>1,"参照ID不正",IF(INDEX('02_工程タスク'!$G$4:$G$135,MATCH(A4,'02_工程タスク'!$A$4:$A$135,0))="","",INDEX('02_工程タスク'!$G$4:$G$135,MATCH(A4,'02_工程タスク'!$A$4:$A$135,0)))) -> R02, R03 | D4: =IF(COUNTIF('02_工程タスク'!$A$4:$A$135,A4)<>1,"参照ID不正",IF(INDEX('02_工程タスク'!$H$4:$H$135,MATCH(A4,'02_工程タスク'!$A$4:$A$135,0))="","",INDEX('02_工程タスク'!$H$4:$H$135,MATCH(A4,'02_工程タスク'!$A$4:$A$135,0)))) -> R01 | E4: S001 | F4: =IF(COUNTIF('07_スキル辞書'!$A$4:$A$109,E4)<>1,"参照ID不正",IF(INDEX('07_スキル辞書'!$D$4:$D$109,MATCH(E4,'07_スキル辞書'!$A$4:$A$109,0))="","",INDEX('07_スキル辞書'!$D$4:$D$109,MATCH(E4,'07_スキル辞書'!$A$4:$A$109,0)))) -> 七工程と事業投資・公開ゲートの運用 | G4: 2 | H4: =IF(COUNTIF('07_スキル辞書'!$A$4:$A$109,E4)<>1,"参照ID不正",IF(INDEX('07_スキル辞書'!$I$4:$I$109,MATCH(E4,'07_スキル辞書'!$A$4:$A$109,0))="","",INDEX('07_スキル辞書'!$I$4:$I$109,MATCH(E4,'07_スキル辞書'!$A$4:$A$109,0)))) -> G0〜G5判断記録・再Gate計画 | I4: 役割ごとに必要な組合せを06/28で担当者へ割当。全員に全Skillを要求しない。
A5: B0-01 | B5: =IF(COUNTIF('02_工程タスク'!$A$4:$A$135,A5)<>1,"参照ID不正",IF(INDEX('02_工程タスク'!$D$4:$D$135,MATCH(A5,'02_工程タスク'!$A$4:$A$135,0))="","",INDEX('02_工程タスク'!$D$4:$D$135,MATCH(A5,'02_工程タスク'!$A$4:$A$135,0)))) -> 探索責任者・初期枠の設定 | C5: =IF(COUNTIF('02_工程タスク'!$A$4:$A$135,A5)<>1,"参照ID不正",IF(INDEX('02_工程タスク'!$G$4:$G$135,MATCH(A5,'02_工程タスク'!$A$4:$A$135,0))="","",INDEX('02_工程タスク'!$G$4:$G$135,MATCH(A5,'02_工程タスク'!$A$4:$A$135,0)))) -> R02, R03 | D5: =IF(COUNTIF('02_工程タスク'!$A$4:$A$135,A5)<>1,"参照ID不正",IF(INDEX('02_工程タスク'!$H$4:$H$135,MATCH(A5,'02_工程タスク'!$A$4:$A$135,0))="","",INDEX('02_工程タスク'!$H$4:$H$135,MATCH(A5,'02_工程タスク'!$A$4:$A$135,0)))) -> R01 | E5: S006 | F5: =IF(COUNTIF('07_スキル辞書'!$A$4:$A$109,E5)<>1,"参照ID不正",IF(INDEX('07_スキル辞書'!$D$4:$D$109,MATCH(E5,'07_スキル辞書'!$A$4:$A$109,0))="","",INDEX('07_スキル辞書'!$D$4:$D$109,MATCH(E5,'07_スキル辞書'!$A$4:$A$109,0)))) -> ステークホルダー分析とRACI運用 | G5: 2 | H5: =IF(COUNTIF('07_スキル辞書'!$A$4:$A$109,E5)<>1,"参照ID不正",IF(INDEX('07_スキル辞書'!$I$4:$I$109,MATCH(E5,'07_スキル辞書'!$A$4:$A$109,0))="","",INDEX('07_スキル辞書'!$I$4:$I$109,MATCH(E5,'07_スキル辞書'!$A$4:$A$109,0)))) -> ステークホルダーマップ、RACIチャート v1、RACIチャート v2、利用部門の責任・権限一覧、運用体制図 | I5: 役割ごとに必要な組合せを06/28で担当者へ割当。全員に全Skillを要求しない。
A6: B0-01 | B6: =IF(COUNTIF('02_工程タスク'!$A$4:$A$135,A6)<>1,"参照ID不正",IF(INDEX('02_工程タスク'!$D$4:$D$135,MATCH(A6,'02_工程タスク'!$A$4:$A$135,0))="","",INDEX('02_工程タスク'!$D$4:$D$135,MATCH(A6,'02_工程タスク'!$A$4:$A$135,0)))) -> 探索責任者・初期枠の設定 | C6: =IF(COUNTIF('02_工程タスク'!$A$4:$A$135,A6)<>1,"参照ID不正",IF(INDEX('02_工程タスク'!$G$4:$G$135,MATCH(A6,'02_工程タスク'!$A$4:$A$135,0))="","",INDEX('02_工程タスク'!$G$4:$G$135,MATCH(A6,'02_工程タスク'!$A$4:$A$135,0)))) -> R02, R03 | D6: =IF(COUNTIF('02_工程タスク'!$A$4:$A$135,A6)<>1,"参照ID不正",IF(INDEX('02_工程タスク'!$H$4:$H$135,MATCH(A6,'02_工程タスク'!$A$4:$A$135,0))="","",INDEX('02_工程タスク'!$H$4:$H$135,MATCH(A6,'02_工程タスク'!$A$4:$A$135,0)))) -> R01 | E6: S082 | F6: =IF(COUNTIF('07_スキル辞書'!$A$4:$A$109,E6)<>1,"参照ID不正",IF(INDEX('07_スキル辞書'!$D$4:$D$109,MATCH(E6,'07_スキル辞書'!$A$4:$A$109,0))="","",INDEX('07_スキル辞書'!$D$4:$D$109,MATCH(E6,'07_スキル辞書'!$A$4:$A$109,0)))) -> 課題発見と需要の反証 | G6: 2 | H6: =IF(COUNTIF('07_スキル辞書'!$A$4:$A$109,E6)<>1,"参照ID不正",IF(INDEX('07_スキル辞書'!$I$4:$I$109,MATCH(E6,'07_スキル辞書'!$A$4:$A$109,0))="","",INDEX('07_スキル辞書'!$I$4:$I$109,MATCH(E6,'07_スキル辞書'!$A$4:$A$109,0)))) -> 観察記録・Opportunity Brief | I6: 役割ごとに必要な組合せを06/28で担当者へ割当。全員に全Skillを要求しない。
A7: B0-02 | B7: =IF(COUNTIF('02_工程タスク'!$A$4:$A$135,A7)<>1,"参照ID不正",IF(INDEX('02_工程タスク'!$D$4:$D$135,MATCH(A7,'02_工程タスク'!$A$4:$A$135,0))="","",INDEX('02_工程タスク'!$D$4:$D$135,MATCH(A7,'02_工程タスク'!$A$4:$A$135,0)))) -> 市場・競合・規制候補の調査 | C7: =IF(COUNTIF('02_工程タスク'!$A$4:$A$135,A7)<>1,"参照ID不正",IF(INDEX('02_工程タスク'!$G$4:$G$135,MATCH(A7,'02_工程タスク'!$A$4:$A$135,0))="","",INDEX('02_工程タスク'!$G$4:$G$135,MATCH(A7,'02_工程タスク'!$A$4:$A$135,0)))) -> R02, R04, R16 | D7: =IF(COUNTIF('02_工程タスク'!$A$4:$A$135,A7)<>1,"参照ID不正",IF(INDEX('02_工程タスク'!$H$4:$H$135,MATCH(A7,'02_工程タスク'!$A$4:$A$135,0))="","",INDEX('02_工程タスク'!$H$4:$H$135,MATCH(A7,'02_工程タスク'!$A$4:$A$135,0)))) -> R02 | E7: S002 | F7: =IF(COUNTIF('07_スキル辞書'!$A$4:$A$109,E7)<>1,"参照ID不正",IF(INDEX('07_スキル辞書'!$D$4:$D$109,MATCH(E7,'07_スキル辞書'!$A$4:$A$109,0))="","",INDEX('07_スキル辞書'!$D$4:$D$109,MATCH(E7,'07_スキル辞書'!$A$4:$A$109,0)))) -> AIガバナンスと関連法規の適用 | G7: 2 | H7: =IF(COUNTIF('07_スキル辞書'!$A$4:$A$109,E7)<>1,"参照ID不正",IF(INDEX('07_スキル辞書'!$I$4:$I$109,MATCH(E7,'07_スキル辞書'!$A$4:$A$109,0))="","",INDEX('07_スキル辞書'!$I$4:$I$109,MATCH(E7,'07_スキル辞書'!$A$4:$A$109,0)))) -> リサーチ資料、リスク管理台帳 v1、責任あるAI評価レポート、モデルカード、AIインシデント対応手順書 | I7: 役割ごとに必要な組合せを06/28で担当者へ割当。全員に全Skillを要求しない。
A8: B0-02 | B8: =IF(COUNTIF('02_工程タスク'!$A$4:$A$135,A8)<>1,"参照ID不正",IF(INDEX('02_工程タスク'!$D$4:$D$135,MATCH(A8,'02_工程タスク'!$A$4:$A$135,0))="","",INDEX('02_工程タスク'!$D$4:$D$135,MATCH(A8,'02_工程タスク'!$A$4:$A$135,0)))) -> 市場・競合・規制候補の調査 | C8: =IF(COUNTIF('02_工程タスク'!$A$4:$A$135,A8)<>1,"参照ID不正",IF(INDEX('02_工程タスク'!$G$4:$G$135,MATCH(A8,'02_工程タスク'!$A$4:$A$135,0))="","",INDEX('02_工程タスク'!$G$4:$G$135,MATCH(A8,'02_工程タスク'!$A$4:$A$135,0)))) -> R02, R04, R16 | D8: =IF(COUNTIF('02_工程タスク'!$A$4:$A$135,A8)<>1,"参照ID不正",IF(INDEX('02_工程タスク'!$H$4:$H$135,MATCH(A8,'02_工程タスク'!$A$4:$A$135,0))="","",INDEX('02_工程タスク'!$H$4:$H$135,MATCH(A8,'02_工程タスク'!$A$4:$A$135,0)))) -> R02 | E8: S007 | F8: =IF(COUNTIF('07_スキル辞書'!$A$4:$A$109,E8)<>1,"参照ID不正",IF(INDEX('07_スキル辞書'!$D$4:$D$109,MATCH(E8,'07_スキル辞書'!$A$4:$A$109,0))="","",INDEX('07_スキル辞書'!$D$4:$D$109,MATCH(E8,'07_スキル辞書'!$A$4:$A$109,0)))) -> ドメイン知識の獲得と活用 | G8: 2 | H8: =IF(COUNTIF('07_スキル辞書'!$A$4:$A$109,E8)<>1,"参照ID不正",IF(INDEX('07_スキル辞書'!$I$4:$I$109,MATCH(E8,'07_スキル辞書'!$A$4:$A$109,0))="","",INDEX('07_スキル辞書'!$I$4:$I$109,MATCH(E8,'07_スキル辞書'!$A$4:$A$109,0)))) -> リサーチ資料、As-Is業務フロー図、業務適合性評価レポート、ヒアリング議事録 | I8: 役割ごとに必要な組合せを06/28で担当者へ割当。全員に全Skillを要求しない。
A9: B0-02 | B9: =IF(COUNTIF('02_工程タスク'!$A$4:$A$135,A9)<>1,"参照ID不正",IF(INDEX('02_工程タスク'!$D$4:$D$135,MATCH(A9,'02_工程タスク'!$A$4:$A$135,0))="","",INDEX('02_工程タスク'!$D$4:$D$135,MATCH(A9,'02_工程タスク'!$A$4:$A$135,0)))) -> 市場・競合・規制候補の調査 | C9: =IF(COUNTIF('02_工程タスク'!$A$4:$A$135,A9)<>1,"参照ID不正",IF(INDEX('02_工程タスク'!$G$4:$G$135,MATCH(A9,'02_工程タスク'!$A$4:$A$135,0))="","",INDEX('02_工程タスク'!$G$4:$G$135,MATCH(A9,'02_工程タスク'!$A$4:$A$135,0)))) -> R02, R04, R16 | D9: =IF(COUNTIF('02_工程タスク'!$A$4:$A$135,A9)<>1,"参照ID不正",IF(INDEX('02_工程タスク'!$H$4:$H$135,MATCH(A9,'02_工程タスク'!$A$4:$A$135,0))="","",INDEX('02_工程タスク'!$H$4:$H$135,MATCH(A9,'02_工程タスク'!$A$4:$A$135,0)))) -> R02 | E9: S008 | F9: =IF(COUNTIF('07_スキル辞書'!$A$4:$A$109,E9)<>1,"参照ID不正",IF(INDEX('07_スキル辞書'!$D$4:$D$109,MATCH(E9,'07_スキル辞書'!$A$4:$A$109,0))="","",INDEX('07_スキル辞書'!$D$4:$D$109,MATCH(E9,'07_スキル辞書'!$A$4:$A$109,0)))) -> 事業戦略理解とビジネス分析フレームワークの活用 | G9: 2 | H9: =IF(COUNTIF('07_スキル辞書'!$A$4:$A$109,E9)<>1,"参照ID不正",IF(INDEX('07_スキル辞書'!$I$4:$I$109,MATCH(E9,'07_スキル辞書'!$A$4:$A$109,0))="","",INDEX('07_スキル辞書'!$I$4:$I$109,MATCH(E9,'07_スキル辞書'!$A$4:$A$109,0)))) -> リサーチ資料、実現可能性評価レポート、QBR資料、次期提案、提案書 | I9: 役割ごとに必要な組合せを06/28で担当者へ割当。全員に全Skillを要求しない。
A10: B0-03 | B10: =IF(COUNTIF('02_工程タスク'!$A$4:$A$135,A10)<>1,"参照ID不正",IF(INDEX('02_工程タスク'!$D$4:$D$135,MATCH(A10,'02_工程タスク'!$A$4:$A$135,0))="","",INDEX('02_工程タスク'!$D$4:$D$135,MATCH(A10,'02_工程タスク'!$A$4:$A$135,0)))) -> 利用者・購買者の仮説分解 | C10: =IF(COUNTIF('02_工程タスク'!$A$4:$A$135,A10)<>1,"参照ID不正",IF(INDEX('02_工程タスク'!$G$4:$G$135,MATCH(A10,'02_工程タスク'!$A$4:$A$135,0))="","",INDEX('02_工程タスク'!$G$4:$G$135,MATCH(A10,'02_工程タスク'!$A$4:$A$135,0)))) -> R02, R05 | D10: =IF(COUNTIF('02_工程タスク'!$A$4:$A$135,A10)<>1,"参照ID不正",IF(INDEX('02_工程タスク'!$H$4:$H$135,MATCH(A10,'02_工程タスク'!$A$4:$A$135,0))="","",INDEX('02_工程タスク'!$H$4:$H$135,MATCH(A10,'02_工程タスク'!$A$4:$A$135,0)))) -> R02 | E10: S004 | F10: =IF(COUNTIF('07_スキル辞書'!$A$4:$A$109,E10)<>1,"参照ID不正",IF(INDEX('07_スキル辞書'!$D$4:$D$109,MATCH(E10,'07_スキル辞書'!$A$4:$A$109,0))="","",INDEX('07_スキル辞書'!$D$4:$D$109,MATCH(E10,'07_スキル辞書'!$A$4:$A$109,0)))) -> ヒアリングと課題定義 | G10: 2 | H10: =IF(COUNTIF('07_スキル辞書'!$A$4:$A$109,E10)<>1,"参照ID不正",IF(INDEX('07_スキル辞書'!$I$4:$I$109,MATCH(E10,'07_スキル辞書'!$A$4:$A$109,0))="","",INDEX('07_スキル辞書'!$I$4:$I$109,MATCH(E10,'07_スキル辞書'!$A$4:$A$109,0)))) -> ヒアリングリスト、ヒアリング記録、課題リスト（優先順位付き）、ヒアリング議事録、課題定義書 | I10: 役割ごとに必要な組合せを06/28で担当者へ割当。全員に全Skillを要求しない。
A11: B0-03 | B11: =IF(COUNTIF('02_工程タスク'!$A$4:$A$135,A11)<>1,"参照ID不正",IF(INDEX('02_工程タスク'!$D$4:$D$135,MATCH(A11,'02_工程タスク'!$A$4:$A$135,0))="","",INDEX('02_工程タスク'!$D$4:$D$135,MATCH(A11,'02_工程タスク'!$A$4:$A$135,0)))) -> 利用者・購買者の仮説分解 | C11: =IF(COUNTIF('02_工程タスク'!$A$4:$A$135,A11)<>1,"参照ID不正",IF(INDEX('02_工程タスク'!$G$4:$G$135,MATCH(A11,'02_工程タスク'!$A$4:$A$135,0))="","",INDEX('02_工程タスク'!$G$4:$G$135,MATCH(A11,'02_工程タスク'!$A$4:$A$135,0)))) -> R02, R05 | D11: =IF(COUNTIF('02_工程タスク'!$A$4:$A$135,A11)<>1,"参照ID不正",IF(INDEX('02_工程タスク'!$H$4:$H$135,MATCH(A11,'02_工程タスク'!$A$4:$A$135,0))="","",INDEX('02_工程タスク'!$H$4:$H$135,MATCH(A11,'02_工程タスク'!$A$4:$A$135,0)))) -> R02 | E11: S082 | F11: =IF(COUNTIF('07_スキル辞書'!$A$4:$A$109,E11)<>1,"参照ID不正",IF(INDEX('07_スキル辞書'!$D$4:$D$109,MATCH(E11,'07_スキル辞書'!$A$4:$A$109,0))="","",INDEX('07_スキル辞書'!$D$4:$D$109,MATCH(E11,'07_スキル辞書'!$A$4:$A$109,0)))) -> 課題発見と需要の反証 | G11: 2 | H11: =IF(COUNTIF('07_スキル辞書'!$A$4:$A$109,E11)<>1,"参照ID不正",IF(INDEX('07_スキル辞書'!$I$4:$I$109,MATCH(E11,'07_スキル辞書'!$A$4:$A$109,0))="","",INDEX('07_スキル辞書'!$I$4:$I$109,MATCH(E11,'07_スキル辞書'!$A$4:$A$109,0)))) -> 観察記録・Opportunity Brief | I11: 役割ごとに必要な組合せを06/28で担当者へ割当。全員に全Skillを要求しない。
A12: B0-03 | B12: =IF(COUNTIF('02_工程タスク'!$A$4:$A$135,A12)<>1,"参照ID不正",IF(INDEX('02_工程タスク'!$D$4:$D$135,MATCH(A12,'02_工程タスク'!$A$4:$A$135,0))="","",INDEX('02_工程タスク'!$D$4:$D$135,MATCH(A12,'02_工程タスク'!$A$4:$A$135,0)))) -> 利用者・購買者の仮説分解 | C12: =IF(COUNTIF('02_工程タスク'!$A$4:$A$135,A12)<>1,"参照ID不正",IF(INDEX('02_工程タスク'!$G$4:$G$135,MATCH(A12,'02_工程タスク'!$A$4:$A$135,0))="","",INDEX('02_工程タスク'!$G$4:$G$135,MATCH(A12,'02_工程タスク'!$A$4:$A$135,0)))) -> R02, R05 | D12: =IF(COUNTIF('02_工程タスク'!$A$4:$A$135,A12)<>1,"参照ID不正",IF(INDEX('02_工程タスク'!$H$4:$H$135,MATCH(A12,'02_工程タスク'!$A$4:$A$135,0))="","",INDEX('02_工程タスク'!$H$4:$H$135,MATCH(A12,'02_工程タスク'!$A$4:$A$135,0)))) -> R02 | E12: S085 | F12: =IF(COUNTIF('07_スキル辞書'!$A$4:$A$109,E12)<>1,"参照ID不正",IF(INDEX('07_スキル辞書'!$D$4:$D$109,MATCH(E12,'07_スキル辞書'!$A$4:$A$109,0))="","",INDEX('07_スキル辞書'!$D$4:$D$109,MATCH(E12,'07_スキル辞書'!$A$4:$A$109,0)))) -> 市場投入・販売・導入設計 | G12: 2 | H12: =IF(COUNTIF('07_スキル辞書'!$A$4:$A$109,E12)<>1,"参照ID不正",IF(INDEX('07_スキル辞書'!$I$4:$I$109,MATCH(E12,'07_スキル辞書'!$A$4:$A$109,0))="","",INDEX('07_スキル辞書'!$I$4:$I$109,MATCH(E12,'07_スキル辞書'!$A$4:$A$109,0)))) -> Launch計画・販売資料・導入実績 | I12: 役割ごとに必要な組合せを06/28で担当者へ割当。全員に全Skillを要求しない。
A13: B0-04 | B13: =IF(COUNTIF('02_工程タスク'!$A$4:$A$135,A13)<>1,"参照ID不正",IF(INDEX('02_工程タスク'!$D$4:$D$135,MATCH(A13,'02_工程タスク'!$A$4:$A$135,0))="","",INDEX('02_工程タスク'!$D$4:$D$135,MATCH(A13,'02_工程タスク'!$A$4:$A$135,0)))) -> インタビュー・現場観察 | C13: =IF(COUNTIF('02_工程タスク'!$A$4:$A$135,A13)<>1,"参照ID不正",IF(INDEX('02_工程タスク'!$G$4:$G$135,MATCH(A13,'02_工程タスク'!$A$4:$A$135,0))="","",INDEX('02_工程タスク'!$G$4:$G$135,MATCH(A13,'02_工程タスク'!$A$4:$A$135,0)))) -> R05, R04 | D13: =IF(COUNTIF('02_工程タスク'!$A$4:$A$135,A13)<>1,"参照ID不正",IF(INDEX('02_工程タスク'!$H$4:$H$135,MATCH(A13,'02_工程タスク'!$A$4:$A$135,0))="","",INDEX('02_工程タスク'!$H$4:$H$135,MATCH(A13,'02_工程タスク'!$A$4:$A$135,0)))) -> R02 | E13: S004 | F13: =IF(COUNTIF('07_スキル辞書'!$A$4:$A$109,E13)<>1,"参照ID不正",IF(INDEX('07_スキル辞書'!$D$4:$D$109,MATCH(E13,'07_スキル辞書'!$A$4:$A$109,0))="","",INDEX('07_スキル辞書'!$D$4:$D$109,MATCH(E13,'07_スキル辞書'!$A$4:$A$109,0)))) -> ヒアリングと課題定義 | G13: 2 | H13: =IF(COUNTIF('07_スキル辞書'!$A$4:$A$109,E13)<>1,"参照ID不正",IF(INDEX('07_スキル辞書'!$I$4:$I$109,MATCH(E13,'07_スキル辞書'!$A$4:$A$109,0))="","",INDEX('07_スキル辞書'!$I$4:$I$109,MATCH(E13,'07_スキル辞書'!$A$4:$A$109,0)))) -> ヒアリングリスト、ヒアリング記録、課題リスト（優先順位付き）、ヒアリング議事録、課題定義書 | I13: 役割ごとに必要な組合せを06/28で担当者へ割当。全員に全Skillを要求しない。
A14: B0-04 | B14: =IF(COUNTIF('02_工程タスク'!$A$4:$A$135,A14)<>1,"参照ID不正",IF(INDEX('02_工程タスク'!$D$4:$D$135,MATCH(A14,'02_工程タスク'!$A$4:$A$135,0))="","",INDEX('02_工程タスク'!$D$4:$D$135,MATCH(A14,'02_工程タスク'!$A$4:$A$135,0)))) -> インタビュー・現場観察 | C14: =IF(COUNTIF('02_工程タスク'!$A$4:$A$135,A14)<>1,"参照ID不正",IF(INDEX('02_工程タスク'!$G$4:$G$135,MATCH(A14,'02_工程タスク'!$A$4:$A$135,0))="","",INDEX('02_工程タスク'!$G$4:$G$135,MATCH(A14,'02_工程タスク'!$A$4:$A$135,0)))) -> R05, R04 | D14: =IF(COUNTIF('02_工程タスク'!$A$4:$A$135,A14)<>1,"参照ID不正",IF(INDEX('02_工程タスク'!$H$4:$H$135,MATCH(A14,'02_工程タスク'!$A$4:$A$135,0))="","",INDEX('02_工程タスク'!$H$4:$H$135,MATCH(A14,'02_工程タスク'!$A$4:$A$135,0)))) -> R02 | E14: S019 | F14: =IF(COUNTIF('07_スキル辞書'!$A$4:$A$109,E14)<>1,"参照ID不正",IF(INDEX('07_スキル辞書'!$D$4:$D$109,MATCH(E14,'07_スキル辞書'!$A$4:$A$109,0))="","",INDEX('07_スキル辞書'!$D$4:$D$109,MATCH(E14,'07_スキル辞書'!$A$4:$A$109,0)))) -> 業務フロー分析とHITL設計 | G14: 2 | H14: =IF(COUNTIF('07_スキル辞書'!$A$4:$A$109,E14)<>1,"参照ID不正",IF(INDEX('07_スキル辞書'!$I$4:$I$109,MATCH(E14,'07_スキル辞書'!$A$4:$A$109,0))="","",INDEX('07_スキル辞書'!$I$4:$I$109,MATCH(E14,'07_スキル辞書'!$A$4:$A$109,0)))) -> As-Is業務フロー図、To-Be業務フロー図、段階展開計画 | I14: 役割ごとに必要な組合せを06/28で担当者へ割当。全員に全Skillを要求しない。
A15: B0-04 | B15: =IF(COUNTIF('02_工程タスク'!$A$4:$A$135,A15)<>1,"参照ID不正",IF(INDEX('02_工程タスク'!$D$4:$D$135,MATCH(A15,'02_工程タスク'!$A$4:$A$135,0))="","",INDEX('02_工程タスク'!$D$4:$D$135,MATCH(A15,'02_工程タスク'!$A$4:$A$135,0)))) -> インタビュー・現場観察 | C15: =IF(COUNTIF('02_工程タスク'!$A$4:$A$135,A15)<>1,"参照ID不正",IF(INDEX('02_工程タスク'!$G$4:$G$135,MATCH(A15,'02_工程タスク'!$A$4:$A$135,0))="","",INDEX('02_工程タスク'!$G$4:$G$135,MATCH(A15,'02_工程タスク'!$A$4:$A$135,0)))) -> R05, R04 | D15: =IF(COUNTIF('02_工程タスク'!$A$4:$A$135,A15)<>1,"参照ID不正",IF(INDEX('02_工程タスク'!$H$4:$H$135,MATCH(A15,'02_工程タスク'!$A$4:$A$135,0))="","",INDEX('02_工程タスク'!$H$4:$H$135,MATCH(A15,'02_工程タスク'!$A$4:$A$135,0)))) -> R02 | E15: S082 | F15: =IF(COUNTIF('07_スキル辞書'!$A$4:$A$109,E15)<>1,"参照ID不正",IF(INDEX('07_スキル辞書'!$D$4:$D$109,MATCH(E15,'07_スキル辞書'!$A$4:$A$109,0))="","",INDEX('07_スキル辞書'!$D$4:$D$109,MATCH(E15,'07_スキル辞書'!$A$4:$A$109,0)))) -> 課題発見と需要の反証 | G15: 2 | H15: =IF(COUNTIF('07_スキル辞書'!$A$4:$A$109,E15)<>1,"参照ID不正",IF(INDEX('07_スキル辞書'!$I$4:$I$109,MATCH(E15,'07_スキル辞書'!$A$4:$A$109,0))="","",INDEX('07_スキル辞書'!$I$4:$I$109,MATCH(E15,'07_スキル辞書'!$A$4:$A$109,0)))) -> 観察記録・Opportunity Brief | I15: 役割ごとに必要な組合せを06/28で担当者へ割当。全員に全Skillを要求しない。
... A430: B6-11 | B430: =IF(COUNTIF('02_工程タスク'!$A$4:$A$135,A430)<>1,"参照ID不正",IF(INDEX('02_工程タスク'!$D$4:$D$135,MATCH(A430,'02_工程タスク'!$A$4:$A$135,0))="","",INDEX('02_工程タスク'!$D$4:$D$135,MATCH(A430,'02_工程タスク'!$A$4:$A$135,0)))) -> 保持期限到来・残存請求の追跡 | C430: =IF(COUNTIF('02_工程タスク'!$A$4:$A$135,A430)<>1,"参照ID不正",IF(INDEX('02_工程タスク'!$G$4:$G$135,MATCH(A430,'02_工程タスク'!$A$4:$A$135,0))="","",INDEX('02_工程タスク'!$G$4:$G$135,MATCH(A430,'02_工程タスク'!$A$4:$A$135,0)))) -> R18, R10, R15 | D430: =IF(COUNTIF('02_工程タスク'!$A$4:$A$135,A430)<>1,"参照ID不正",IF(INDEX('02_工程タスク'!$H$4:$H$135,MATCH(A430,'02_工程タスク'!$A$4:$A$135,0))="","",INDEX('02_工程タスク'!$H$4:$H$135,MATCH(A430,'02_工程タスク'!$A$4:$A$135,0)))) -> R18 | E430: S103 | F430: =IF(COUNTIF('07_スキル辞書'!$A$4:$A$109,E430)<>1,"参照ID不正",IF(INDEX('07_スキル辞書'!$D$4:$D$109,MATCH(E430,'07_スキル辞書'!$A$4:$A$109,0))="","",INDEX('07_スキル辞書'!$D$4:$D$109,MATCH(E430,'07_スキル辞書'!$A$4:$A$109,0)))) -> 移管・削除・権限失効・請求終了 | G430: 2 | H430: =IF(COUNTIF('07_スキル辞書'!$A$4:$A$109,E430)<>1,"参照ID不正",IF(INDEX('07_スキル辞書'!$I$4:$I$109,MATCH(E430,'07_スキル辞書'!$A$4:$A$109,0))="","",INDEX('07_スキル辞書'!$I$4:$I$109,MATCH(E430,'07_スキル辞書'!$A$4:$A$109,0)))) -> 廃止計画・Deletion/Retention・G5 | I430: 役割ごとに必要な組合せを06/28で担当者へ割当。全員に全Skillを要求しない。

Sheet 09_成果物・正本マップ
A1: 成果物・正本マップ｜証拠の所在を一つにつなぐ
A2: 1行=標準タスクの証拠パッケージ。独立した132文書は不要。Issue/ADR/PR/Eval/Releaseへ版付きリンクで代替できる。
A3: Evidence ID | B3: Task ID | C3: 成果物群 | D3: 推奨する正本 | E3: Ownerロール | F3: 最低限の証拠内容 | G3: 正本URI（入力） | H3: 対象版/hash（入力） | I3: 更新責任者（入力） | J3: 最終確認日（入力） | K3: 承認記録ID（入力）
A4: EV-B0-01 | B4: B0-01 | C4: 探索チャーター・初期予算枠 | D4: Versioned Docs/Issue＋業務台帳 | E4: R01 | F4: 責任者、探索上限、意思決定日、停止権限が記録されている。
A5: EV-B0-02 | B5: B0-02 | C5: 調査メモ・根拠一覧 | D5: Versioned Docs/Issue＋業務台帳 | E5: R02 | F5: 対象市場、利用者、競合、情報の確認日と不確実性がある。
A6: EV-B0-03 | B6: B0-03 | C6: 対象セグメント・調査計画 | D6: Versioned Docs/Issue＋業務台帳 | E6: R02 | F6: 対象者、募集条件、質問、個人情報取扱いが明確。
A7: EV-B0-04 | B7: B0-04 | C7: JTBD・観察記録 | D7: Versioned Docs/Issue＋業務台帳 | E7: R02 | F7: 現行の代替行動と未解決課題を記録し、反証も保存。
A8: EV-B0-05 | B8: B0-05 | C8: Opportunity Brief | D8: Versioned Docs/Issue＋業務台帳 | E8: R01 | F8: 価値仮説、非対象、代替手段との違いを説明できる。
A9: EV-B0-06 | B9: B0-06 | C9: 方式比較・仮ADR | D9: Versioned Docs/Issue＋業務台帳 | E9: R01 | F9: 品質、運用責任、権利、総費用、切替可能性を比較。
A10: EV-B0-07 | B10: B0-07 | C10: 初期Data Asset候補 | D10: Versioned Docs/Issue＋業務台帳 | E10: R10 | F10: 必要データと不足、権利未確認部分、取得計画がある。
A11: EV-B0-08 | B11: B0-08 | C11: 初期Risk Tier・法令スコープ | D11: Versioned Docs/Issue＋業務台帳 | E11: R01 | F11: 製品と開発Agentを別境界で評価し未確定条件を記録。
A12: EV-B0-09 | B12: B0-09 | C12: 価格仮説・価値交換モデル | D12: Versioned Docs/Issue＋業務台帳 | E12: R01 | F12: 誰が何に支払うか、代替価格、検証方法がある。
A13: EV-B0-10 | B13: B0-10 | C13: Business Case・原価仮説 | D13: Versioned Docs/Issue＋業務台帳 | E13: R01 | F13: 費用境界と仮定が明確で、AI一律削減を含まない。
A14: EV-B0-11 | B14: B0-11 | C14: 仮説・実験バックログ | D14: Versioned Docs/Issue＋業務台帳 | E14: R02 | F14: 成功だけでなく再検証・縮小・停止条件が事前定義。
A15: EV-B0-12 | B15: B0-12 | C15: 需要検証記録 | D15: Versioned Docs/Issue＋業務台帳 | E15: R02 | F15: 募集条件、観察結果、反証、次の判断がある。
... A135: EV-B6-11 | B135: B6-11 | C135: 廃止後残件・最終閉鎖 | D135: Versioned Docs/Issue＋業務台帳 | E135: R18 | F135: 全残件の処理又は正当な継続保存を確認。

Sheet 10_データ台帳
A1: データ台帳｜取得から派生・削除まで
A2: 1行=1データ資産。取得・投入・送信前に利用許可を確認。仮名加工と匿名加工を区別し、派生データまで追跡する。
A3: Data ID | B3: 名称・種類 | C3: Owner実名 | D3: 用途・目的 | E3: 個人情報区分 | F3: 仮名/匿名・加工状態 | G3: 取得元・出所URI | H3: 権利・利用条件 | I3: 学習利用可否 | J3: RAG利用可否 | K3: 外部送信先/依存ID | L3: 送信・処理国 | M3: 再委託先 | N3: 保存場所 | O3: 保持期間/起算点 | P3: 削除/保全方法 | Q3: 派生先ID（index/log等） | R3: 独立評価との分離 | S3: 利用承認者 | T3: 承認日 | U3: 根拠URI | V3: 最終確認日 | W3: 確認状態 | X3: 記録点検
X4: =IF(A4="","",IF(OR(C4="",D4="",E4="",G4="",H4="",N4="",O4="",P4="",S4="",T4="",U4=""),"利用根拠不足","記録あり・内容審査別"))
X5: =IF(A5="","",IF(OR(C5="",D5="",E5="",G5="",H5="",N5="",O5="",P5="",S5="",T5="",U5=""),"利用根拠不足","記録あり・内容審査別"))
X6: =IF(A6="","",IF(OR(C6="",D6="",E6="",G6="",H6="",N6="",O6="",P6="",S6="",T6="",U6=""),"利用根拠不足","記録あり・内容審査別"))
X7: =IF(A7="","",IF(OR(C7="",D7="",E7="",G7="",H7="",N7="",O7="",P7="",S7="",T7="",U7=""),"利用根拠不足","記録あり・内容審査別"))
X8: =IF(A8="","",IF(OR(C8="",D8="",E8="",G8="",H8="",N8="",O8="",P8="",S8="",T8="",U8=""),"利用根拠不足","記録あり・内容審査別"))
X9: =IF(A9="","",IF(OR(C9="",D9="",E9="",G9="",H9="",N9="",O9="",P9="",S9="",T9="",U9=""),"利用根拠不足","記録あり・内容審査別"))
X10: =IF(A10="","",IF(OR(C10="",D10="",E10="",G10="",H10="",N10="",O10="",P10="",S10="",T10="",U10=""),"利用根拠不足","記録あり・内容審査別"))
X11: =IF(A11="","",IF(OR(C11="",D11="",E11="",G11="",H11="",N11="",O11="",P11="",S11="",T11="",U11=""),"利用根拠不足","記録あり・内容審査別"))
X12: =IF(A12="","",IF(OR(C12="",D12="",E12="",G12="",H12="",N12="",O12="",P12="",S12="",T12="",U12=""),"利用根拠不足","記録あり・内容審査別"))
X13: =IF(A13="","",IF(OR(C13="",D13="",E13="",G13="",H13="",N13="",O13="",P13="",S13="",T13="",U13=""),"利用根拠不足","記録あり・内容審査別"))
X14: =IF(A14="","",IF(OR(C14="",D14="",E14="",G14="",H14="",N14="",O14="",P14="",S14="",T14="",U14=""),"利用根拠不足","記録あり・内容審査別"))
X15: =IF(A15="","",IF(OR(C15="",D15="",E15="",G15="",H15="",N15="",O15="",P15="",S15="",T15="",U15=""),"利用根拠不足","記録あり・内容審査別"))
... X43: =IF(A43="","",IF(OR(C43="",D43="",E43="",G43="",H43="",N43="",O43="",P43="",S43="",T43="",U43=""),"利用根拠不足","記録あり・内容審査別"))
A47: 記入時の重点
A48: 項目 | B48: 記入要領 | C48: 根拠
A49: 実データの投入前 | B49: 個人データ・営業秘密を未承認の開発Agent/評価/ログへ投入しない | C49: U01,W02,W03
A50: 派生の追跡 | B50: 原文→chunk→embedding/index→cache→trace/log→評価データをIDで接続 | C50: U01,U03
A51: 学習済みモデル | B51: 元データ削除だけで学習への影響が除去されたとしない。学習由来と対応方針を確認 | C51: U03
A52: 保全と削除 | B52: 法定保存/訴訟保全/バックアップ期限は削除と別の残存義務として管理 | C52: U01,U03

Sheet 11_モデル・外部AI・ベンダー台帳
A1: モデル・外部AI・ベンダー台帳｜依存の変更を見逃さない
A2: 1行=1依存/版。API・ローカルモデル・クラウド・MCP・Tool・Agent Skillを識別し、製品用と開発用を別記する。
A3: 依存ID | B3: 種類 | C3: 製品AI/開発AI | D3: 提供者・名称 | E3: model/tool/Skill ID | F3: 固定版/hash | G3: Owner実名 | H3: 利用目的 | I3: 処理地域 | J3: 送信データID | K3: 学習利用/保存条件 | L3: 再委託/telemetry | M3: 規約・契約ID | N3: EOL/変更通知 | O3: 可用性・制限 | P3: 原価・請求単位 | Q3: 代替/移行策 | R3: 許可操作・Scope | S3: 認証/秘密保管 | T3: 通信allowlist | U3: 供給元/知財 | V3: 評価Run ID | W3: 承認者・日付 | X3: 証拠URI | Y3: 最終確認日 | Z3: 状態
A47: 依存変更で再審査する条件
A48: 条件 | B48: 戻り先 | C48: 証拠
A49: モデル/Provider/地域/規約/EOLの変更 | B49: 12法務・13ADR・15/16評価・20変更 | C49: 性能/安全/原価/利用条件/移行の差分
A50: Tool追加・write権限・Skill scripts更新 | B50: 13設計・14実行Policy・19脅威・20変更 | C50: Scope、署名/由来、供給網、攻撃・回帰試験
A51: APIで固定版を指定できない | B51: 20変更・21監視で検知/再評価を設計 | C51: 監視対象・代替・変更後の評価Runと承認

Sheet 12_プライバシー・法令判定
A1: プライバシー・法令判定｜推奨事項を法律と混同しない
A2: 一般的な確認項目であり、個別法務判断を代替しない。対象国・役割・用途を入力し、法的禁止を経営判断で上書きしない。
A3: 判定ID | B3: 対象 | C3: 位置づけ | D3: 具体的な確認 | E3: 責任Role | F3: タイミング | G3: 適用判定 | H3: 判断・条件（入力） | I3: 実名権限者 | J3: 判断日 | K3: 根拠URI | L3: 再確認日 | M3: 根拠ID | N3: 公式URL
A4: L01 | B4: 提供国・役割・用途 | C4: 適用法のスコープ判定 | D4: 国/利用者/業種/データ/AI actor roleを確定。未指定のまま適合宣言しない | E4: R14 | F4: 取得/企画・変更時 | G4: 未判定 | M4: U01,W15 | N4: https://digital-strategy.ec.europa.eu/en/news/ai-omnibus-enters-force
A5: L02 | B5: 日本のAI方針・ガバナンス | C5: 法と任意指針を分ける | D5: 添付が挙げるAI法・内閣府指針は適用確認対象。W01の第1.2版指針だけを法律上の義務と扱わない | E5: R14 | F5: G0/G1 | G5: 未判定 | M5: U01,W01 | N5: https://www.meti.go.jp/shingikai/mono_info_service/ai_shakai_jisso/
A6: L03 | B6: 個人情報・利用目的 | C6: 法令/ガイドライン | D6: 情報区分、目的、取得方法、通知・同意等の要否、安全管理・委託先管理を判断 | E6: R14 | F6: 取得・利用前 | G6: 未判定 | M6: U01,W02,W03 | N6: https://www.ppc.go.jp/personalinfo/legal/guidelines_anonymous/ https://www.ppc.go.jp/personalinfo/legal/guidelines_offshore/
A7: L04 | B7: 仮名加工情報 | C7: 法令/ガイドライン | D7: 第三者提供の原則禁止と、法律上第三者に当たらない委託等を区別。通常の本人同意を万能な解除根拠にしない | E7: R14 | F7: 外部提供前 | G7: 未判定 | M7: W02 | N7: https://www.ppc.go.jp/personalinfo/legal/guidelines_anonymous/
A8: L05 | B8: 外国への提供/委託 | C8: 法令/ガイドライン | D8: 国内委託の整理とは別に、外国提供の例外・同意・相当措置等の適用を判断。送信先/国/再委託を特定 | E8: R14 | F8: 外部送信前 | G8: 未判定 | M8: W03 | N8: https://www.ppc.go.jp/personalinfo/legal/guidelines_offshore/
A9: L06 | B9: 基盤モデル・開発AI規約 | C9: 契約/利用条件 | D9: 学習利用、保持、地域、秘密情報、知財、免責、再委託、通知、削除条件を確認 | E9: R14 | F9: 購入/データ投入前 | G9: 未判定 | M9: U01
A10: L07 | B10: データ/コード/生成物の権利 | C10: 法令/契約/ライセンス | D10: 取得元、著作権・営業秘密、OSSライセンス、生成物の用途と権利不確実性を確認 | E10: R14 | F10: 取り込み/公開前 | G10: 未判定 | M10: U01,U03
A11: L08 | B11: 消費者/利用者への説明・救済 | C11: 用途/国に応じ法判定 | D11: AI利用、能力/限界、禁止用途、料金、問い合わせ、訂正・異議・返金等を設計 | E11: R14 | F11: 外販/公開前 | G11: 未判定 | M11: U01,U03
A12: L09 | B12: EU AI Act/Omnibus | C12: 対象該当時の法令判定 | D12: 提供/利用地域、禁止用途、高リスク/GPAI等の役割、経過措置と適用日を法務が記録。全サービス一律の期限を置かない | E12: R14 | F12: EU対象/重大変更 | G12: 未判定 | M12: W15 | N12: https://digital-strategy.ec.europa.eu/en/news/ai-omnibus-enters-force
A13: L10 | B13: 業法・高影響用途 | C13: 対象該当時の法令判定 | D13: 医療・金融・雇用・教育・生命身体等は専門家が資格、承認、監督、利用制限を判断 | E13: R14 | F13: G0/G1/用途変更 | G13: 未判定 | M13: U01
A14: L11 | B14: ISO/IEC 42001 | C14: 任意規格/契約指定時 | D14: 公開概要のみ確認。認証要否と正式規格本文の要求は組織が別途判定し、認証済みと表記しない | E14: R14 | F14: 組織方針決定時 | G14: 未判定 | M14: W16 | N14: https://www.iso.org/standard/42001
A15: L12 | B15: NIST/OWASP/MITRE | C15: 任意フレーム/技術指針 | D15: 脅威・評価・制御設計の参照。法令準拠や安全を自動保証するチェックリストではない | E15: R13 | F15: 設計/評価/変更 | G15: 未判定 | M15: W10,W11,W12,W13,W17,W18 | N15: https://www.nist.gov/publications/artificial-intelligence-risk-management-framework-generative-artificial-intelligence https://csrc.nist.gov/pubs/sp/800/218/a/final https://genai.owasp.org/resource/a-practical-guide-for-secure-mcp-server-development/ https://genai.owasp.org/resource/agent-control-standard-acs/ https://genai.owasp.org/resource/owasp-genai-llm-top-10-2026/ https://atlas.mitre.org/
A16: L13 | B16: 公開・マーケ表現 | C16: 法令/契約/実証の照合 | D16: 実測した能力を超える精度保証や自律性の表示をしない。宣伝の対象版・条件を証拠化 | E16: R14 | F16: GTM/公開前 | G16: 未判定 | M16: U03
A17: L14 | B17: 保存・削除・事故通知 | C17: 法令/契約/保全義務 | D17: 保存期間、本人請求、漏えい等の通知条件、法的保全、廃止後の残存責任を記録 | E17: R14 | F17: G1/運用/廃止 | G17: 未判定 | M17: U01,W02,W03 | N17: https://www.ppc.go.jp/personalinfo/legal/guidelines_anonymous/ https://www.ppc.go.jp/personalinfo/legal/guidelines_offshore/

Sheet 13_アーキテクチャ・ADR台帳
A1: アーキテクチャ・ADR台帳｜選択肢と再審査条件を残す
A2: 12件は検討テーマであり、決定済みADRではない。採用案・却下理由・影響・証拠を案件で記入する。
A3: ADR ID | B3: 検討テーマ | C3: 最低限検討する論点 | D3: 関連B-ID | E3: 採用案（入力） | F3: 比較/却下理由 | G3: Data/依存ID | H3: 原価/制約 | I3: 残存リスク | J3: 復旧/代替案 | K3: 見直しトリガー | L3: 決定者 | M3: 決定日 | N3: 版・正本URI | O3: 状態
A4: ADR01 | B4: AI適用/非AI代替 | C4: 非AI、ルール、検索、AIの価値/危害/原価比較 | D4: B0-06,B2-01 | O4: 未決定
A5: ADR02 | B5: Build/Buy/Partner | C5: 内製/購入/提携の差別化・データ・撤退容易性 | D5: B0-06,B1-13 | O5: 未決定
A6: ADR03 | B6: RAG/GraphRAG/Agent | C6: 単純な構成で足りない条件を実測。Graph/自律性の追加理由 | D6: B2-01,B2-04,B2-06 | O6: 未決定
A7: ADR04 | B7: Model/Provider/配置 | C7: モデル能力・ライセンス・処理地域・冗長性・EOL | D7: B2-02 | O7: 未決定
A8: ADR05 | B8: Data Flow/権利/削除 | C8: 入力から派生/ログ/評価/バックアップまで | D8: B2-03 | O8: 未決定
A9: ADR06 | B9: 権限・脅威境界 | C9: 製品Agentと開発Agentを別境界で設計 | D9: B2-07 | O9: 未決定
A10: ADR07 | B10: Human-AI UX/救済 | C10: 確認・保留・介入・再試行・同意・訂正 | D10: B2-08 | O10: 未決定
A11: ADR08 | B11: 品質と評価設計 | C11: 業務成否、grader、独立セット、重大失敗、回帰 | D11: B2-10 | O11: 未決定
A12: ADR09 | B12: 開発Harness/Skill | C12: Repo正本、Skill契約、実行権限、loop予算 | D12: B2-11,B2-12 | O12: 未決定
A13: ADR10 | B13: CI/観測/供給網 | C13: Agentが検証可能な環境と版・由来・署名 | D13: B2-11,B2-13,B2-15 | O13: 未決定
A14: ADR11 | B14: SLO/復旧/縮退 | C14: 性能、容量、provider障害、データ移行・補償 | D14: B1-08,B2-16 | O14: 未決定
A15: ADR12 | B15: 原価/課金/計測 | C15: cost/success、上限、料金、請求、分析イベント | D15: B2-17,B1-18 | O15: 未決定

Sheet 14_AI駆動開発・ハーネス標準
A1: AI駆動開発・ハーネス標準｜人が方向を定め実行を制御する
A2: 開発AIと製品AIの境界を別管理。宣言は実行認可ではない。下段AT01〜07は適用時の実試験仕様であり実施済みではない。
A3: 制御ID | B3: 対象 | C3: 標準 | D3: 実施内容 | E3: Owner | F3: 証拠 | G3: 関連Task | H3: 根拠ID | I3: 参照URL
A4: A01 | B4: 共通 | C4: Repo/Issueを正本にする | D4: 短いAgent指示は参照地図。仕様、ADR、テスト、Runbookを版管理し、更新責任者と鮮度を持つ | E4: R06 | F4: 正本URIと整合チェック | G4: B2-11,B3-01 | H4: U01,W06 | I4: https://openai.com/index/harness-engineering/
A5: A02 | B5: 共通 | C5: AgentごとのIdentity/Scope | D5: 共有管理者権限は禁止。サービスID/短期資格情報/最小権限/秘密保管/失効を設計 | E5: R13 | F5: IAM・資格情報ポリシー・拒否試験 | G5: B2-07,B3-04 | H5: U01,W12 | I5: https://genai.owasp.org/resource/a-practical-guide-for-secure-mcp-server-development/
A6: A03 | B6: 共通 | C6: Network/Tool制約を実行側で強制 | D6: 送信先allowlist、引数schema、認可、テナント分離を実装。Promptで禁止と書くだけにしない | E6: R13 | F6: runtime policyと越境/権限逸脱試験 | G6: B3-02,B3-11,B4-06 | H6: U01,W12,W13 | I6: https://genai.owasp.org/resource/a-practical-guide-for-secure-mcp-server-development/ https://genai.owasp.org/resource/agent-control-standard-acs/
A7: A04 | B7: 開発 | C7: 隔離sandbox/worktree | D7: 変更ごとにworkspaceと試験環境を分離。外部通信/データ/mountを制限。信頼しないコードを本番秘密で実行しない | E7: R12 | F7: workspace設定、隔離・破棄記録 | G7: B2-13,B3-02 | H7: U01,W06,W09 | I7: https://openai.com/index/harness-engineering/ https://www.anthropic.com/engineering/effective-harnesses-for-long-running-agents
A8: A05 | B8: 共通 | C8: 有限のループ予算 | D8: 時間、iteration、token、金額、retry、並列上限、タイムアウトを設定。改善しない/上限到達で停止・人へ移管 | E8: R06 | F8: 上限設定、停止・再開テスト | G8: B2-14,B3-04 | H8: U01,W04,W09 | I8: https://www.anthropic.com/engineering/building-effective-agents https://www.anthropic.com/engineering/effective-harnesses-for-long-running-agents
A9: A06 | B9: 共通 | C9: 高影響操作の人間承認 | D9: 金銭、権限、削除、外部送信の確認を実行直前に結び付ける。承認対象/期限/変更検知/取消を記録 | E9: R18 | F9: 操作ID・承認・実行結果の対応 | G9: B2-06,B3-11,B3-13 | H9: U01,W12 | I9: https://genai.owasp.org/resource/a-practical-guide-for-secure-mcp-server-development/
A10: A07 | B10: 共通 | C10: Skillの適用契約 | D10: 適用/非適用、前提、入力/出力、成功/停止、依存、権限、所有者を定義。人のS-ID習熟度とは別物 | E10: R06 | F10: SKILL.md等とschema・利用例 | G10: B2-12,B3-03 | H10: U01,U03,W14 | I10: https://agentskills.io/specification
A11: A08 | B11: 共通 | C11: Skillの供給網と評価 | D11: 信頼できる由来、ライセンス、版/hash、scripts/dependencies、悪性指示を審査。trigger/non-trigger、正常/敵対/回帰を試験 | E11: R13 | F11: Skill release、回帰Run、承認・撤回 | G11: B3-03,B5-18 | H11: U03,W14 | I11: https://agentskills.io/specification
A12: A09 | B12: 共通 | C12: 宣言と実行認可の分離 | D12: Skillのallowed-tools等の宣言は実行制御の代替ではない。対応が実験的/実装依存の項目はランタイムで検証 | E12: R13 | F12: 実装別の権限拒否試験 | G12: B3-02,B3-11 | H12: W14,U03 | I12: https://agentskills.io/specification
A13: A10 | B13: 共通 | C13: Context最小化・境界 | D13: 必要な情報だけ投入し、機密/古い記憶/検索文書内の指示を分離。要約による前提欠落をテスト | E13: R08 | F13: context版、出所、可視性、漏えい試験 | G13: B2-12,B3-10 | H13: U01,U03
A14: A11 | B14: 開発 | C14: CI/評価で閉じる修復ループ | D14: lint/型/単体/統合/安全/必要evalの失敗を修正。基準を緩めて通す変更は承認対象。上限後にIssueへ | E14: R11 | F14: CIログ、失敗分類、差分、再実行 | G14: B3-16,B3-17 | H14: U01,W06 | I14: https://openai.com/index/harness-engineering/
A15: A12 | B15: 共通 | C15: 独立評価とgrader較正 | D15: 生成者の自己採点を最終合否にしない。凍結セット隔離、複数trial、slice/不確実性、専門家との較正 | E15: R19 | F15: Eval計画・凍結版・人判定差異 | G15: B1-07,B3-07,B4-02 | H15: U01,W05 | I15: https://www.anthropic.com/engineering/demystifying-evals-for-ai-agents
A16: A13 | B16: 開発 | C16: 並列化・checkpoint・引継ぎ | D16: 競合しない小変更へ分割しworktree隔離。状態・未完・次アクション・検証結果を引き継ぐ。無条件の多Agent化はしない | E16: R06 | F16: task manifest、merge/review、checkpoint | G16: B3-05 | H16: U01,W09 | I16: https://www.anthropic.com/engineering/effective-harnesses-for-long-running-agents
A17: A14 | B17: 共通 | C17: Observe / reconstruct | D17: model、prompt、Skill、tool、data版、権限、承認、結果、コストを関連付ける。機密/私的思考を過剰収集せず保持を制御 | E17: R12 | F17: trace/manifest、欠損率、アクセス/保存 | G17: B3-15,B5-03 | H17: U01,W13 | I17: https://genai.owasp.org/resource/agent-control-standard-acs/
A18: A15 | B18: 共通 | C18: 停止・縮退・復旧 | D18: kill switch、read-only、手動対応、旧構成復元。副作用あるToolの重複/部分失敗/補償を検証 | E18: R18 | F18: Runbook、訓練、実復旧証拠 | G18: B3-19,B4-11 | H18: U01,W04 | I18: https://www.anthropic.com/engineering/building-effective-agents
A19: A16 | B19: 開発 | C19: AI効果のE2E計測 | D19: 準備/実装/レビュー/検証/手戻り/事故/費用込み。並列時の経過時間と人時間を分離 | E19: R15 | F19: 18比較データ、品質条件、差分 | G19: B3-22,B5-19 | H19: U01,W07,W08 | I19: https://metr.org/blog/2026-02-24-uplift-update/ https://dora.dev/ai/roi/calculator/
A23: 標準開発ループ（工程を横断して繰り返す）
A24: 順 | B24: ステップ | C24: 入力/処理 | D24: AIの担当 | E24: 人の担当 | F24: 停止・差戻し
A25: 01 | B25: Spec/Issue | C25: 価値・対象・禁止・Acceptance/Eval・変更範囲を定義 | D25: 要件草案・異常系候補 | E25: 人が受入基準を確定 | F25: 未承認の実データ/権限が必要なら止める
A26: 02 | B26: Plan/Context | C26: ADR/Skill/依存/試験/予算/正本を取得 | D26: 候補計画・小タスク分割 | E26: 高影響・設計差分を人が承認 | F26: 曖昧な前提や外部送信は確認へ
A27: 03 | B27: Execute | C27: 隔離環境で小変更、必要なToolのみ実行 | D27: コード/試験/文書/移行案 | E27: 高影響操作は実行時承認 | F27: 予算上限・許可外・危害兆候で停止
A28: 04 | B28: Verify | C28: CIと決定済みEvals、差分/攻撃/性能試験 | D28: 失敗再現・評価実行・ログ収集 | E28: grader/評価セット変更は審査 | F28: 単なる自己申告の成功を拒否
A29: 05 | B29: Bounded repair | C29: 失敗分類→最小修正→再評価を有限回 | D29: 修正PR・再試験 | E29: スコープ拡大/停止後再開を承認 | F29: 停滞/上限到達は人へ引継ぎ
A30: 06 | B30: Independent review | C30: 設計/コード/安全/独立評価を確認 | D30: 指摘候補・差分整理 | E30: 人の責任者が合否/マージ判断 | F30: 重大未解決・独立評価不合格は拒否
A31: 07 | B31: Release/Observe | C31: 対象版を固定し段階展開・指標監視 | D31: release準備/アラート整理 | E31: R18公開判断・停止/復旧 | F31: SLO/安全/原価の逸脱で縮退
A32: 08 | B32: Learn/Skill update | C32: 本番失敗を回帰例へ、再利用手順をSkillへ | D32: 改善案・Skill/文書差分 | E32: 利用目的/権限/基準変更多は再審査 | F32: 本番ログを無許可で学習へ流用しない
A35: Agent/Skill実行設定（実運用値を記入）
A36: 設定 | B36: 値（入力） | C36: 確認事項 | D36: Owner（入力） | E36: 承認URI（入力） | F36: 確認日
A37: 実行Runtime/境界 | C37: 製品/開発で別のID・権限
A38: 利用Skill/固定版 | C38: 11依存台帳のIDを指定
A39: Tool/Network allowlist | C39: 宣言ではなく実行側の制御URI
A40: 時間・iteration・retry上限 | C40: 単位を付ける。未指定の無限loopは禁止
A41: token/金額/並列上限 | C41: 課金単位・超過停止・オーナー
A42: Human Approval操作 | C42: 対象操作・Scope・有効期限・取消
A43: checkpoint/再開 | C43: 状態・失敗・予算残と重複実行防止
A44: 停止/復旧・連絡先 | C44: 実地確認日とRunbookを接続
A47: 試験ID | B47: 適用 | C47: 試験テーマ | D47: 具体的な負の試験／受入条件 | E47: Owner | F47: 保存する証拠 | G47: 関連Task | H47: 根拠 | I47: 実案件実行
A48: AT01 | B48: 子Agent使用時 | C48: 親子予算を合算 | D48: 親＋全子の時間・token・金額を集約。各子は上限内でも合計超過で新規操作停止。retry・再開で残予算をリセットしない。 | E48: R06 | F48: 親子RunID、上限、支出イベント、拒否ログ | G48: B2-14,B3-04,B4-04 | H48: AR22 / 既存W05・W14 | I48: 未実施：案件側で実行
A49: AT02 | B49: 子Agent使用時 | C49: 委譲権限を拡大させない | D49: 子のScopeを親以下に制限。親より広いTool・引数・送信先・資格情報の利用要求を拒否する。 | E49: R13 | F49: Scope差分、権限昇格拒否、監査ログ | G49: B3-11,B4-06 | H49: AR22 | I49: 未実施：案件側で実行
A50: AT03 | B50: 子Agent使用時 | C50: 停止伝播と競合 | D50: 親の停止／取消後に子の新規副作用を拒否。既に進行中の非取消処理は隔離・補償・結果確認し、停止の成功宣言だけで完了しない。 | E50: R18 | F50: 停止時刻、各子状態、未完副作用、補償証拠 | G50: B3-19,B4-11 | H50: AR22 | I50: 未実施：案件側で実行
A51: AT04 | B51: 共有メモリ使用時 | C51: 利用者・Run間の隔離 | D51: 他利用者／過去Runのメモリ・Tool出力・悪性指示を混入させ、越境読出し・権限変更・履歴再利用を拒否する。 | E51: R13 | F51: メモリnamespace、攻撃入力、拒否と正例 | G51: B3-10,B4-06 | H51: AR22 | I51: 未実施：案件側で実行
A52: AT05 | B52: 副作用あるTool | C52: 冪等性・部分失敗 | D52: 同一業務をretry／子Agentが重複送信しても二重決済等を起こさない。部分失敗の補償・人への移管を実外部状態で確認。 | E52: R08 | F52: 業務ID、冪等キー、外部状態差分、補償 | G52: B3-11,B4-04 | H52: AR22・AR23 | I52: 未実施：案件側で実行
A53: AT06 | B53: Agent評価 | C53: 清浄状態と汚染状態 | D53: TrialごとにDB/cache/file/memoryの初期Snapshotを復元しReset成否を検査。前試行の残状態を故意に入れ、検出・無効化されることを確認。 | E53: R11 | F53: TrialID、FixtureID、Reset、外部差分、失敗 | G53: B4-04,B3-17 | H53: AR23 / 既存W05 | I53: 未実施：案件側で実行
A54: AT07 | B54: 反復試行する評価 | C54: 成功率の意味 | D54: 一回成功率、k試行で一度以上成功する率、全試行で成功する率を混同しない。部分成功・手動補正・retry・失敗の分母と費用を記録。 | E54: R19 | F54: 採点定義、試行構造、母数、区間、費用 | G54: B4-04,B4-13 | H54: AR23 / 既存W05 | I54: 未実施：案件側で実行

Sheet 15_評価計画・品質ゲート
A1: 評価計画・品質ゲート｜閾値は評価前に固定する
A2: 分類は32、計画はPlanID@版。複数機能・版を予約行4〜103へ追加。承認後の上書きをせず新しい版を作る。
A3: EvalType | B3: 評価軸 | C3: 指標候補 | D3: 設計上の要点 | E3: 適用条件 | F3: 設計Role | G3: 母集団/分母（入力） | H3: slice/標本/反復 | I3: 比較対象・版 | J3: 合格閾値/方向 | K3: 重大失敗条件 | L3: 評価Data ID/凍結版 | M3: grader/較正方式 | N3: 独立評価者 | O3: 計画承認URI | P3: 状態 | Q3: 根拠ID | R3: EvalPlan ID | S3: 計画版 | T3: 対象機能／業務 | U3: 対象ManifestHash | V3: PlanKey（自動） | W3: 計画記録点検 | X3: 初期状態／Fixture定義URI | Y3: Reset・副作用検査 | Z3: 試行成功率の定義
A4: E01 | B4: =IF(A4="","",IF(COUNTIF('32_定義マスター'!$A$13:$A$30,A4)<>1,"参照ID不正",IF(INDEX('32_定義マスター'!$B$13:$B$30,MATCH(A4,'32_定義マスター'!$A$13:$A$30,0))="","",INDEX('32_定義マスター'!$B$13:$B$30,MATCH(A4,'32_定義マスター'!$A$13:$A$30,0))))) -> 業務価値 | C4: =IF(A4="","",IF(COUNTIF('32_定義マスター'!$A$13:$A$30,A4)<>1,"参照ID不正",IF(INDEX('32_定義マスター'!$C$13:$C$30,MATCH(A4,'32_定義マスター'!$A$13:$A$30,0))="","",INDEX('32_定義マスター'!$C$13:$C$30,MATCH(A4,'32_定義マスター'!$A$13:$A$30,0))))) -> 利用者が対象業務を正しく完了した割合 | D4: =IF(A4="","",IF(COUNTIF('32_定義マスター'!$A$13:$A$30,A4)<>1,"参照ID不正",IF(INDEX('32_定義マスター'!$D$13:$D$30,MATCH(A4,'32_定義マスター'!$A$13:$A$30,0))="","",INDEX('32_定義マスター'!$D$13:$D$30,MATCH(A4,'32_定義マスター'!$A$13:$A$30,0))))) -> 非AI/現行と同条件で比較。手動補正/失敗の扱いを定義 | E4: =IF(A4="","",IF(COUNTIF('32_定義マスター'!$A$13:$A$30,A4)<>1,"参照ID不正",IF(INDEX('32_定義マスター'!$E$13:$E$30,MATCH(A4,'32_定義マスター'!$A$13:$A$30,0))="","",INDEX('32_定義マスター'!$E$13:$E$30,MATCH(A4,'32_定義マスター'!$A$13:$A$30,0))))) -> 全 | F4: =IF(A4="","",IF(COUNTIF('32_定義マスター'!$A$13:$A$30,A4)<>1,"参照ID不正",IF(INDEX('32_定義マスター'!$F$13:$F$30,MATCH(A4,'32_定義マスター'!$A$13:$A$30,0))="","",INDEX('32_定義マスター'!$F$13:$F$30,MATCH(A4,'32_定義マスター'!$A$13:$A$30,0))))) -> R04,R11 | P4: 未設定 | Q4: =IF(A4="","",IF(COUNTIF('32_定義マスター'!$A$13:$A$30,A4)<>1,"参照ID不正",IF(INDEX('32_定義マスター'!$G$13:$G$30,MATCH(A4,'32_定義マスター'!$A$13:$A$30,0))="","",INDEX('32_定義マスター'!$G$13:$G$30,MATCH(A4,'32_定義マスター'!$A$13:$A$30,0))))) -> U01 | R4: EP-001 | S4: 1 | V4: =IF(OR(R4="",S4=""),"",R4&"@"&S4) -> EP-001@1 | W4: =IF(A4="","",IF(COUNTIF('32_定義マスター'!$A$13:$A$30,A4)<>1,"EvalType不正",IF(OR(V4="",COUNTIF($V$4:$V$103,V4)<>1),"PlanKey不足・重複",IF(OR(P4="",P4="未設定",P4="設計中",P4="改訂中"),"計画未確定",IF(AND(P4<>"承認",P4<>"対象外承認"),"状態不正",IF(OR(T4="",U4="",O4=""),"計画対象・承認不足",IF(P4="対象外承認",IF(G4="","対象外理由不足","対象外計画記録"),IF(OR(G4="",H4="",I4="",J4="",K4="",L4="",M4="",N4=""),"評価設計不足",IF(AND(A4="E05",OR(X4="",Y4="",Z4="")),"試行状態・成功定義不足","計画記録あり"))))))))) -> 計画未確定
A5: E02 | B5: =IF(A5="","",IF(COUNTIF('32_定義マスター'!$A$13:$A$30,A5)<>1,"参照ID不正",IF(INDEX('32_定義マスター'!$B$13:$B$30,MATCH(A5,'32_定義マスター'!$A$13:$A$30,0))="","",INDEX('32_定義マスター'!$B$13:$B$30,MATCH(A5,'32_定義マスター'!$A$13:$A$30,0))))) -> AI出力 | C5: =IF(A5="","",IF(COUNTIF('32_定義マスター'!$A$13:$A$30,A5)<>1,"参照ID不正",IF(INDEX('32_定義マスター'!$C$13:$C$30,MATCH(A5,'32_定義マスター'!$A$13:$A$30,0))="","",INDEX('32_定義マスター'!$C$13:$C$30,MATCH(A5,'32_定義マスター'!$A$13:$A$30,0))))) -> 正確性/適合性/業務別誤りコスト | D5: =IF(A5="","",IF(COUNTIF('32_定義マスター'!$A$13:$A$30,A5)<>1,"参照ID不正",IF(INDEX('32_定義マスター'!$D$13:$D$30,MATCH(A5,'32_定義マスター'!$A$13:$A$30,0))="","",INDEX('32_定義マスター'!$D$13:$D$30,MATCH(A5,'32_定義マスター'!$A$13:$A$30,0))))) -> 用途に応じAccuracy/F1等を選択。少数重大例を平均で隠さない | E5: =IF(A5="","",IF(COUNTIF('32_定義マスター'!$A$13:$A$30,A5)<>1,"参照ID不正",IF(INDEX('32_定義マスター'!$E$13:$E$30,MATCH(A5,'32_定義マスター'!$A$13:$A$30,0))="","",INDEX('32_定義マスター'!$E$13:$E$30,MATCH(A5,'32_定義マスター'!$A$13:$A$30,0))))) -> AI | F5: =IF(A5="","",IF(COUNTIF('32_定義マスター'!$A$13:$A$30,A5)<>1,"参照ID不正",IF(INDEX('32_定義マスター'!$F$13:$F$30,MATCH(A5,'32_定義マスター'!$A$13:$A$30,0))="","",INDEX('32_定義マスター'!$F$13:$F$30,MATCH(A5,'32_定義マスター'!$A$13:$A$30,0))))) -> R08,R11 | P5: 未設定 | Q5: =IF(A5="","",IF(COUNTIF('32_定義マスター'!$A$13:$A$30,A5)<>1,"参照ID不正",IF(INDEX('32_定義マスター'!$G$13:$G$30,MATCH(A5,'32_定義マスター'!$A$13:$A$30,0))="","",INDEX('32_定義マスター'!$G$13:$G$30,MATCH(A5,'32_定義マスター'!$A$13:$A$30,0))))) -> U01,W05 | R5: EP-002 | S5: 1 | V5: =IF(OR(R5="",S5=""),"",R5&"@"&S5) -> EP-002@1 | W5: =IF(A5="","",IF(COUNTIF('32_定義マスター'!$A$13:$A$30,A5)<>1,"EvalType不正",IF(OR(V5="",COUNTIF($V$4:$V$103,V5)<>1),"PlanKey不足・重複",IF(OR(P5="",P5="未設定",P5="設計中",P5="改訂中"),"計画未確定",IF(AND(P5<>"承認",P5<>"対象外承認"),"状態不正",IF(OR(T5="",U5="",O5=""),"計画対象・承認不足",IF(P5="対象外承認",IF(G5="","対象外理由不足","対象外計画記録"),IF(OR(G5="",H5="",I5="",J5="",K5="",L5="",M5="",N5=""),"評価設計不足",IF(AND(A5="E05",OR(X5="",Y5="",Z5="")),"試行状態・成功定義不足","計画記録あり"))))))))) -> 計画未確定
A6: E03 | B6: =IF(A6="","",IF(COUNTIF('32_定義マスター'!$A$13:$A$30,A6)<>1,"参照ID不正",IF(INDEX('32_定義マスター'!$B$13:$B$30,MATCH(A6,'32_定義マスター'!$A$13:$A$30,0))="","",INDEX('32_定義マスター'!$B$13:$B$30,MATCH(A6,'32_定義マスター'!$A$13:$A$30,0))))) -> RAG検索 | C6: =IF(A6="","",IF(COUNTIF('32_定義マスター'!$A$13:$A$30,A6)<>1,"参照ID不正",IF(INDEX('32_定義マスター'!$C$13:$C$30,MATCH(A6,'32_定義マスター'!$A$13:$A$30,0))="","",INDEX('32_定義マスター'!$C$13:$C$30,MATCH(A6,'32_定義マスター'!$A$13:$A$30,0))))) -> 検索Recall/根拠到達/権限遵守 | D6: =IF(A6="","",IF(COUNTIF('32_定義マスター'!$A$13:$A$30,A6)<>1,"参照ID不正",IF(INDEX('32_定義マスター'!$D$13:$D$30,MATCH(A6,'32_定義マスター'!$A$13:$A$30,0))="","",INDEX('32_定義マスター'!$D$13:$D$30,MATCH(A6,'32_定義マスター'!$A$13:$A$30,0))))) -> 正解文書ID・母集団・権限制御・更新鮮度 | E6: =IF(A6="","",IF(COUNTIF('32_定義マスター'!$A$13:$A$30,A6)<>1,"参照ID不正",IF(INDEX('32_定義マスター'!$E$13:$E$30,MATCH(A6,'32_定義マスター'!$A$13:$A$30,0))="","",INDEX('32_定義マスター'!$E$13:$E$30,MATCH(A6,'32_定義マスター'!$A$13:$A$30,0))))) -> RAG | F6: =IF(A6="","",IF(COUNTIF('32_定義マスター'!$A$13:$A$30,A6)<>1,"参照ID不正",IF(INDEX('32_定義マスター'!$F$13:$F$30,MATCH(A6,'32_定義マスター'!$A$13:$A$30,0))="","",INDEX('32_定義マスター'!$F$13:$F$30,MATCH(A6,'32_定義マスター'!$A$13:$A$30,0))))) -> R09,R11 | P6: 未設定 | Q6: =IF(A6="","",IF(COUNTIF('32_定義マスター'!$A$13:$A$30,A6)<>1,"参照ID不正",IF(INDEX('32_定義マスター'!$G$13:$G$30,MATCH(A6,'32_定義マスター'!$A$13:$A$30,0))="","",INDEX('32_定義マスター'!$G$13:$G$30,MATCH(A6,'32_定義マスター'!$A$13:$A$30,0))))) -> U01 | R6: EP-003 | S6: 1 | V6: =IF(OR(R6="",S6=""),"",R6&"@"&S6) -> EP-003@1 | W6: =IF(A6="","",IF(COUNTIF('32_定義マスター'!$A$13:$A$30,A6)<>1,"EvalType不正",IF(OR(V6="",COUNTIF($V$4:$V$103,V6)<>1),"PlanKey不足・重複",IF(OR(P6="",P6="未設定",P6="設計中",P6="改訂中"),"計画未確定",IF(AND(P6<>"承認",P6<>"対象外承認"),"状態不正",IF(OR(T6="",U6="",O6=""),"計画対象・承認不足",IF(P6="対象外承認",IF(G6="","対象外理由不足","対象外計画記録"),IF(OR(G6="",H6="",I6="",J6="",K6="",L6="",M6="",N6=""),"評価設計不足",IF(AND(A6="E05",OR(X6="",Y6="",Z6="")),"試行状態・成功定義不足","計画記録あり"))))))))) -> 計画未確定
A7: E04 | B7: =IF(A7="","",IF(COUNTIF('32_定義マスター'!$A$13:$A$30,A7)<>1,"参照ID不正",IF(INDEX('32_定義マスター'!$B$13:$B$30,MATCH(A7,'32_定義マスター'!$A$13:$A$30,0))="","",INDEX('32_定義マスター'!$B$13:$B$30,MATCH(A7,'32_定義マスター'!$A$13:$A$30,0))))) -> RAG回答 | C7: =IF(A7="","",IF(COUNTIF('32_定義マスター'!$A$13:$A$30,A7)<>1,"参照ID不正",IF(INDEX('32_定義マスター'!$C$13:$C$30,MATCH(A7,'32_定義マスター'!$A$13:$A$30,0))="","",INDEX('32_定義マスター'!$C$13:$C$30,MATCH(A7,'32_定義マスター'!$A$13:$A$30,0))))) -> 根拠整合/引用/回答保留 | D7: =IF(A7="","",IF(COUNTIF('32_定義マスター'!$A$13:$A$30,A7)<>1,"参照ID不正",IF(INDEX('32_定義マスター'!$D$13:$D$30,MATCH(A7,'32_定義マスター'!$A$13:$A$30,0))="","",INDEX('32_定義マスター'!$D$13:$D$30,MATCH(A7,'32_定義マスター'!$A$13:$A$30,0))))) -> 検索と生成を分離。答えが存在しない/古い/矛盾する場合を含む | E7: =IF(A7="","",IF(COUNTIF('32_定義マスター'!$A$13:$A$30,A7)<>1,"参照ID不正",IF(INDEX('32_定義マスター'!$E$13:$E$30,MATCH(A7,'32_定義マスター'!$A$13:$A$30,0))="","",INDEX('32_定義マスター'!$E$13:$E$30,MATCH(A7,'32_定義マスター'!$A$13:$A$30,0))))) -> RAG | F7: =IF(A7="","",IF(COUNTIF('32_定義マスター'!$A$13:$A$30,A7)<>1,"参照ID不正",IF(INDEX('32_定義マスター'!$F$13:$F$30,MATCH(A7,'32_定義マスター'!$A$13:$A$30,0))="","",INDEX('32_定義マスター'!$F$13:$F$30,MATCH(A7,'32_定義マスター'!$A$13:$A$30,0))))) -> R04,R11 | P7: 未設定 | Q7: =IF(A7="","",IF(COUNTIF('32_定義マスター'!$A$13:$A$30,A7)<>1,"参照ID不正",IF(INDEX('32_定義マスター'!$G$13:$G$30,MATCH(A7,'32_定義マスター'!$A$13:$A$30,0))="","",INDEX('32_定義マスター'!$G$13:$G$30,MATCH(A7,'32_定義マスター'!$A$13:$A$30,0))))) -> U01 | R7: EP-004 | S7: 1 | V7: =IF(OR(R7="",S7=""),"",R7&"@"&S7) -> EP-004@1 | W7: =IF(A7="","",IF(COUNTIF('32_定義マスター'!$A$13:$A$30,A7)<>1,"EvalType不正",IF(OR(V7="",COUNTIF($V$4:$V$103,V7)<>1),"PlanKey不足・重複",IF(OR(P7="",P7="未設定",P7="設計中",P7="改訂中"),"計画未確定",IF(AND(P7<>"承認",P7<>"対象外承認"),"状態不正",IF(OR(T7="",U7="",O7=""),"計画対象・承認不足",IF(P7="対象外承認",IF(G7="","対象外理由不足","対象外計画記録"),IF(OR(G7="",H7="",I7="",J7="",K7="",L7="",M7="",N7=""),"評価設計不足",IF(AND(A7="E05",OR(X7="",Y7="",Z7="")),"試行状態・成功定義不足","計画記録あり"))))))))) -> 計画未確定
A8: E05 | B8: =IF(A8="","",IF(COUNTIF('32_定義マスター'!$A$13:$A$30,A8)<>1,"参照ID不正",IF(INDEX('32_定義マスター'!$B$13:$B$30,MATCH(A8,'32_定義マスター'!$A$13:$A$30,0))="","",INDEX('32_定義マスター'!$B$13:$B$30,MATCH(A8,'32_定義マスター'!$A$13:$A$30,0))))) -> Agent成否 | C8: =IF(A8="","",IF(COUNTIF('32_定義マスター'!$A$13:$A$30,A8)<>1,"参照ID不正",IF(INDEX('32_定義マスター'!$C$13:$C$30,MATCH(A8,'32_定義マスター'!$A$13:$A$30,0))="","",INDEX('32_定義マスター'!$C$13:$C$30,MATCH(A8,'32_定義マスター'!$A$13:$A$30,0))))) -> タスク成否と実世界の副作用 | D8: =IF(A8="","",IF(COUNTIF('32_定義マスター'!$A$13:$A$30,A8)<>1,"参照ID不正",IF(INDEX('32_定義マスター'!$D$13:$D$30,MATCH(A8,'32_定義マスター'!$A$13:$A$30,0))="","",INDEX('32_定義マスター'!$D$13:$D$30,MATCH(A8,'32_定義マスター'!$A$13:$A$30,0))))) -> 単なる最終文の成功宣言ではなく外部状態を検証 | E8: =IF(A8="","",IF(COUNTIF('32_定義マスター'!$A$13:$A$30,A8)<>1,"参照ID不正",IF(INDEX('32_定義マスター'!$E$13:$E$30,MATCH(A8,'32_定義マスター'!$A$13:$A$30,0))="","",INDEX('32_定義マスター'!$E$13:$E$30,MATCH(A8,'32_定義マスター'!$A$13:$A$30,0))))) -> Agent | F8: =IF(A8="","",IF(COUNTIF('32_定義マスター'!$A$13:$A$30,A8)<>1,"参照ID不正",IF(INDEX('32_定義マスター'!$F$13:$F$30,MATCH(A8,'32_定義マスター'!$A$13:$A$30,0))="","",INDEX('32_定義マスター'!$F$13:$F$30,MATCH(A8,'32_定義マスター'!$A$13:$A$30,0))))) -> R11 | P8: 未設定 | Q8: =IF(A8="","",IF(COUNTIF('32_定義マスター'!$A$13:$A$30,A8)<>1,"参照ID不正",IF(INDEX('32_定義マスター'!$G$13:$G$30,MATCH(A8,'32_定義マスター'!$A$13:$A$30,0))="","",INDEX('32_定義マスター'!$G$13:$G$30,MATCH(A8,'32_定義マスター'!$A$13:$A$30,0))))) -> W05 | R8: EP-005 | S8: 1 | V8: =IF(OR(R8="",S8=""),"",R8&"@"&S8) -> EP-005@1 | W8: =IF(A8="","",IF(COUNTIF('32_定義マスター'!$A$13:$A$30,A8)<>1,"EvalType不正",IF(OR(V8="",COUNTIF($V$4:$V$103,V8)<>1),"PlanKey不足・重複",IF(OR(P8="",P8="未設定",P8="設計中",P8="改訂中"),"計画未確定",IF(AND(P8<>"承認",P8<>"対象外承認"),"状態不正",IF(OR(T8="",U8="",O8=""),"計画対象・承認不足",IF(P8="対象外承認",IF(G8="","対象外理由不足","対象外計画記録"),IF(OR(G8="",H8="",I8="",J8="",K8="",L8="",M8="",N8=""),"評価設計不足",IF(AND(A8="E05",OR(X8="",Y8="",Z8="")),"試行状態・成功定義不足","計画記録あり"))))))))) -> 計画未確定
A9: E06 | B9: =IF(A9="","",IF(COUNTIF('32_定義マスター'!$A$13:$A$30,A9)<>1,"参照ID不正",IF(INDEX('32_定義マスター'!$B$13:$B$30,MATCH(A9,'32_定義マスター'!$A$13:$A$30,0))="","",INDEX('32_定義マスター'!$B$13:$B$30,MATCH(A9,'32_定義マスター'!$A$13:$A$30,0))))) -> 安全性 | C9: =IF(A9="","",IF(COUNTIF('32_定義マスター'!$A$13:$A$30,A9)<>1,"参照ID不正",IF(INDEX('32_定義マスター'!$C$13:$C$30,MATCH(A9,'32_定義マスター'!$A$13:$A$30,0))="","",INDEX('32_定義マスター'!$C$13:$C$30,MATCH(A9,'32_定義マスター'!$A$13:$A$30,0))))) -> 重大失敗・禁止操作・危険出力 | D9: =IF(A9="","",IF(COUNTIF('32_定義マスター'!$A$13:$A$30,A9)<>1,"参照ID不正",IF(INDEX('32_定義マスター'!$D$13:$D$30,MATCH(A9,'32_定義マスター'!$A$13:$A$30,0))="","",INDEX('32_定義マスター'!$D$13:$D$30,MATCH(A9,'32_定義マスター'!$A$13:$A$30,0))))) -> 重大と定義した試験の失敗0を初期案。0件はリスク0の証明ではない | E9: =IF(A9="","",IF(COUNTIF('32_定義マスター'!$A$13:$A$30,A9)<>1,"参照ID不正",IF(INDEX('32_定義マスター'!$E$13:$E$30,MATCH(A9,'32_定義マスター'!$A$13:$A$30,0))="","",INDEX('32_定義マスター'!$E$13:$E$30,MATCH(A9,'32_定義マスター'!$A$13:$A$30,0))))) -> 全 | F9: =IF(A9="","",IF(COUNTIF('32_定義マスター'!$A$13:$A$30,A9)<>1,"参照ID不正",IF(INDEX('32_定義マスター'!$F$13:$F$30,MATCH(A9,'32_定義マスター'!$A$13:$A$30,0))="","",INDEX('32_定義マスター'!$F$13:$F$30,MATCH(A9,'32_定義マスター'!$A$13:$A$30,0))))) -> R19 | P9: 未設定 | Q9: =IF(A9="","",IF(COUNTIF('32_定義マスター'!$A$13:$A$30,A9)<>1,"参照ID不正",IF(INDEX('32_定義マスター'!$G$13:$G$30,MATCH(A9,'32_定義マスター'!$A$13:$A$30,0))="","",INDEX('32_定義マスター'!$G$13:$G$30,MATCH(A9,'32_定義マスター'!$A$13:$A$30,0))))) -> U01 | R9: EP-006 | S9: 1 | V9: =IF(OR(R9="",S9=""),"",R9&"@"&S9) -> EP-006@1 | W9: =IF(A9="","",IF(COUNTIF('32_定義マスター'!$A$13:$A$30,A9)<>1,"EvalType不正",IF(OR(V9="",COUNTIF($V$4:$V$103,V9)<>1),"PlanKey不足・重複",IF(OR(P9="",P9="未設定",P9="設計中",P9="改訂中"),"計画未確定",IF(AND(P9<>"承認",P9<>"対象外承認"),"状態不正",IF(OR(T9="",U9="",O9=""),"計画対象・承認不足",IF(P9="対象外承認",IF(G9="","対象外理由不足","対象外計画記録"),IF(OR(G9="",H9="",I9="",J9="",K9="",L9="",M9="",N9=""),"評価設計不足",IF(AND(A9="E05",OR(X9="",Y9="",Z9="")),"試行状態・成功定義不足","計画記録あり"))))))))) -> 計画未確定
A10: E07 | B10: =IF(A10="","",IF(COUNTIF('32_定義マスター'!$A$13:$A$30,A10)<>1,"参照ID不正",IF(INDEX('32_定義マスター'!$B$13:$B$30,MATCH(A10,'32_定義マスター'!$A$13:$A$30,0))="","",INDEX('32_定義マスター'!$B$13:$B$30,MATCH(A10,'32_定義マスター'!$A$13:$A$30,0))))) -> Security | C10: =IF(A10="","",IF(COUNTIF('32_定義マスター'!$A$13:$A$30,A10)<>1,"参照ID不正",IF(INDEX('32_定義マスター'!$C$13:$C$30,MATCH(A10,'32_定義マスター'!$A$13:$A$30,0))="","",INDEX('32_定義マスター'!$C$13:$C$30,MATCH(A10,'32_定義マスター'!$A$13:$A$30,0))))) -> 越権/秘密流出/injection/Tool悪用 | D10: =IF(A10="","",IF(COUNTIF('32_定義マスター'!$A$13:$A$30,A10)<>1,"参照ID不正",IF(INDEX('32_定義マスター'!$D$13:$D$30,MATCH(A10,'32_定義マスター'!$A$13:$A$30,0))="","",INDEX('32_定義マスター'!$D$13:$D$30,MATCH(A10,'32_定義マスター'!$A$13:$A$30,0))))) -> 製品と開発の境界、ログ/MCP/sub-agentを含む | E10: =IF(A10="","",IF(COUNTIF('32_定義マスター'!$A$13:$A$30,A10)<>1,"参照ID不正",IF(INDEX('32_定義マスター'!$E$13:$E$30,MATCH(A10,'32_定義マスター'!$A$13:$A$30,0))="","",INDEX('32_定義マスター'!$E$13:$E$30,MATCH(A10,'32_定義マスター'!$A$13:$A$30,0))))) -> 全 | F10: =IF(A10="","",IF(COUNTIF('32_定義マスター'!$A$13:$A$30,A10)<>1,"参照ID不正",IF(INDEX('32_定義マスター'!$F$13:$F$30,MATCH(A10,'32_定義マスター'!$A$13:$A$30,0))="","",INDEX('32_定義マスター'!$F$13:$F$30,MATCH(A10,'32_定義マスター'!$A$13:$A$30,0))))) -> R13 | P10: 未設定 | Q10: =IF(A10="","",IF(COUNTIF('32_定義マスター'!$A$13:$A$30,A10)<>1,"参照ID不正",IF(INDEX('32_定義マスター'!$G$13:$G$30,MATCH(A10,'32_定義マスター'!$A$13:$A$30,0))="","",INDEX('32_定義マスター'!$G$13:$G$30,MATCH(A10,'32_定義マスター'!$A$13:$A$30,0))))) -> U01,W12,W17 | R10: EP-007 | S10: 1 | V10: =IF(OR(R10="",S10=""),"",R10&"@"&S10) -> EP-007@1 | W10: =IF(A10="","",IF(COUNTIF('32_定義マスター'!$A$13:$A$30,A10)<>1,"EvalType不正",IF(OR(V10="",COUNTIF($V$4:$V$103,V10)<>1),"PlanKey不足・重複",IF(OR(P10="",P10="未設定",P10="設計中",P10="改訂中"),"計画未確定",IF(AND(P10<>"承認",P10<>"対象外承認"),"状態不正",IF(OR(T10="",U10="",O10=""),"計画対象・承認不足",IF(P10="対象外承認",IF(G10="","対象外理由不足","対象外計画記録"),IF(OR(G10="",H10="",I10="",J10="",K10="",L10="",M10="",N10=""),"評価設計不足",IF(AND(A10="E05",OR(X10="",Y10="",Z10="")),"試行状態・成功定義不足","計画記録あり"))))))))) -> 計画未確定
A11: E08 | B11: =IF(A11="","",IF(COUNTIF('32_定義マスター'!$A$13:$A$30,A11)<>1,"参照ID不正",IF(INDEX('32_定義マスター'!$B$13:$B$30,MATCH(A11,'32_定義マスター'!$A$13:$A$30,0))="","",INDEX('32_定義マスター'!$B$13:$B$30,MATCH(A11,'32_定義マスター'!$A$13:$A$30,0))))) -> Privacy/権利 | C11: =IF(A11="","",IF(COUNTIF('32_定義マスター'!$A$13:$A$30,A11)<>1,"参照ID不正",IF(INDEX('32_定義マスター'!$C$13:$C$30,MATCH(A11,'32_定義マスター'!$A$13:$A$30,0))="","",INDEX('32_定義マスター'!$C$13:$C$30,MATCH(A11,'32_定義マスター'!$A$13:$A$30,0))))) -> 無許可送信/利用/保持/削除失敗 | D11: =IF(A11="","",IF(COUNTIF('32_定義マスター'!$A$13:$A$30,A11)<>1,"参照ID不正",IF(INDEX('32_定義マスター'!$D$13:$D$30,MATCH(A11,'32_定義マスター'!$A$13:$A$30,0))="","",INDEX('32_定義マスター'!$D$13:$D$30,MATCH(A11,'32_定義マスター'!$A$13:$A$30,0))))) -> データ区分/利用目的/送信先/派生資産まで | E11: =IF(A11="","",IF(COUNTIF('32_定義マスター'!$A$13:$A$30,A11)<>1,"参照ID不正",IF(INDEX('32_定義マスター'!$E$13:$E$30,MATCH(A11,'32_定義マスター'!$A$13:$A$30,0))="","",INDEX('32_定義マスター'!$E$13:$E$30,MATCH(A11,'32_定義マスター'!$A$13:$A$30,0))))) -> 全 | F11: =IF(A11="","",IF(COUNTIF('32_定義マスター'!$A$13:$A$30,A11)<>1,"参照ID不正",IF(INDEX('32_定義マスター'!$F$13:$F$30,MATCH(A11,'32_定義マスター'!$A$13:$A$30,0))="","",INDEX('32_定義マスター'!$F$13:$F$30,MATCH(A11,'32_定義マスター'!$A$13:$A$30,0))))) -> R14,R10 | P11: 未設定 | Q11: =IF(A11="","",IF(COUNTIF('32_定義マスター'!$A$13:$A$30,A11)<>1,"参照ID不正",IF(INDEX('32_定義マスター'!$G$13:$G$30,MATCH(A11,'32_定義マスター'!$A$13:$A$30,0))="","",INDEX('32_定義マスター'!$G$13:$G$30,MATCH(A11,'32_定義マスター'!$A$13:$A$30,0))))) -> U01,W02,W03 | R11: EP-008 | S11: 1 | V11: =IF(OR(R11="",S11=""),"",R11&"@"&S11) -> EP-008@1 | W11: =IF(A11="","",IF(COUNTIF('32_定義マスター'!$A$13:$A$30,A11)<>1,"EvalType不正",IF(OR(V11="",COUNTIF($V$4:$V$103,V11)<>1),"PlanKey不足・重複",IF(OR(P11="",P11="未設定",P11="設計中",P11="改訂中"),"計画未確定",IF(AND(P11<>"承認",P11<>"対象外承認"),"状態不正",IF(OR(T11="",U11="",O11=""),"計画対象・承認不足",IF(P11="対象外承認",IF(G11="","対象外理由不足","対象外計画記録"),IF(OR(G11="",H11="",I11="",J11="",K11="",L11="",M11="",N11=""),"評価設計不足",IF(AND(A11="E05",OR(X11="",Y11="",Z11="")),"試行状態・成功定義不足","計画記録あり"))))))))) -> 計画未確定
A12: E09 | B12: =IF(A12="","",IF(COUNTIF('32_定義マスター'!$A$13:$A$30,A12)<>1,"参照ID不正",IF(INDEX('32_定義マスター'!$B$13:$B$30,MATCH(A12,'32_定義マスター'!$A$13:$A$30,0))="","",INDEX('32_定義マスター'!$B$13:$B$30,MATCH(A12,'32_定義マスター'!$A$13:$A$30,0))))) -> 公平性・重要slice | C12: =IF(A12="","",IF(COUNTIF('32_定義マスター'!$A$13:$A$30,A12)<>1,"参照ID不正",IF(INDEX('32_定義マスター'!$C$13:$C$30,MATCH(A12,'32_定義マスター'!$A$13:$A$30,0))="","",INDEX('32_定義マスター'!$C$13:$C$30,MATCH(A12,'32_定義マスター'!$A$13:$A$30,0))))) -> 群別性能と被害の差 | D12: =IF(A12="","",IF(COUNTIF('32_定義マスター'!$A$13:$A$30,A12)<>1,"参照ID不正",IF(INDEX('32_定義マスター'!$D$13:$D$30,MATCH(A12,'32_定義マスター'!$A$13:$A$30,0))="","",INDEX('32_定義マスター'!$D$13:$D$30,MATCH(A12,'32_定義マスター'!$A$13:$A$30,0))))) -> 用途上の重要slice/サンプル数/信頼区間・採取可否を定義 | E12: =IF(A12="","",IF(COUNTIF('32_定義マスター'!$A$13:$A$30,A12)<>1,"参照ID不正",IF(INDEX('32_定義マスター'!$E$13:$E$30,MATCH(A12,'32_定義マスター'!$A$13:$A$30,0))="","",INDEX('32_定義マスター'!$E$13:$E$30,MATCH(A12,'32_定義マスター'!$A$13:$A$30,0))))) -> 条件付 | F12: =IF(A12="","",IF(COUNTIF('32_定義マスター'!$A$13:$A$30,A12)<>1,"参照ID不正",IF(INDEX('32_定義マスター'!$F$13:$F$30,MATCH(A12,'32_定義マスター'!$A$13:$A$30,0))="","",INDEX('32_定義マスター'!$F$13:$F$30,MATCH(A12,'32_定義マスター'!$A$13:$A$30,0))))) -> R11,R04 | P12: 未設定 | Q12: =IF(A12="","",IF(COUNTIF('32_定義マスター'!$A$13:$A$30,A12)<>1,"参照ID不正",IF(INDEX('32_定義マスター'!$G$13:$G$30,MATCH(A12,'32_定義マスター'!$A$13:$A$30,0))="","",INDEX('32_定義マスター'!$G$13:$G$30,MATCH(A12,'32_定義マスター'!$A$13:$A$30,0))))) -> U01 | R12: EP-009 | S12: 1 | V12: =IF(OR(R12="",S12=""),"",R12&"@"&S12) -> EP-009@1 | W12: =IF(A12="","",IF(COUNTIF('32_定義マスター'!$A$13:$A$30,A12)<>1,"EvalType不正",IF(OR(V12="",COUNTIF($V$4:$V$103,V12)<>1),"PlanKey不足・重複",IF(OR(P12="",P12="未設定",P12="設計中",P12="改訂中"),"計画未確定",IF(AND(P12<>"承認",P12<>"対象外承認"),"状態不正",IF(OR(T12="",U12="",O12=""),"計画対象・承認不足",IF(P12="対象外承認",IF(G12="","対象外理由不足","対象外計画記録"),IF(OR(G12="",H12="",I12="",J12="",K12="",L12="",M12="",N12=""),"評価設計不足",IF(AND(A12="E05",OR(X12="",Y12="",Z12="")),"試行状態・成功定義不足","計画記録あり"))))))))) -> 計画未確定
A13: E10 | B13: =IF(A13="","",IF(COUNTIF('32_定義マスター'!$A$13:$A$30,A13)<>1,"参照ID不正",IF(INDEX('32_定義マスター'!$B$13:$B$30,MATCH(A13,'32_定義マスター'!$A$13:$A$30,0))="","",INDEX('32_定義マスター'!$B$13:$B$30,MATCH(A13,'32_定義マスター'!$A$13:$A$30,0))))) -> UX・透明性 | C13: =IF(A13="","",IF(COUNTIF('32_定義マスター'!$A$13:$A$30,A13)<>1,"参照ID不正",IF(INDEX('32_定義マスター'!$C$13:$C$30,MATCH(A13,'32_定義マスター'!$A$13:$A$30,0))="","",INDEX('32_定義マスター'!$C$13:$C$30,MATCH(A13,'32_定義マスター'!$A$13:$A$30,0))))) -> 理解/誤信/介入/訂正・救済 | D13: =IF(A13="","",IF(COUNTIF('32_定義マスター'!$A$13:$A$30,A13)<>1,"参照ID不正",IF(INDEX('32_定義マスター'!$D$13:$D$30,MATCH(A13,'32_定義マスター'!$A$13:$A$30,0))="","",INDEX('32_定義マスター'!$D$13:$D$30,MATCH(A13,'32_定義マスター'!$A$13:$A$30,0))))) -> 実ユーザー試験、アクセシビリティ、失敗時行動 | E13: =IF(A13="","",IF(COUNTIF('32_定義マスター'!$A$13:$A$30,A13)<>1,"参照ID不正",IF(INDEX('32_定義マスター'!$E$13:$E$30,MATCH(A13,'32_定義マスター'!$A$13:$A$30,0))="","",INDEX('32_定義マスター'!$E$13:$E$30,MATCH(A13,'32_定義マスター'!$A$13:$A$30,0))))) -> 全 | F13: =IF(A13="","",IF(COUNTIF('32_定義マスター'!$A$13:$A$30,A13)<>1,"参照ID不正",IF(INDEX('32_定義マスター'!$F$13:$F$30,MATCH(A13,'32_定義マスター'!$A$13:$A$30,0))="","",INDEX('32_定義マスター'!$F$13:$F$30,MATCH(A13,'32_定義マスター'!$A$13:$A$30,0))))) -> R05,R11 | P13: 未設定 | Q13: =IF(A13="","",IF(COUNTIF('32_定義マスター'!$A$13:$A$30,A13)<>1,"参照ID不正",IF(INDEX('32_定義マスター'!$G$13:$G$30,MATCH(A13,'32_定義マスター'!$A$13:$A$30,0))="","",INDEX('32_定義マスター'!$G$13:$G$30,MATCH(A13,'32_定義マスター'!$A$13:$A$30,0))))) -> U01 | R13: EP-010 | S13: 1 | V13: =IF(OR(R13="",S13=""),"",R13&"@"&S13) -> EP-010@1 | W13: =IF(A13="","",IF(COUNTIF('32_定義マスター'!$A$13:$A$30,A13)<>1,"EvalType不正",IF(OR(V13="",COUNTIF($V$4:$V$103,V13)<>1),"PlanKey不足・重複",IF(OR(P13="",P13="未設定",P13="設計中",P13="改訂中"),"計画未確定",IF(AND(P13<>"承認",P13<>"対象外承認"),"状態不正",IF(OR(T13="",U13="",O13=""),"計画対象・承認不足",IF(P13="対象外承認",IF(G13="","対象外理由不足","対象外計画記録"),IF(OR(G13="",H13="",I13="",J13="",K13="",L13="",M13="",N13=""),"評価設計不足",IF(AND(A13="E05",OR(X13="",Y13="",Z13="")),"試行状態・成功定義不足","計画記録あり"))))))))) -> 計画未確定
A14: E11 | B14: =IF(A14="","",IF(COUNTIF('32_定義マスター'!$A$13:$A$30,A14)<>1,"参照ID不正",IF(INDEX('32_定義マスター'!$B$13:$B$30,MATCH(A14,'32_定義マスター'!$A$13:$A$30,0))="","",INDEX('32_定義マスター'!$B$13:$B$30,MATCH(A14,'32_定義マスター'!$A$13:$A$30,0))))) -> 信頼性/性能 | C14: =IF(A14="","",IF(COUNTIF('32_定義マスター'!$A$13:$A$30,A14)<>1,"参照ID不正",IF(INDEX('32_定義マスター'!$C$13:$C$30,MATCH(A14,'32_定義マスター'!$A$13:$A$30,0))="","",INDEX('32_定義マスター'!$C$13:$C$30,MATCH(A14,'32_定義マスター'!$A$13:$A$30,0))))) -> p95/p99/可用性/timeout | D14: =IF(A14="","",IF(COUNTIF('32_定義マスター'!$A$13:$A$30,A14)<>1,"参照ID不正",IF(INDEX('32_定義マスター'!$D$13:$D$30,MATCH(A14,'32_定義マスター'!$A$13:$A$30,0))="","",INDEX('32_定義マスター'!$D$13:$D$30,MATCH(A14,'32_定義マスター'!$A$13:$A$30,0))))) -> 同時実行・負荷分布・依存障害を定義 | E14: =IF(A14="","",IF(COUNTIF('32_定義マスター'!$A$13:$A$30,A14)<>1,"参照ID不正",IF(INDEX('32_定義マスター'!$E$13:$E$30,MATCH(A14,'32_定義マスター'!$A$13:$A$30,0))="","",INDEX('32_定義マスター'!$E$13:$E$30,MATCH(A14,'32_定義マスター'!$A$13:$A$30,0))))) -> 全 | F14: =IF(A14="","",IF(COUNTIF('32_定義マスター'!$A$13:$A$30,A14)<>1,"参照ID不正",IF(INDEX('32_定義マスター'!$F$13:$F$30,MATCH(A14,'32_定義マスター'!$A$13:$A$30,0))="","",INDEX('32_定義マスター'!$F$13:$F$30,MATCH(A14,'32_定義マスター'!$A$13:$A$30,0))))) -> R12 | P14: 未設定 | Q14: =IF(A14="","",IF(COUNTIF('32_定義マスター'!$A$13:$A$30,A14)<>1,"参照ID不正",IF(INDEX('32_定義マスター'!$G$13:$G$30,MATCH(A14,'32_定義マスター'!$A$13:$A$30,0))="","",INDEX('32_定義マスター'!$G$13:$G$30,MATCH(A14,'32_定義マスター'!$A$13:$A$30,0))))) -> U01 | R14: EP-011 | S14: 1 | V14: =IF(OR(R14="",S14=""),"",R14&"@"&S14) -> EP-011@1 | W14: =IF(A14="","",IF(COUNTIF('32_定義マスター'!$A$13:$A$30,A14)<>1,"EvalType不正",IF(OR(V14="",COUNTIF($V$4:$V$103,V14)<>1),"PlanKey不足・重複",IF(OR(P14="",P14="未設定",P14="設計中",P14="改訂中"),"計画未確定",IF(AND(P14<>"承認",P14<>"対象外承認"),"状態不正",IF(OR(T14="",U14="",O14=""),"計画対象・承認不足",IF(P14="対象外承認",IF(G14="","対象外理由不足","対象外計画記録"),IF(OR(G14="",H14="",I14="",J14="",K14="",L14="",M14="",N14=""),"評価設計不足",IF(AND(A14="E05",OR(X14="",Y14="",Z14="")),"試行状態・成功定義不足","計画記録あり"))))))))) -> 計画未確定
A15: E12 | B15: =IF(A15="","",IF(COUNTIF('32_定義マスター'!$A$13:$A$30,A15)<>1,"参照ID不正",IF(INDEX('32_定義マスター'!$B$13:$B$30,MATCH(A15,'32_定義マスター'!$A$13:$A$30,0))="","",INDEX('32_定義マスター'!$B$13:$B$30,MATCH(A15,'32_定義マスター'!$A$13:$A$30,0))))) -> 復旧・縮退 | C15: =IF(A15="","",IF(COUNTIF('32_定義マスター'!$A$13:$A$30,A15)<>1,"参照ID不正",IF(INDEX('32_定義マスター'!$C$13:$C$30,MATCH(A15,'32_定義マスター'!$A$13:$A$30,0))="","",INDEX('32_定義マスター'!$C$13:$C$30,MATCH(A15,'32_定義マスター'!$A$13:$A$30,0))))) -> RTO/RPO/停止/部分失敗復旧 | D15: =IF(A15="","",IF(COUNTIF('32_定義マスター'!$A$13:$A$30,A15)<>1,"参照ID不正",IF(INDEX('32_定義マスター'!$D$13:$D$30,MATCH(A15,'32_定義マスター'!$A$13:$A$30,0))="","",INDEX('32_定義マスター'!$D$13:$D$30,MATCH(A15,'32_定義マスター'!$A$13:$A$30,0))))) -> モデルだけでなくPrompt/Data/Tool/権限版を復元 | E15: =IF(A15="","",IF(COUNTIF('32_定義マスター'!$A$13:$A$30,A15)<>1,"参照ID不正",IF(INDEX('32_定義マスター'!$E$13:$E$30,MATCH(A15,'32_定義マスター'!$A$13:$A$30,0))="","",INDEX('32_定義マスター'!$E$13:$E$30,MATCH(A15,'32_定義マスター'!$A$13:$A$30,0))))) -> 全 | F15: =IF(A15="","",IF(COUNTIF('32_定義マスター'!$A$13:$A$30,A15)<>1,"参照ID不正",IF(INDEX('32_定義マスター'!$F$13:$F$30,MATCH(A15,'32_定義マスター'!$A$13:$A$30,0))="","",INDEX('32_定義マスター'!$F$13:$F$30,MATCH(A15,'32_定義マスター'!$A$13:$A$30,0))))) -> R12,R18 | P15: 未設定 | Q15: =IF(A15="","",IF(COUNTIF('32_定義マスター'!$A$13:$A$30,A15)<>1,"参照ID不正",IF(INDEX('32_定義マスター'!$G$13:$G$30,MATCH(A15,'32_定義マスター'!$A$13:$A$30,0))="","",INDEX('32_定義マスター'!$G$13:$G$30,MATCH(A15,'32_定義マスター'!$A$13:$A$30,0))))) -> U01 | R15: EP-012 | S15: 1 | V15: =IF(OR(R15="",S15=""),"",R15&"@"&S15) -> EP-012@1 | W15: =IF(A15="","",IF(COUNTIF('32_定義マスター'!$A$13:$A$30,A15)<>1,"EvalType不正",IF(OR(V15="",COUNTIF($V$4:$V$103,V15)<>1),"PlanKey不足・重複",IF(OR(P15="",P15="未設定",P15="設計中",P15="改訂中"),"計画未確定",IF(AND(P15<>"承認",P15<>"対象外承認"),"状態不正",IF(OR(T15="",U15="",O15=""),"計画対象・承認不足",IF(P15="対象外承認",IF(G15="","対象外理由不足","対象外計画記録"),IF(OR(G15="",H15="",I15="",J15="",K15="",L15="",M15="",N15=""),"評価設計不足",IF(AND(A15="E05",OR(X15="",Y15="",Z15="")),"試行状態・成功定義不足","計画記録あり"))))))))) -> 計画未確定
... A21: E18 | B21: =IF(A21="","",IF(COUNTIF('32_定義マスター'!$A$13:$A$30,A21)<>1,"参照ID不正",IF(INDEX('32_定義マスター'!$B$13:$B$30,MATCH(A21,'32_定義マスター'!$A$13:$A$30,0))="","",INDEX('32_定義マスター'!$B$13:$B$30,MATCH(A21,'32_定義マスター'!$A$13:$A$30,0))))) -> 公開準備 | C21: =IF(A21="","",IF(COUNTIF('32_定義マスター'!$A$13:$A$30,A21)<>1,"参照ID不正",IF(INDEX('32_定義マスター'!$C$13:$C$30,MATCH(A21,'32_定義マスター'!$A$13:$A$30,0))="","",INDEX('32_定義マスター'!$C$13:$C$30,MATCH(A21,'32_定義マスター'!$A$13:$A$30,0))))) -> 未解決リスク・運用・支援の充足 | D21: =IF(A21="","",IF(COUNTIF('32_定義マスター'!$A$13:$A$30,A21)<>1,"参照ID不正",IF(INDEX('32_定義マスター'!$D$13:$D$30,MATCH(A21,'32_定義マスター'!$A$13:$A$30,0))="","",INDEX('32_定義マスター'!$D$13:$D$30,MATCH(A21,'32_定義マスター'!$A$13:$A$30,0))))) -> 独立評価・公開対象版・承認・条件期限を照合 | E21: =IF(A21="","",IF(COUNTIF('32_定義マスター'!$A$13:$A$30,A21)<>1,"参照ID不正",IF(INDEX('32_定義マスター'!$E$13:$E$30,MATCH(A21,'32_定義マスター'!$A$13:$A$30,0))="","",INDEX('32_定義マスター'!$E$13:$E$30,MATCH(A21,'32_定義マスター'!$A$13:$A$30,0))))) -> 全 | F21: =IF(A21="","",IF(COUNTIF('32_定義マスター'!$A$13:$A$30,A21)<>1,"参照ID不正",IF(INDEX('32_定義マスター'!$F$13:$F$30,MATCH(A21,'32_定義マスター'!$A$13:$A$30,0))="","",INDEX('32_定義マスター'!$F$13:$F$30,MATCH(A21,'32_定義マスター'!$A$13:$A$30,0))))) -> R19,R18 | P21: 未設定 | Q21: =IF(A21="","",IF(COUNTIF('32_定義マスター'!$A$13:$A$30,A21)<>1,"参照ID不正",IF(INDEX('32_定義マスター'!$G$13:$G$30,MATCH(A21,'32_定義マスター'!$A$13:$A$30,0))="","",INDEX('32_定義マスター'!$G$13:$G$30,MATCH(A21,'32_定義マスター'!$A$13:$A$30,0))))) -> U01 | R21: EP-018 | S21: 1 | V21: =IF(OR(R21="",S21=""),"",R21&"@"&S21) -> EP-018@1 | W21: =IF(A21="","",IF(COUNTIF('32_定義マスター'!$A$13:$A$30,A21)<>1,"EvalType不正",IF(OR(V21="",COUNTIF($V$4:$V$103,V21)<>1),"PlanKey不足・重複",IF(OR(P21="",P21="未設定",P21="設計中",P21="改訂中"),"計画未確定",IF(AND(P21<>"承認",P21<>"対象外承認"),"状態不正",IF(OR(T21="",U21="",O21=""),"計画対象・承認不足",IF(P21="対象外承認",IF(G21="","対象外理由不足","対象外計画記録"),IF(OR(G21="",H21="",I21="",J21="",K21="",L21="",M21="",N21=""),"評価設計不足",IF(AND(A21="E05",OR(X21="",Y21="",Z21="")),"試行状態・成功定義不足","計画記録あり"))))))))) -> 計画未確定
B22: =IF(A22="","",IF(COUNTIF('32_定義マスター'!$A$13:$A$30,A22)<>1,"参照ID不正",IF(INDEX('32_定義マスター'!$B$13:$B$30,MATCH(A22,'32_定義マスター'!$A$13:$A$30,0))="","",INDEX('32_定義マスター'!$B$13:$B$30,MATCH(A22,'32_定義マスター'!$A$13:$A$30,0))))) | C22: =IF(A22="","",IF(COUNTIF('32_定義マスター'!$A$13:$A$30,A22)<>1,"参照ID不正",IF(INDEX('32_定義マスター'!$C$13:$C$30,MATCH(A22,'32_定義マスター'!$A$13:$A$30,0))="","",INDEX('32_定義マスター'!$C$13:$C$30,MATCH(A22,'32_定義マスター'!$A$13:$A$30,0))))) | D22: =IF(A22="","",IF(COUNTIF('32_定義マスター'!$A$13:$A$30,A22)<>1,"参照ID不正",IF(INDEX('32_定義マスター'!$D$13:$D$30,MATCH(A22,'32_定義マスター'!$A$13:$A$30,0))="","",INDEX('32_定義マスター'!$D$13:$D$30,MATCH(A22,'32_定義マスター'!$A$13:$A$30,0))))) | E22: =IF(A22="","",IF(COUNTIF('32_定義マスター'!$A$13:$A$30,A22)<>1,"参照ID不正",IF(INDEX('32_定義マスター'!$E$13:$E$30,MATCH(A22,'32_定義マスター'!$A$13:$A$30,0))="","",INDEX('32_定義マスター'!$E$13:$E$30,MATCH(A22,'32_定義マスター'!$A$13:$A$30,0))))) | F22: =IF(A22="","",IF(COUNTIF('32_定義マスター'!$A$13:$A$30,A22)<>1,"参照ID不正",IF(INDEX('32_定義マスター'!$F$13:$F$30,MATCH(A22,'32_定義マスター'!$A$13:$A$30,0))="","",INDEX('32_定義マスター'!$F$13:$F$30,MATCH(A22,'32_定義マスター'!$A$13:$A$30,0))))) | Q22: =IF(A22="","",IF(COUNTIF('32_定義マスター'!$A$13:$A$30,A22)<>1,"参照ID不正",IF(INDEX('32_定義マスター'!$G$13:$G$30,MATCH(A22,'32_定義マスター'!$A$13:$A$30,0))="","",INDEX('32_定義マスター'!$G$13:$G$30,MATCH(A22,'32_定義マスター'!$A$13:$A$30,0))))) | V22: =IF(OR(R22="",S22=""),"",R22&"@"&S22) | W22: =IF(A22="","",IF(COUNTIF('32_定義マスター'!$A$13:$A$30,A22)<>1,"EvalType不正",IF(OR(V22="",COUNTIF($V$4:$V$103,V22)<>1),"PlanKey不足・重複",IF(OR(P22="",P22="未設定",P22="設計中",P22="改訂中"),"計画未確定",IF(AND(P22<>"承認",P22<>"対象外承認"),"状態不正",IF(OR(T22="",U22="",O22=""),"計画対象・承認不足",IF(P22="対象外承認",IF(G22="","対象外理由不足","対象外計画記録"),IF(OR(G22="",H22="",I22="",J22="",K22="",L22="",M22="",N22=""),"評価設計不足",IF(AND(A22="E05",OR(X22="",Y22="",Z22="")),"試行状態・成功定義不足","計画記録あり")))))))))
B23: =IF(A23="","",IF(COUNTIF('32_定義マスター'!$A$13:$A$30,A23)<>1,"参照ID不正",IF(INDEX('32_定義マスター'!$B$13:$B$30,MATCH(A23,'32_定義マスター'!$A$13:$A$30,0))="","",INDEX('32_定義マスター'!$B$13:$B$30,MATCH(A23,'32_定義マスター'!$A$13:$A$30,0))))) | C23: =IF(A23="","",IF(COUNTIF('32_定義マスター'!$A$13:$A$30,A23)<>1,"参照ID不正",IF(INDEX('32_定義マスター'!$C$13:$C$30,MATCH(A23,'32_定義マスター'!$A$13:$A$30,0))="","",INDEX('32_定義マスター'!$C$13:$C$30,MATCH(A23,'32_定義マスター'!$A$13:$A$30,0))))) | D23: =IF(A23="","",IF(COUNTIF('32_定義マスター'!$A$13:$A$30,A23)<>1,"参照ID不正",IF(INDEX('32_定義マスター'!$D$13:$D$30,MATCH(A23,'32_定義マスター'!$A$13:$A$30,0))="","",INDEX('32_定義マスター'!$D$13:$D$30,MATCH(A23,'32_定義マスター'!$A$13:$A$30,0))))) | E23: =IF(A23="","",IF(COUNTIF('32_定義マスター'!$A$13:$A$30,A23)<>1,"参照ID不正",IF(INDEX('32_定義マスター'!$E$13:$E$30,MATCH(A23,'32_定義マスター'!$A$13:$A$30,0))="","",INDEX('32_定義マスター'!$E$13:$E$30,MATCH(A23,'32_定義マスター'!$A$13:$A$30,0))))) | F23: =IF(A23="","",IF(COUNTIF('32_定義マスター'!$A$13:$A$30,A23)<>1,"参照ID不正",IF(INDEX('32_定義マスター'!$F$13:$F$30,MATCH(A23,'32_定義マスター'!$A$13:$A$30,0))="","",INDEX('32_定義マスター'!$F$13:$F$30,MATCH(A23,'32_定義マスター'!$A$13:$A$30,0))))) | Q23: =IF(A23="","",IF(COUNTIF('32_定義マスター'!$A$13:$A$30,A23)<>1,"参照ID不正",IF(INDEX('32_定義マスター'!$G$13:$G$30,MATCH(A23,'32_定義マスター'!$A$13:$A$30,0))="","",INDEX('32_定義マスター'!$G$13:$G$30,MATCH(A23,'32_定義マスター'!$A$13:$A$30,0))))) | V23: =IF(OR(R23="",S23=""),"",R23&"@"&S23) | W23: =IF(A23="","",IF(COUNTIF('32_定義マスター'!$A$13:$A$30,A23)<>1,"EvalType不正",IF(OR(V23="",COUNTIF($V$4:$V$103,V23)<>1),"PlanKey不足・重複",IF(OR(P23="",P23="未設定",P23="設計中",P23="改訂中"),"計画未確定",IF(AND(P23<>"承認",P23<>"対象外承認"),"状態不正",IF(OR(T23="",U23="",O23=""),"計画対象・承認不足",IF(P23="対象外承認",IF(G23="","対象外理由不足","対象外計画記録"),IF(OR(G23="",H23="",I23="",J23="",K23="",L23="",M23="",N23=""),"評価設計不足",IF(AND(A23="E05",OR(X23="",Y23="",Z23="")),"試行状態・成功定義不足","計画記録あり")))))))))
B24: =IF(A24="","",IF(COUNTIF('32_定義マスター'!$A$13:$A$30,A24)<>1,"参照ID不正",IF(INDEX('32_定義マスター'!$B$13:$B$30,MATCH(A24,'32_定義マスター'!$A$13:$A$30,0))="","",INDEX('32_定義マスター'!$B$13:$B$30,MATCH(A24,'32_定義マスター'!$A$13:$A$30,0))))) | C24: =IF(A24="","",IF(COUNTIF('32_定義マスター'!$A$13:$A$30,A24)<>1,"参照ID不正",IF(INDEX('32_定義マスター'!$C$13:$C$30,MATCH(A24,'32_定義マスター'!$A$13:$A$30,0))="","",INDEX('32_定義マスター'!$C$13:$C$30,MATCH(A24,'32_定義マスター'!$A$13:$A$30,0))))) | D24: =IF(A24="","",IF(COUNTIF('32_定義マスター'!$A$13:$A$30,A24)<>1,"参照ID不正",IF(INDEX('32_定義マスター'!$D$13:$D$30,MATCH(A24,'32_定義マスター'!$A$13:$A$30,0))="","",INDEX('32_定義マスター'!$D$13:$D$30,MATCH(A24,'32_定義マスター'!$A$13:$A$30,0))))) | E24: =IF(A24="","",IF(COUNTIF('32_定義マスター'!$A$13:$A$30,A24)<>1,"参照ID不正",IF(INDEX('32_定義マスター'!$E$13:$E$30,MATCH(A24,'32_定義マスター'!$A$13:$A$30,0))="","",INDEX('32_定義マスター'!$E$13:$E$30,MATCH(A24,'32_定義マスター'!$A$13:$A$30,0))))) | F24: =IF(A24="","",IF(COUNTIF('32_定義マスター'!$A$13:$A$30,A24)<>1,"参照ID不正",IF(INDEX('32_定義マスター'!$F$13:$F$30,MATCH(A24,'32_定義マスター'!$A$13:$A$30,0))="","",INDEX('32_定義マスター'!$F$13:$F$30,MATCH(A24,'32_定義マスター'!$A$13:$A$30,0))))) | Q24: =IF(A24="","",IF(COUNTIF('32_定義マスター'!$A$13:$A$30,A24)<>1,"参照ID不正",IF(INDEX('32_定義マスター'!$G$13:$G$30,MATCH(A24,'32_定義マスター'!$A$13:$A$30,0))="","",INDEX('32_定義マスター'!$G$13:$G$30,MATCH(A24,'32_定義マスター'!$A$13:$A$30,0))))) | V24: =IF(OR(R24="",S24=""),"",R24&"@"&S24) | W24: =IF(A24="","",IF(COUNTIF('32_定義マスター'!$A$13:$A$30,A24)<>1,"EvalType不正",IF(OR(V24="",COUNTIF($V$4:$V$103,V24)<>1),"PlanKey不足・重複",IF(OR(P24="",P24="未設定",P24="設計中",P24="改訂中"),"計画未確定",IF(AND(P24<>"承認",P24<>"対象外承認"),"状態不正",IF(OR(T24="",U24="",O24=""),"計画対象・承認不足",IF(P24="対象外承認",IF(G24="","対象外理由不足","対象外計画記録"),IF(OR(G24="",H24="",I24="",J24="",K24="",L24="",M24="",N24=""),"評価設計不足",IF(AND(A24="E05",OR(X24="",Y24="",Z24="")),"試行状態・成功定義不足","計画記録あり")))))))))
B25: =IF(A25="","",IF(COUNTIF('32_定義マスター'!$A$13:$A$30,A25)<>1,"参照ID不正",IF(INDEX('32_定義マスター'!$B$13:$B$30,MATCH(A25,'32_定義マスター'!$A$13:$A$30,0))="","",INDEX('32_定義マスター'!$B$13:$B$30,MATCH(A25,'32_定義マスター'!$A$13:$A$30,0))))) | C25: =IF(A25="","",IF(COUNTIF('32_定義マスター'!$A$13:$A$30,A25)<>1,"参照ID不正",IF(INDEX('32_定義マスター'!$C$13:$C$30,MATCH(A25,'32_定義マスター'!$A$13:$A$30,0))="","",INDEX('32_定義マスター'!$C$13:$C$30,MATCH(A25,'32_定義マスター'!$A$13:$A$30,0))))) | D25: =IF(A25="","",IF(COUNTIF('32_定義マスター'!$A$13:$A$30,A25)<>1,"参照ID不正",IF(INDEX('32_定義マスター'!$D$13:$D$30,MATCH(A25,'32_定義マスター'!$A$13:$A$30,0))="","",INDEX('32_定義マスター'!$D$13:$D$30,MATCH(A25,'32_定義マスター'!$A$13:$A$30,0))))) | E25: =IF(A25="","",IF(COUNTIF('32_定義マスター'!$A$13:$A$30,A25)<>1,"参照ID不正",IF(INDEX('32_定義マスター'!$E$13:$E$30,MATCH(A25,'32_定義マスター'!$A$13:$A$30,0))="","",INDEX('32_定義マスター'!$E$13:$E$30,MATCH(A25,'32_定義マスター'!$A$13:$A$30,0))))) | F25: =IF(A25="","",IF(COUNTIF('32_定義マスター'!$A$13:$A$30,A25)<>1,"参照ID不正",IF(INDEX('32_定義マスター'!$F$13:$F$30,MATCH(A25,'32_定義マスター'!$A$13:$A$30,0))="","",INDEX('32_定義マスター'!$F$13:$F$30,MATCH(A25,'32_定義マスター'!$A$13:$A$30,0))))) | Q25: =IF(A25="","",IF(COUNTIF('32_定義マスター'!$A$13:$A$30,A25)<>1,"参照ID不正",IF(INDEX('32_定義マスター'!$G$13:$G$30,MATCH(A25,'32_定義マスター'!$A$13:$A$30,0))="","",INDEX('32_定義マスター'!$G$13:$G$30,MATCH(A25,'32_定義マスター'!$A$13:$A$30,0))))) | V25: =IF(OR(R25="",S25=""),"",R25&"@"&S25) | W25: =IF(A25="","",IF(COUNTIF('32_定義マスター'!$A$13:$A$30,A25)<>1,"EvalType不正",IF(OR(V25="",COUNTIF($V$4:$V$103,V25)<>1),"PlanKey不足・重複",IF(OR(P25="",P25="未設定",P25="設計中",P25="改訂中"),"計画未確定",IF(AND(P25<>"承認",P25<>"対象外承認"),"状態不正",IF(OR(T25="",U25="",O25=""),"計画対象・承認不足",IF(P25="対象外承認",IF(G25="","対象外理由不足","対象外計画記録"),IF(OR(G25="",H25="",I25="",J25="",K25="",L25="",M25="",N25=""),"評価設計不足",IF(AND(A25="E05",OR(X25="",Y25="",Z25="")),"試行状態・成功定義不足","計画記録あり")))))))))
B26: =IF(A26="","",IF(COUNTIF('32_定義マスター'!$A$13:$A$30,A26)<>1,"参照ID不正",IF(INDEX('32_定義マスター'!$B$13:$B$30,MATCH(A26,'32_定義マスター'!$A$13:$A$30,0))="","",INDEX('32_定義マスター'!$B$13:$B$30,MATCH(A26,'32_定義マスター'!$A$13:$A$30,0))))) | C26: =IF(A26="","",IF(COUNTIF('32_定義マスター'!$A$13:$A$30,A26)<>1,"参照ID不正",IF(INDEX('32_定義マスター'!$C$13:$C$30,MATCH(A26,'32_定義マスター'!$A$13:$A$30,0))="","",INDEX('32_定義マスター'!$C$13:$C$30,MATCH(A26,'32_定義マスター'!$A$13:$A$30,0))))) | D26: =IF(A26="","",IF(COUNTIF('32_定義マスター'!$A$13:$A$30,A26)<>1,"参照ID不正",IF(INDEX('32_定義マスター'!$D$13:$D$30,MATCH(A26,'32_定義マスター'!$A$13:$A$30,0))="","",INDEX('32_定義マスター'!$D$13:$D$30,MATCH(A26,'32_定義マスター'!$A$13:$A$30,0))))) | E26: =IF(A26="","",IF(COUNTIF('32_定義マスター'!$A$13:$A$30,A26)<>1,"参照ID不正",IF(INDEX('32_定義マスター'!$E$13:$E$30,MATCH(A26,'32_定義マスター'!$A$13:$A$30,0))="","",INDEX('32_定義マスター'!$E$13:$E$30,MATCH(A26,'32_定義マスター'!$A$13:$A$30,0))))) | F26: =IF(A26="","",IF(COUNTIF('32_定義マスター'!$A$13:$A$30,A26)<>1,"参照ID不正",IF(INDEX('32_定義マスター'!$F$13:$F$30,MATCH(A26,'32_定義マスター'!$A$13:$A$30,0))="","",INDEX('32_定義マスター'!$F$13:$F$30,MATCH(A26,'32_定義マスター'!$A$13:$A$30,0))))) | Q26: =IF(A26="","",IF(COUNTIF('32_定義マスター'!$A$13:$A$30,A26)<>1,"参照ID不正",IF(INDEX('32_定義マスター'!$G$13:$G$30,MATCH(A26,'32_定義マスター'!$A$13:$A$30,0))="","",INDEX('32_定義マスター'!$G$13:$G$30,MATCH(A26,'32_定義マスター'!$A$13:$A$30,0))))) | V26: =IF(OR(R26="",S26=""),"",R26&"@"&S26) | W26: =IF(A26="","",IF(COUNTIF('32_定義マスター'!$A$13:$A$30,A26)<>1,"EvalType不正",IF(OR(V26="",COUNTIF($V$4:$V$103,V26)<>1),"PlanKey不足・重複",IF(OR(P26="",P26="未設定",P26="設計中",P26="改訂中"),"計画未確定",IF(AND(P26<>"承認",P26<>"対象外承認"),"状態不正",IF(OR(T26="",U26="",O26=""),"計画対象・承認不足",IF(P26="対象外承認",IF(G26="","対象外理由不足","対象外計画記録"),IF(OR(G26="",H26="",I26="",J26="",K26="",L26="",M26="",N26=""),"評価設計不足",IF(AND(A26="E05",OR(X26="",Y26="",Z26="")),"試行状態・成功定義不足","計画記録あり")))))))))
B27: =IF(A27="","",IF(COUNTIF('32_定義マスター'!$A$13:$A$30,A27)<>1,"参照ID不正",IF(INDEX('32_定義マスター'!$B$13:$B$30,MATCH(A27,'32_定義マスター'!$A$13:$A$30,0))="","",INDEX('32_定義マスター'!$B$13:$B$30,MATCH(A27,'32_定義マスター'!$A$13:$A$30,0))))) | C27: =IF(A27="","",IF(COUNTIF('32_定義マスター'!$A$13:$A$30,A27)<>1,"参照ID不正",IF(INDEX('32_定義マスター'!$C$13:$C$30,MATCH(A27,'32_定義マスター'!$A$13:$A$30,0))="","",INDEX('32_定義マスター'!$C$13:$C$30,MATCH(A27,'32_定義マスター'!$A$13:$A$30,0))))) | D27: =IF(A27="","",IF(COUNTIF('32_定義マスター'!$A$13:$A$30,A27)<>1,"参照ID不正",IF(INDEX('32_定義マスター'!$D$13:$D$30,MATCH(A27,'32_定義マスター'!$A$13:$A$30,0))="","",INDEX('32_定義マスター'!$D$13:$D$30,MATCH(A27,'32_定義マスター'!$A$13:$A$30,0))))) | E27: =IF(A27="","",IF(COUNTIF('32_定義マスター'!$A$13:$A$30,A27)<>1,"参照ID不正",IF(INDEX('32_定義マスター'!$E$13:$E$30,MATCH(A27,'32_定義マスター'!$A$13:$A$30,0))="","",INDEX('32_定義マスター'!$E$13:$E$30,MATCH(A27,'32_定義マスター'!$A$13:$A$30,0))))) | F27: =IF(A27="","",IF(COUNTIF('32_定義マスター'!$A$13:$A$30,A27)<>1,"参照ID不正",IF(INDEX('32_定義マスター'!$F$13:$F$30,MATCH(A27,'32_定義マスター'!$A$13:$A$30,0))="","",INDEX('32_定義マスター'!$F$13:$F$30,MATCH(A27,'32_定義マスター'!$A$13:$A$30,0))))) | Q27: =IF(A27="","",IF(COUNTIF('32_定義マスター'!$A$13:$A$30,A27)<>1,"参照ID不正",IF(INDEX('32_定義マスター'!$G$13:$G$30,MATCH(A27,'32_定義マスター'!$A$13:$A$30,0))="","",INDEX('32_定義マスター'!$G$13:$G$30,MATCH(A27,'32_定義マスター'!$A$13:$A$30,0))))) | V27: =IF(OR(R27="",S27=""),"",R27&"@"&S27) | W27: =IF(A27="","",IF(COUNTIF('32_定義マスター'!$A$13:$A$30,A27)<>1,"EvalType不正",IF(OR(V27="",COUNTIF($V$4:$V$103,V27)<>1),"PlanKey不足・重複",IF(OR(P27="",P27="未設定",P27="設計中",P27="改訂中"),"計画未確定",IF(AND(P27<>"承認",P27<>"対象外承認"),"状態不正",IF(OR(T27="",U27="",O27=""),"計画対象・承認不足",IF(P27="対象外承認",IF(G27="","対象外理由不足","対象外計画記録"),IF(OR(G27="",H27="",I27="",J27="",K27="",L27="",M27="",N27=""),"評価設計不足",IF(AND(A27="E05",OR(X27="",Y27="",Z27="")),"試行状態・成功定義不足","計画記録あり")))))))))
B28: =IF(A28="","",IF(COUNTIF('32_定義マスター'!$A$13:$A$30,A28)<>1,"参照ID不正",IF(INDEX('32_定義マスター'!$B$13:$B$30,MATCH(A28,'32_定義マスター'!$A$13:$A$30,0))="","",INDEX('32_定義マスター'!$B$13:$B$30,MATCH(A28,'32_定義マスター'!$A$13:$A$30,0))))) | C28: =IF(A28="","",IF(COUNTIF('32_定義マスター'!$A$13:$A$30,A28)<>1,"参照ID不正",IF(INDEX('32_定義マスター'!$C$13:$C$30,MATCH(A28,'32_定義マスター'!$A$13:$A$30,0))="","",INDEX('32_定義マスター'!$C$13:$C$30,MATCH(A28,'32_定義マスター'!$A$13:$A$30,0))))) | D28: =IF(A28="","",IF(COUNTIF('32_定義マスター'!$A$13:$A$30,A28)<>1,"参照ID不正",IF(INDEX('32_定義マスター'!$D$13:$D$30,MATCH(A28,'32_定義マスター'!$A$13:$A$30,0))="","",INDEX('32_定義マスター'!$D$13:$D$30,MATCH(A28,'32_定義マスター'!$A$13:$A$30,0))))) | E28: =IF(A28="","",IF(COUNTIF('32_定義マスター'!$A$13:$A$30,A28)<>1,"参照ID不正",IF(INDEX('32_定義マスター'!$E$13:$E$30,MATCH(A28,'32_定義マスター'!$A$13:$A$30,0))="","",INDEX('32_定義マスター'!$E$13:$E$30,MATCH(A28,'32_定義マスター'!$A$13:$A$30,0))))) | F28: =IF(A28="","",IF(COUNTIF('32_定義マスター'!$A$13:$A$30,A28)<>1,"参照ID不正",IF(INDEX('32_定義マスター'!$F$13:$F$30,MATCH(A28,'32_定義マスター'!$A$13:$A$30,0))="","",INDEX('32_定義マスター'!$F$13:$F$30,MATCH(A28,'32_定義マスター'!$A$13:$A$30,0))))) | Q28: =IF(A28="","",IF(COUNTIF('32_定義マスター'!$A$13:$A$30,A28)<>1,"参照ID不正",IF(INDEX('32_定義マスター'!$G$13:$G$30,MATCH(A28,'32_定義マスター'!$A$13:$A$30,0))="","",INDEX('32_定義マスター'!$G$13:$G$30,MATCH(A28,'32_定義マスター'!$A$13:$A$30,0))))) | V28: =IF(OR(R28="",S28=""),"",R28&"@"&S28) | W28: =IF(A28="","",IF(COUNTIF('32_定義マスター'!$A$13:$A$30,A28)<>1,"EvalType不正",IF(OR(V28="",COUNTIF($V$4:$V$103,V28)<>1),"PlanKey不足・重複",IF(OR(P28="",P28="未設定",P28="設計中",P28="改訂中"),"計画未確定",IF(AND(P28<>"承認",P28<>"対象外承認"),"状態不正",IF(OR(T28="",U28="",O28=""),"計画対象・承認不足",IF(P28="対象外承認",IF(G28="","対象外理由不足","対象外計画記録"),IF(OR(G28="",H28="",I28="",J28="",K28="",L28="",M28="",N28=""),"評価設計不足",IF(AND(A28="E05",OR(X28="",Y28="",Z28="")),"試行状態・成功定義不足","計画記録あり")))))))))
B29: =IF(A29="","",IF(COUNTIF('32_定義マスター'!$A$13:$A$30,A29)<>1,"参照ID不正",IF(INDEX('32_定義マスター'!$B$13:$B$30,MATCH(A29,'32_定義マスター'!$A$13:$A$30,0))="","",INDEX('32_定義マスター'!$B$13:$B$30,MATCH(A29,'32_定義マスター'!$A$13:$A$30,0))))) | C29: =IF(A29="","",IF(COUNTIF('32_定義マスター'!$A$13:$A$30,A29)<>1,"参照ID不正",IF(INDEX('32_定義マスター'!$C$13:$C$30,MATCH(A29,'32_定義マスター'!$A$13:$A$30,0))="","",INDEX('32_定義マスター'!$C$13:$C$30,MATCH(A29,'32_定義マスター'!$A$13:$A$30,0))))) | D29: =IF(A29="","",IF(COUNTIF('32_定義マスター'!$A$13:$A$30,A29)<>1,"参照ID不正",IF(INDEX('32_定義マスター'!$D$13:$D$30,MATCH(A29,'32_定義マスター'!$A$13:$A$30,0))="","",INDEX('32_定義マスター'!$D$13:$D$30,MATCH(A29,'32_定義マスター'!$A$13:$A$30,0))))) | E29: =IF(A29="","",IF(COUNTIF('32_定義マスター'!$A$13:$A$30,A29)<>1,"参照ID不正",IF(INDEX('32_定義マスター'!$E$13:$E$30,MATCH(A29,'32_定義マスター'!$A$13:$A$30,0))="","",INDEX('32_定義マスター'!$E$13:$E$30,MATCH(A29,'32_定義マスター'!$A$13:$A$30,0))))) | F29: =IF(A29="","",IF(COUNTIF('32_定義マスター'!$A$13:$A$30,A29)<>1,"参照ID不正",IF(INDEX('32_定義マスター'!$F$13:$F$30,MATCH(A29,'32_定義マスター'!$A$13:$A$30,0))="","",INDEX('32_定義マスター'!$F$13:$F$30,MATCH(A29,'32_定義マスター'!$A$13:$A$30,0))))) | Q29: =IF(A29="","",IF(COUNTIF('32_定義マスター'!$A$13:$A$30,A29)<>1,"参照ID不正",IF(INDEX('32_定義マスター'!$G$13:$G$30,MATCH(A29,'32_定義マスター'!$A$13:$A$30,0))="","",INDEX('32_定義マスター'!$G$13:$G$30,MATCH(A29,'32_定義マスター'!$A$13:$A$30,0))))) | V29: =IF(OR(R29="",S29=""),"",R29&"@"&S29) | W29: =IF(A29="","",IF(COUNTIF('32_定義マスター'!$A$13:$A$30,A29)<>1,"EvalType不正",IF(OR(V29="",COUNTIF($V$4:$V$103,V29)<>1),"PlanKey不足・重複",IF(OR(P29="",P29="未設定",P29="設計中",P29="改訂中"),"計画未確定",IF(AND(P29<>"承認",P29<>"対象外承認"),"状態不正",IF(OR(T29="",U29="",O29=""),"計画対象・承認不足",IF(P29="対象外承認",IF(G29="","対象外理由不足","対象外計画記録"),IF(OR(G29="",H29="",I29="",J29="",K29="",L29="",M29="",N29=""),"評価設計不足",IF(AND(A29="E05",OR(X29="",Y29="",Z29="")),"試行状態・成功定義不足","計画記録あり")))))))))
B30: =IF(A30="","",IF(COUNTIF('32_定義マスター'!$A$13:$A$30,A30)<>1,"参照ID不正",IF(INDEX('32_定義マスター'!$B$13:$B$30,MATCH(A30,'32_定義マスター'!$A$13:$A$30,0))="","",INDEX('32_定義マスター'!$B$13:$B$30,MATCH(A30,'32_定義マスター'!$A$13:$A$30,0))))) | C30: =IF(A30="","",IF(COUNTIF('32_定義マスター'!$A$13:$A$30,A30)<>1,"参照ID不正",IF(INDEX('32_定義マスター'!$C$13:$C$30,MATCH(A30,'32_定義マスター'!$A$13:$A$30,0))="","",INDEX('32_定義マスター'!$C$13:$C$30,MATCH(A30,'32_定義マスター'!$A$13:$A$30,0))))) | D30: =IF(A30="","",IF(COUNTIF('32_定義マスター'!$A$13:$A$30,A30)<>1,"参照ID不正",IF(INDEX('32_定義マスター'!$D$13:$D$30,MATCH(A30,'32_定義マスター'!$A$13:$A$30,0))="","",INDEX('32_定義マスター'!$D$13:$D$30,MATCH(A30,'32_定義マスター'!$A$13:$A$30,0))))) | E30: =IF(A30="","",IF(COUNTIF('32_定義マスター'!$A$13:$A$30,A30)<>1,"参照ID不正",IF(INDEX('32_定義マスター'!$E$13:$E$30,MATCH(A30,'32_定義マスター'!$A$13:$A$30,0))="","",INDEX('32_定義マスター'!$E$13:$E$30,MATCH(A30,'32_定義マスター'!$A$13:$A$30,0))))) | F30: =IF(A30="","",IF(COUNTIF('32_定義マスター'!$A$13:$A$30,A30)<>1,"参照ID不正",IF(INDEX('32_定義マスター'!$F$13:$F$30,MATCH(A30,'32_定義マスター'!$A$13:$A$30,0))="","",INDEX('32_定義マスター'!$F$13:$F$30,MATCH(A30,'32_定義マスター'!$A$13:$A$30,0))))) | Q30: =IF(A30="","",IF(COUNTIF('32_定義マスター'!$A$13:$A$30,A30)<>1,"参照ID不正",IF(INDEX('32_定義マスター'!$G$13:$G$30,MATCH(A30,'32_定義マスター'!$A$13:$A$30,0))="","",INDEX('32_定義マスター'!$G$13:$G$30,MATCH(A30,'32_定義マスター'!$A$13:$A$30,0))))) | V30: =IF(OR(R30="",S30=""),"",R30&"@"&S30) | W30: =IF(A30="","",IF(COUNTIF('32_定義マスター'!$A$13:$A$30,A30)<>1,"EvalType不正",IF(OR(V30="",COUNTIF($V$4:$V$103,V30)<>1),"PlanKey不足・重複",IF(OR(P30="",P30="未設定",P30="設計中",P30="改訂中"),"計画未確定",IF(AND(P30<>"承認",P30<>"対象外承認"),"状態不正",IF(OR(T30="",U30="",O30=""),"計画対象・承認不足",IF(P30="対象外承認",IF(G30="","対象外理由不足","対象外計画記録"),IF(OR(G30="",H30="",I30="",J30="",K30="",L30="",M30="",N30=""),"評価設計不足",IF(AND(A30="E05",OR(X30="",Y30="",Z30="")),"試行状態・成功定義不足","計画記録あり")))))))))
B31: =IF(A31="","",IF(COUNTIF('32_定義マスター'!$A$13:$A$30,A31)<>1,"参照ID不正",IF(INDEX('32_定義マスター'!$B$13:$B$30,MATCH(A31,'32_定義マスター'!$A$13:$A$30,0))="","",INDEX('32_定義マスター'!$B$13:$B$30,MATCH(A31,'32_定義マスター'!$A$13:$A$30,0))))) | C31: =IF(A31="","",IF(COUNTIF('32_定義マスター'!$A$13:$A$30,A31)<>1,"参照ID不正",IF(INDEX('32_定義マスター'!$C$13:$C$30,MATCH(A31,'32_定義マスター'!$A$13:$A$30,0))="","",INDEX('32_定義マスター'!$C$13:$C$30,MATCH(A31,'32_定義マスター'!$A$13:$A$30,0))))) | D31: =IF(A31="","",IF(COUNTIF('32_定義マスター'!$A$13:$A$30,A31)<>1,"参照ID不正",IF(INDEX('32_定義マスター'!$D$13:$D$30,MATCH(A31,'32_定義マスター'!$A$13:$A$30,0))="","",INDEX('32_定義マスター'!$D$13:$D$30,MATCH(A31,'32_定義マスター'!$A$13:$A$30,0))))) | E31: =IF(A31="","",IF(COUNTIF('32_定義マスター'!$A$13:$A$30,A31)<>1,"参照ID不正",IF(INDEX('32_定義マスター'!$E$13:$E$30,MATCH(A31,'32_定義マスター'!$A$13:$A$30,0))="","",INDEX('32_定義マスター'!$E$13:$E$30,MATCH(A31,'32_定義マスター'!$A$13:$A$30,0))))) | F31: =IF(A31="","",IF(COUNTIF('32_定義マスター'!$A$13:$A$30,A31)<>1,"参照ID不正",IF(INDEX('32_定義マスター'!$F$13:$F$30,MATCH(A31,'32_定義マスター'!$A$13:$A$30,0))="","",INDEX('32_定義マスター'!$F$13:$F$30,MATCH(A31,'32_定義マスター'!$A$13:$A$30,0))))) | Q31: =IF(A31="","",IF(COUNTIF('32_定義マスター'!$A$13:$A$30,A31)<>1,"参照ID不正",IF(INDEX('32_定義マスター'!$G$13:$G$30,MATCH(A31,'32_定義マスター'!$A$13:$A$30,0))="","",INDEX('32_定義マスター'!$G$13:$G$30,MATCH(A31,'32_定義マスター'!$A$13:$A$30,0))))) | V31: =IF(OR(R31="",S31=""),"",R31&"@"&S31) | W31: =IF(A31="","",IF(COUNTIF('32_定義マスター'!$A$13:$A$30,A31)<>1,"EvalType不正",IF(OR(V31="",COUNTIF($V$4:$V$103,V31)<>1),"PlanKey不足・重複",IF(OR(P31="",P31="未設定",P31="設計中",P31="改訂中"),"計画未確定",IF(AND(P31<>"承認",P31<>"対象外承認"),"状態不正",IF(OR(T31="",U31="",O31=""),"計画対象・承認不足",IF(P31="対象外承認",IF(G31="","対象外理由不足","対象外計画記録"),IF(OR(G31="",H31="",I31="",J31="",K31="",L31="",M31="",N31=""),"評価設計不足",IF(AND(A31="E05",OR(X31="",Y31="",Z31="")),"試行状態・成功定義不足","計画記録あり")))))))))
B32: =IF(A32="","",IF(COUNTIF('32_定義マスター'!$A$13:$A$30,A32)<>1,"参照ID不正",IF(INDEX('32_定義マスター'!$B$13:$B$30,MATCH(A32,'32_定義マスター'!$A$13:$A$30,0))="","",INDEX('32_定義マスター'!$B$13:$B$30,MATCH(A32,'32_定義マスター'!$A$13:$A$30,0))))) | C32: =IF(A32="","",IF(COUNTIF('32_定義マスター'!$A$13:$A$30,A32)<>1,"参照ID不正",IF(INDEX('32_定義マスター'!$C$13:$C$30,MATCH(A32,'32_定義マスター'!$A$13:$A$30,0))="","",INDEX('32_定義マスター'!$C$13:$C$30,MATCH(A32,'32_定義マスター'!$A$13:$A$30,0))))) | D32: =IF(A32="","",IF(COUNTIF('32_定義マスター'!$A$13:$A$30,A32)<>1,"参照ID不正",IF(INDEX('32_定義マスター'!$D$13:$D$30,MATCH(A32,'32_定義マスター'!$A$13:$A$30,0))="","",INDEX('32_定義マスター'!$D$13:$D$30,MATCH(A32,'32_定義マスター'!$A$13:$A$30,0))))) | E32: =IF(A32="","",IF(COUNTIF('32_定義マスター'!$A$13:$A$30,A32)<>1,"参照ID不正",IF(INDEX('32_定義マスター'!$E$13:$E$30,MATCH(A32,'32_定義マスター'!$A$13:$A$30,0))="","",INDEX('32_定義マスター'!$E$13:$E$30,MATCH(A32,'32_定義マスター'!$A$13:$A$30,0))))) | F32: =IF(A32="","",IF(COUNTIF('32_定義マスター'!$A$13:$A$30,A32)<>1,"参照ID不正",IF(INDEX('32_定義マスター'!$F$13:$F$30,MATCH(A32,'32_定義マスター'!$A$13:$A$30,0))="","",INDEX('32_定義マスター'!$F$13:$F$30,MATCH(A32,'32_定義マスター'!$A$13:$A$30,0))))) | Q32: =IF(A32="","",IF(COUNTIF('32_定義マスター'!$A$13:$A$30,A32)<>1,"参照ID不正",IF(INDEX('32_定義マスター'!$G$13:$G$30,MATCH(A32,'32_定義マスター'!$A$13:$A$30,0))="","",INDEX('32_定義マスター'!$G$13:$G$30,MATCH(A32,'32_定義マスター'!$A$13:$A$30,0))))) | V32: =IF(OR(R32="",S32=""),"",R32&"@"&S32) | W32: =IF(A32="","",IF(COUNTIF('32_定義マスター'!$A$13:$A$30,A32)<>1,"EvalType不正",IF(OR(V32="",COUNTIF($V$4:$V$103,V32)<>1),"PlanKey不足・重複",IF(OR(P32="",P32="未設定",P32="設計中",P32="改訂中"),"計画未確定",IF(AND(P32<>"承認",P32<>"対象外承認"),"状態不正",IF(OR(T32="",U32="",O32=""),"計画対象・承認不足",IF(P32="対象外承認",IF(G32="","対象外理由不足","対象外計画記録"),IF(OR(G32="",H32="",I32="",J32="",K32="",L32="",M32="",N32=""),"評価設計不足",IF(AND(A32="E05",OR(X32="",Y32="",Z32="")),"試行状態・成功定義不足","計画記録あり")))))))))
B33: =IF(A33="","",IF(COUNTIF('32_定義マスター'!$A$13:$A$30,A33)<>1,"参照ID不正",IF(INDEX('32_定義マスター'!$B$13:$B$30,MATCH(A33,'32_定義マスター'!$A$13:$A$30,0))="","",INDEX('32_定義マスター'!$B$13:$B$30,MATCH(A33,'32_定義マスター'!$A$13:$A$30,0))))) | C33: =IF(A33="","",IF(COUNTIF('32_定義マスター'!$A$13:$A$30,A33)<>1,"参照ID不正",IF(INDEX('32_定義マスター'!$C$13:$C$30,MATCH(A33,'32_定義マスター'!$A$13:$A$30,0))="","",INDEX('32_定義マスター'!$C$13:$C$30,MATCH(A33,'32_定義マスター'!$A$13:$A$30,0))))) | D33: =IF(A33="","",IF(COUNTIF('32_定義マスター'!$A$13:$A$30,A33)<>1,"参照ID不正",IF(INDEX('32_定義マスター'!$D$13:$D$30,MATCH(A33,'32_定義マスター'!$A$13:$A$30,0))="","",INDEX('32_定義マスター'!$D$13:$D$30,MATCH(A33,'32_定義マスター'!$A$13:$A$30,0))))) | E33: =IF(A33="","",IF(COUNTIF('32_定義マスター'!$A$13:$A$30,A33)<>1,"参照ID不正",IF(INDEX('32_定義マスター'!$E$13:$E$30,MATCH(A33,'32_定義マスター'!$A$13:$A$30,0))="","",INDEX('32_定義マスター'!$E$13:$E$30,MATCH(A33,'32_定義マスター'!$A$13:$A$30,0))))) | F33: =IF(A33="","",IF(COUNTIF('32_定義マスター'!$A$13:$A$30,A33)<>1,"参照ID不正",IF(INDEX('32_定義マスター'!$F$13:$F$30,MATCH(A33,'32_定義マスター'!$A$13:$A$30,0))="","",INDEX('32_定義マスター'!$F$13:$F$30,MATCH(A33,'32_定義マスター'!$A$13:$A$30,0))))) | Q33: =IF(A33="","",IF(COUNTIF('32_定義マスター'!$A$13:$A$30,A33)<>1,"参照ID不正",IF(INDEX('32_定義マスター'!$G$13:$G$30,MATCH(A33,'32_定義マスター'!$A$13:$A$30,0))="","",INDEX('32_定義マスター'!$G$13:$G$30,MATCH(A33,'32_定義マスター'!$A$13:$A$30,0))))) | V33: =IF(OR(R33="",S33=""),"",R33&"@"&S33) | W33: =IF(A33="","",IF(COUNTIF('32_定義マスター'!$A$13:$A$30,A33)<>1,"EvalType不正",IF(OR(V33="",COUNTIF($V$4:$V$103,V33)<>1),"PlanKey不足・重複",IF(OR(P33="",P33="未設定",P33="設計中",P33="改訂中"),"計画未確定",IF(AND(P33<>"承認",P33<>"対象外承認"),"状態不正",IF(OR(T33="",U33="",O33=""),"計画対象・承認不足",IF(P33="対象外承認",IF(G33="","対象外理由不足","対象外計画記録"),IF(OR(G33="",H33="",I33="",J33="",K33="",L33="",M33="",N33=""),"評価設計不足",IF(AND(A33="E05",OR(X33="",Y33="",Z33="")),"試行状態・成功定義不足","計画記録あり")))))))))
... B103: =IF(A103="","",IF(COUNTIF('32_定義マスター'!$A$13:$A$30,A103)<>1,"参照ID不正",IF(INDEX('32_定義マスター'!$B$13:$B$30,MATCH(A103,'32_定義マスター'!$A$13:$A$30,0))="","",INDEX('32_定義マスター'!$B$13:$B$30,MATCH(A103,'32_定義マスター'!$A$13:$A$30,0))))) | C103: =IF(A103="","",IF(COUNTIF('32_定義マスター'!$A$13:$A$30,A103)<>1,"参照ID不正",IF(INDEX('32_定義マスター'!$C$13:$C$30,MATCH(A103,'32_定義マスター'!$A$13:$A$30,0))="","",INDEX('32_定義マスター'!$C$13:$C$30,MATCH(A103,'32_定義マスター'!$A$13:$A$30,0))))) | D103: =IF(A103="","",IF(COUNTIF('32_定義マスター'!$A$13:$A$30,A103)<>1,"参照ID不正",IF(INDEX('32_定義マスター'!$D$13:$D$30,MATCH(A103,'32_定義マスター'!$A$13:$A$30,0))="","",INDEX('32_定義マスター'!$D$13:$D$30,MATCH(A103,'32_定義マスター'!$A$13:$A$30,0))))) | E103: =IF(A103="","",IF(COUNTIF('32_定義マスター'!$A$13:$A$30,A103)<>1,"参照ID不正",IF(INDEX('32_定義マスター'!$E$13:$E$30,MATCH(A103,'32_定義マスター'!$A$13:$A$30,0))="","",INDEX('32_定義マスター'!$E$13:$E$30,MATCH(A103,'32_定義マスター'!$A$13:$A$30,0))))) | F103: =IF(A103="","",IF(COUNTIF('32_定義マスター'!$A$13:$A$30,A103)<>1,"参照ID不正",IF(INDEX('32_定義マスター'!$F$13:$F$30,MATCH(A103,'32_定義マスター'!$A$13:$A$30,0))="","",INDEX('32_定義マスター'!$F$13:$F$30,MATCH(A103,'32_定義マスター'!$A$13:$A$30,0))))) | Q103: =IF(A103="","",IF(COUNTIF('32_定義マスター'!$A$13:$A$30,A103)<>1,"参照ID不正",IF(INDEX('32_定義マスター'!$G$13:$G$30,MATCH(A103,'32_定義マスター'!$A$13:$A$30,0))="","",INDEX('32_定義マスター'!$G$13:$G$30,MATCH(A103,'32_定義マスター'!$A$13:$A$30,0))))) | V103: =IF(OR(R103="",S103=""),"",R103&"@"&S103) | W103: =IF(A103="","",IF(COUNTIF('32_定義マスター'!$A$13:$A$30,A103)<>1,"EvalType不正",IF(OR(V103="",COUNTIF($V$4:$V$103,V103)<>1),"PlanKey不足・重複",IF(OR(P103="",P103="未設定",P103="設計中",P103="改訂中"),"計画未確定",IF(AND(P103<>"承認",P103<>"対象外承認"),"状態不正",IF(OR(T103="",U103="",O103=""),"計画対象・承認不足",IF(P103="対象外承認",IF(G103="","対象外理由不足","対象外計画記録"),IF(OR(G103="",H103="",I103="",J103="",K103="",L103="",M103="",N103=""),"評価設計不足",IF(AND(A103="E05",OR(X103="",Y103="",Z103="")),"試行状態・成功定義不足","計画記録あり")))))))))

Sheet 16_評価実績インデックス
A1: 評価実績インデックス｜結果を上書きしない
A2: 1行=EvalRun。Aは一意、B=PlanID@版、T=実行構成hash。再実行・変更は新Run。採点と実世界の結果を保存。
A3: Run ID | B3: EvalPlanKey | C3: 対象Release/Issue | D3: 日時 | E3: Model版 | F3: Prompt/Policy版 | G3: Data/Evalセット版 | H3: Tool/Skill/Runtime版 | I3: 母集団/slice/試行数 | J3: 計画版（参照） | K3: 実測/区間/単位 | L3: 重大失敗/未解決 | M3: 採点者/方式 | N3: 独立確認者 | O3: 人の合否 | P3: 証拠URI | Q3: 限界・補正・再実行理由 | R3: 承認日 | S3: 記録点検 | T3: ManifestHash | U3: Trial／初期状態・副作用URI | V3: 実行者PersonID | W3: 独立確認者PersonID | X3: 無効化・取消理由 | Y3: 凍結計画Key照合
J4: =IF(A4="","",IF(COUNTIF('15_評価計画・品質ゲート'!$V$4:$V$103,B4)<>1,"参照ID不正",IF(INDEX('15_評価計画・品質ゲート'!$S$4:$S$103,MATCH(B4,'15_評価計画・品質ゲート'!$V$4:$V$103,0))="","",INDEX('15_評価計画・品質ゲート'!$S$4:$S$103,MATCH(B4,'15_評価計画・品質ゲート'!$V$4:$V$103,0))))) | S4: =IF(A4="","",IF(COUNTIF($A$4:$A$103,A4)<>1,"Run ID重複",IF(Y4<>"計画・構成一致",Y4,IF(X4<>"","無効化Run",IF(OR(OR(C4="",E4="",F4="",G4="",H4="",I4="",K4="",M4="",N4="",P4="",T4=""),LEN(L4&"")=0,COUNT(D4,R4)<2),"記録不足",IF(OR(AND(D4<>"",OR(NOT(ISNUMBER(D4)),IFERROR(D4<1,TRUE),IFERROR(INT(D4)>INT(AsOfDate),TRUE))),AND(R4<>"",OR(NOT(ISNUMBER(R4)),IFERROR(R4<1,TRUE),IFERROR(INT(R4)>INT(AsOfDate),TRUE)))),"実績日時不正",IF(R4<D4,"評価承認日時逆転",IF(OR(V4="",W4="",V4=W4),"独立確認Person不足",IF(AND(IF(COUNTIF('15_評価計画・品質ゲート'!$V$4:$V$103,B4)<>1,"参照ID不正",IF(INDEX('15_評価計画・品質ゲート'!$A$4:$A$103,MATCH(B4,'15_評価計画・品質ゲート'!$V$4:$V$103,0))="","",INDEX('15_評価計画・品質ゲート'!$A$4:$A$103,MATCH(B4,'15_評価計画・品質ゲート'!$V$4:$V$103,0))))="E05",U4=""),"Trial状態証拠不足",IF(OR(O4="",O4="未判定",O4="無効/再実行"),"評価判定未確定","記録あり・内容審査別")))))))))) | Y4: =IF(A4="","",IF(COUNTIF(EvalPlanKeys,B4)<>1,"PlanKey不正",IF(OR(T4="",T4<>IF(COUNTIF('15_評価計画・品質ゲート'!$V$4:$V$103,B4)<>1,"参照ID不正",IF(INDEX('15_評価計画・品質ゲート'!$U$4:$U$103,MATCH(B4,'15_評価計画・品質ゲート'!$V$4:$V$103,0))="","",INDEX('15_評価計画・品質ゲート'!$U$4:$U$103,MATCH(B4,'15_評価計画・品質ゲート'!$V$4:$V$103,0))))),"Manifest不一致",IF(IF(COUNTIF('15_評価計画・品質ゲート'!$V$4:$V$103,B4)<>1,"参照ID不正",IF(INDEX('15_評価計画・品質ゲート'!$W$4:$W$103,MATCH(B4,'15_評価計画・品質ゲート'!$V$4:$V$103,0))="","",INDEX('15_評価計画・品質ゲート'!$W$4:$W$103,MATCH(B4,'15_評価計画・品質ゲート'!$V$4:$V$103,0))))<>"計画記録あり","計画未承認・不足","計画・構成一致"))))
J5: =IF(A5="","",IF(COUNTIF('15_評価計画・品質ゲート'!$V$4:$V$103,B5)<>1,"参照ID不正",IF(INDEX('15_評価計画・品質ゲート'!$S$4:$S$103,MATCH(B5,'15_評価計画・品質ゲート'!$V$4:$V$103,0))="","",INDEX('15_評価計画・品質ゲート'!$S$4:$S$103,MATCH(B5,'15_評価計画・品質ゲート'!$V$4:$V$103,0))))) | S5: =IF(A5="","",IF(COUNTIF($A$4:$A$103,A5)<>1,"Run ID重複",IF(Y5<>"計画・構成一致",Y5,IF(X5<>"","無効化Run",IF(OR(OR(C5="",E5="",F5="",G5="",H5="",I5="",K5="",M5="",N5="",P5="",T5=""),LEN(L5&"")=0,COUNT(D5,R5)<2),"記録不足",IF(OR(AND(D5<>"",OR(NOT(ISNUMBER(D5)),IFERROR(D5<1,TRUE),IFERROR(INT(D5)>INT(AsOfDate),TRUE))),AND(R5<>"",OR(NOT(ISNUMBER(R5)),IFERROR(R5<1,TRUE),IFERROR(INT(R5)>INT(AsOfDate),TRUE)))),"実績日時不正",IF(R5<D5,"評価承認日時逆転",IF(OR(V5="",W5="",V5=W5),"独立確認Person不足",IF(AND(IF(COUNTIF('15_評価計画・品質ゲート'!$V$4:$V$103,B5)<>1,"参照ID不正",IF(INDEX('15_評価計画・品質ゲート'!$A$4:$A$103,MATCH(B5,'15_評価計画・品質ゲート'!$V$4:$V$103,0))="","",INDEX('15_評価計画・品質ゲート'!$A$4:$A$103,MATCH(B5,'15_評価計画・品質ゲート'!$V$4:$V$103,0))))="E05",U5=""),"Trial状態証拠不足",IF(OR(O5="",O5="未判定",O5="無効/再実行"),"評価判定未確定","記録あり・内容審査別")))))))))) | Y5: =IF(A5="","",IF(COUNTIF(EvalPlanKeys,B5)<>1,"PlanKey不正",IF(OR(T5="",T5<>IF(COUNTIF('15_評価計画・品質ゲート'!$V$4:$V$103,B5)<>1,"参照ID不正",IF(INDEX('15_評価計画・品質ゲート'!$U$4:$U$103,MATCH(B5,'15_評価計画・品質ゲート'!$V$4:$V$103,0))="","",INDEX('15_評価計画・品質ゲート'!$U$4:$U$103,MATCH(B5,'15_評価計画・品質ゲート'!$V$4:$V$103,0))))),"Manifest不一致",IF(IF(COUNTIF('15_評価計画・品質ゲート'!$V$4:$V$103,B5)<>1,"参照ID不正",IF(INDEX('15_評価計画・品質ゲート'!$W$4:$W$103,MATCH(B5,'15_評価計画・品質ゲート'!$V$4:$V$103,0))="","",INDEX('15_評価計画・品質ゲート'!$W$4:$W$103,MATCH(B5,'15_評価計画・品質ゲート'!$V$4:$V$103,0))))<>"計画記録あり","計画未承認・不足","計画・構成一致"))))
J6: =IF(A6="","",IF(COUNTIF('15_評価計画・品質ゲート'!$V$4:$V$103,B6)<>1,"参照ID不正",IF(INDEX('15_評価計画・品質ゲート'!$S$4:$S$103,MATCH(B6,'15_評価計画・品質ゲート'!$V$4:$V$103,0))="","",INDEX('15_評価計画・品質ゲート'!$S$4:$S$103,MATCH(B6,'15_評価計画・品質ゲート'!$V$4:$V$103,0))))) | S6: =IF(A6="","",IF(COUNTIF($A$4:$A$103,A6)<>1,"Run ID重複",IF(Y6<>"計画・構成一致",Y6,IF(X6<>"","無効化Run",IF(OR(OR(C6="",E6="",F6="",G6="",H6="",I6="",K6="",M6="",N6="",P6="",T6=""),LEN(L6&"")=0,COUNT(D6,R6)<2),"記録不足",IF(OR(AND(D6<>"",OR(NOT(ISNUMBER(D6)),IFERROR(D6<1,TRUE),IFERROR(INT(D6)>INT(AsOfDate),TRUE))),AND(R6<>"",OR(NOT(ISNUMBER(R6)),IFERROR(R6<1,TRUE),IFERROR(INT(R6)>INT(AsOfDate),TRUE)))),"実績日時不正",IF(R6<D6,"評価承認日時逆転",IF(OR(V6="",W6="",V6=W6),"独立確認Person不足",IF(AND(IF(COUNTIF('15_評価計画・品質ゲート'!$V$4:$V$103,B6)<>1,"参照ID不正",IF(INDEX('15_評価計画・品質ゲート'!$A$4:$A$103,MATCH(B6,'15_評価計画・品質ゲート'!$V$4:$V$103,0))="","",INDEX('15_評価計画・品質ゲート'!$A$4:$A$103,MATCH(B6,'15_評価計画・品質ゲート'!$V$4:$V$103,0))))="E05",U6=""),"Trial状態証拠不足",IF(OR(O6="",O6="未判定",O6="無効/再実行"),"評価判定未確定","記録あり・内容審査別")))))))))) | Y6: =IF(A6="","",IF(COUNTIF(EvalPlanKeys,B6)<>1,"PlanKey不正",IF(OR(T6="",T6<>IF(COUNTIF('15_評価計画・品質ゲート'!$V$4:$V$103,B6)<>1,"参照ID不正",IF(INDEX('15_評価計画・品質ゲート'!$U$4:$U$103,MATCH(B6,'15_評価計画・品質ゲート'!$V$4:$V$103,0))="","",INDEX('15_評価計画・品質ゲート'!$U$4:$U$103,MATCH(B6,'15_評価計画・品質ゲート'!$V$4:$V$103,0))))),"Manifest不一致",IF(IF(COUNTIF('15_評価計画・品質ゲート'!$V$4:$V$103,B6)<>1,"参照ID不正",IF(INDEX('15_評価計画・品質ゲート'!$W$4:$W$103,MATCH(B6,'15_評価計画・品質ゲート'!$V$4:$V$103,0))="","",INDEX('15_評価計画・品質ゲート'!$W$4:$W$103,MATCH(B6,'15_評価計画・品質ゲート'!$V$4:$V$103,0))))<>"計画記録あり","計画未承認・不足","計画・構成一致"))))
J7: =IF(A7="","",IF(COUNTIF('15_評価計画・品質ゲート'!$V$4:$V$103,B7)<>1,"参照ID不正",IF(INDEX('15_評価計画・品質ゲート'!$S$4:$S$103,MATCH(B7,'15_評価計画・品質ゲート'!$V$4:$V$103,0))="","",INDEX('15_評価計画・品質ゲート'!$S$4:$S$103,MATCH(B7,'15_評価計画・品質ゲート'!$V$4:$V$103,0))))) | S7: =IF(A7="","",IF(COUNTIF($A$4:$A$103,A7)<>1,"Run ID重複",IF(Y7<>"計画・構成一致",Y7,IF(X7<>"","無効化Run",IF(OR(OR(C7="",E7="",F7="",G7="",H7="",I7="",K7="",M7="",N7="",P7="",T7=""),LEN(L7&"")=0,COUNT(D7,R7)<2),"記録不足",IF(OR(AND(D7<>"",OR(NOT(ISNUMBER(D7)),IFERROR(D7<1,TRUE),IFERROR(INT(D7)>INT(AsOfDate),TRUE))),AND(R7<>"",OR(NOT(ISNUMBER(R7)),IFERROR(R7<1,TRUE),IFERROR(INT(R7)>INT(AsOfDate),TRUE)))),"実績日時不正",IF(R7<D7,"評価承認日時逆転",IF(OR(V7="",W7="",V7=W7),"独立確認Person不足",IF(AND(IF(COUNTIF('15_評価計画・品質ゲート'!$V$4:$V$103,B7)<>1,"参照ID不正",IF(INDEX('15_評価計画・品質ゲート'!$A$4:$A$103,MATCH(B7,'15_評価計画・品質ゲート'!$V$4:$V$103,0))="","",INDEX('15_評価計画・品質ゲート'!$A$4:$A$103,MATCH(B7,'15_評価計画・品質ゲート'!$V$4:$V$103,0))))="E05",U7=""),"Trial状態証拠不足",IF(OR(O7="",O7="未判定",O7="無効/再実行"),"評価判定未確定","記録あり・内容審査別")))))))))) | Y7: =IF(A7="","",IF(COUNTIF(EvalPlanKeys,B7)<>1,"PlanKey不正",IF(OR(T7="",T7<>IF(COUNTIF('15_評価計画・品質ゲート'!$V$4:$V$103,B7)<>1,"参照ID不正",IF(INDEX('15_評価計画・品質ゲート'!$U$4:$U$103,MATCH(B7,'15_評価計画・品質ゲート'!$V$4:$V$103,0))="","",INDEX('15_評価計画・品質ゲート'!$U$4:$U$103,MATCH(B7,'15_評価計画・品質ゲート'!$V$4:$V$103,0))))),"Manifest不一致",IF(IF(COUNTIF('15_評価計画・品質ゲート'!$V$4:$V$103,B7)<>1,"参照ID不正",IF(INDEX('15_評価計画・品質ゲート'!$W$4:$W$103,MATCH(B7,'15_評価計画・品質ゲート'!$V$4:$V$103,0))="","",INDEX('15_評価計画・品質ゲート'!$W$4:$W$103,MATCH(B7,'15_評価計画・品質ゲート'!$V$4:$V$103,0))))<>"計画記録あり","計画未承認・不足","計画・構成一致"))))
J8: =IF(A8="","",IF(COUNTIF('15_評価計画・品質ゲート'!$V$4:$V$103,B8)<>1,"参照ID不正",IF(INDEX('15_評価計画・品質ゲート'!$S$4:$S$103,MATCH(B8,'15_評価計画・品質ゲート'!$V$4:$V$103,0))="","",INDEX('15_評価計画・品質ゲート'!$S$4:$S$103,MATCH(B8,'15_評価計画・品質ゲート'!$V$4:$V$103,0))))) | S8: =IF(A8="","",IF(COUNTIF($A$4:$A$103,A8)<>1,"Run ID重複",IF(Y8<>"計画・構成一致",Y8,IF(X8<>"","無効化Run",IF(OR(OR(C8="",E8="",F8="",G8="",H8="",I8="",K8="",M8="",N8="",P8="",T8=""),LEN(L8&"")=0,COUNT(D8,R8)<2),"記録不足",IF(OR(AND(D8<>"",OR(NOT(ISNUMBER(D8)),IFERROR(D8<1,TRUE),IFERROR(INT(D8)>INT(AsOfDate),TRUE))),AND(R8<>"",OR(NOT(ISNUMBER(R8)),IFERROR(R8<1,TRUE),IFERROR(INT(R8)>INT(AsOfDate),TRUE)))),"実績日時不正",IF(R8<D8,"評価承認日時逆転",IF(OR(V8="",W8="",V8=W8),"独立確認Person不足",IF(AND(IF(COUNTIF('15_評価計画・品質ゲート'!$V$4:$V$103,B8)<>1,"参照ID不正",IF(INDEX('15_評価計画・品質ゲート'!$A$4:$A$103,MATCH(B8,'15_評価計画・品質ゲート'!$V$4:$V$103,0))="","",INDEX('15_評価計画・品質ゲート'!$A$4:$A$103,MATCH(B8,'15_評価計画・品質ゲート'!$V$4:$V$103,0))))="E05",U8=""),"Trial状態証拠不足",IF(OR(O8="",O8="未判定",O8="無効/再実行"),"評価判定未確定","記録あり・内容審査別")))))))))) | Y8: =IF(A8="","",IF(COUNTIF(EvalPlanKeys,B8)<>1,"PlanKey不正",IF(OR(T8="",T8<>IF(COUNTIF('15_評価計画・品質ゲート'!$V$4:$V$103,B8)<>1,"参照ID不正",IF(INDEX('15_評価計画・品質ゲート'!$U$4:$U$103,MATCH(B8,'15_評価計画・品質ゲート'!$V$4:$V$103,0))="","",INDEX('15_評価計画・品質ゲート'!$U$4:$U$103,MATCH(B8,'15_評価計画・品質ゲート'!$V$4:$V$103,0))))),"Manifest不一致",IF(IF(COUNTIF('15_評価計画・品質ゲート'!$V$4:$V$103,B8)<>1,"参照ID不正",IF(INDEX('15_評価計画・品質ゲート'!$W$4:$W$103,MATCH(B8,'15_評価計画・品質ゲート'!$V$4:$V$103,0))="","",INDEX('15_評価計画・品質ゲート'!$W$4:$W$103,MATCH(B8,'15_評価計画・品質ゲート'!$V$4:$V$103,0))))<>"計画記録あり","計画未承認・不足","計画・構成一致"))))
J9: =IF(A9="","",IF(COUNTIF('15_評価計画・品質ゲート'!$V$4:$V$103,B9)<>1,"参照ID不正",IF(INDEX('15_評価計画・品質ゲート'!$S$4:$S$103,MATCH(B9,'15_評価計画・品質ゲート'!$V$4:$V$103,0))="","",INDEX('15_評価計画・品質ゲート'!$S$4:$S$103,MATCH(B9,'15_評価計画・品質ゲート'!$V$4:$V$103,0))))) | S9: =IF(A9="","",IF(COUNTIF($A$4:$A$103,A9)<>1,"Run ID重複",IF(Y9<>"計画・構成一致",Y9,IF(X9<>"","無効化Run",IF(OR(OR(C9="",E9="",F9="",G9="",H9="",I9="",K9="",M9="",N9="",P9="",T9=""),LEN(L9&"")=0,COUNT(D9,R9)<2),"記録不足",IF(OR(AND(D9<>"",OR(NOT(ISNUMBER(D9)),IFERROR(D9<1,TRUE),IFERROR(INT(D9)>INT(AsOfDate),TRUE))),AND(R9<>"",OR(NOT(ISNUMBER(R9)),IFERROR(R9<1,TRUE),IFERROR(INT(R9)>INT(AsOfDate),TRUE)))),"実績日時不正",IF(R9<D9,"評価承認日時逆転",IF(OR(V9="",W9="",V9=W9),"独立確認Person不足",IF(AND(IF(COUNTIF('15_評価計画・品質ゲート'!$V$4:$V$103,B9)<>1,"参照ID不正",IF(INDEX('15_評価計画・品質ゲート'!$A$4:$A$103,MATCH(B9,'15_評価計画・品質ゲート'!$V$4:$V$103,0))="","",INDEX('15_評価計画・品質ゲート'!$A$4:$A$103,MATCH(B9,'15_評価計画・品質ゲート'!$V$4:$V$103,0))))="E05",U9=""),"Trial状態証拠不足",IF(OR(O9="",O9="未判定",O9="無効/再実行"),"評価判定未確定","記録あり・内容審査別")))))))))) | Y9: =IF(A9="","",IF(COUNTIF(EvalPlanKeys,B9)<>1,"PlanKey不正",IF(OR(T9="",T9<>IF(COUNTIF('15_評価計画・品質ゲート'!$V$4:$V$103,B9)<>1,"参照ID不正",IF(INDEX('15_評価計画・品質ゲート'!$U$4:$U$103,MATCH(B9,'15_評価計画・品質ゲート'!$V$4:$V$103,0))="","",INDEX('15_評価計画・品質ゲート'!$U$4:$U$103,MATCH(B9,'15_評価計画・品質ゲート'!$V$4:$V$103,0))))),"Manifest不一致",IF(IF(COUNTIF('15_評価計画・品質ゲート'!$V$4:$V$103,B9)<>1,"参照ID不正",IF(INDEX('15_評価計画・品質ゲート'!$W$4:$W$103,MATCH(B9,'15_評価計画・品質ゲート'!$V$4:$V$103,0))="","",INDEX('15_評価計画・品質ゲート'!$W$4:$W$103,MATCH(B9,'15_評価計画・品質ゲート'!$V$4:$V$103,0))))<>"計画記録あり","計画未承認・不足","計画・構成一致"))))
J10: =IF(A10="","",IF(COUNTIF('15_評価計画・品質ゲート'!$V$4:$V$103,B10)<>1,"参照ID不正",IF(INDEX('15_評価計画・品質ゲート'!$S$4:$S$103,MATCH(B10,'15_評価計画・品質ゲート'!$V$4:$V$103,0))="","",INDEX('15_評価計画・品質ゲート'!$S$4:$S$103,MATCH(B10,'15_評価計画・品質ゲート'!$V$4:$V$103,0))))) | S10: =IF(A10="","",IF(COUNTIF($A$4:$A$103,A10)<>1,"Run ID重複",IF(Y10<>"計画・構成一致",Y10,IF(X10<>"","無効化Run",IF(OR(OR(C10="",E10="",F10="",G10="",H10="",I10="",K10="",M10="",N10="",P10="",T10=""),LEN(L10&"")=0,COUNT(D10,R10)<2),"記録不足",IF(OR(AND(D10<>"",OR(NOT(ISNUMBER(D10)),IFERROR(D10<1,TRUE),IFERROR(INT(D10)>INT(AsOfDate),TRUE))),AND(R10<>"",OR(NOT(ISNUMBER(R10)),IFERROR(R10<1,TRUE),IFERROR(INT(R10)>INT(AsOfDate),TRUE)))),"実績日時不正",IF(R10<D10,"評価承認日時逆転",IF(OR(V10="",W10="",V10=W10),"独立確認Person不足",IF(AND(IF(COUNTIF('15_評価計画・品質ゲート'!$V$4:$V$103,B10)<>1,"参照ID不正",IF(INDEX('15_評価計画・品質ゲート'!$A$4:$A$103,MATCH(B10,'15_評価計画・品質ゲート'!$V$4:$V$103,0))="","",INDEX('15_評価計画・品質ゲート'!$A$4:$A$103,MATCH(B10,'15_評価計画・品質ゲート'!$V$4:$V$103,0))))="E05",U10=""),"Trial状態証拠不足",IF(OR(O10="",O10="未判定",O10="無効/再実行"),"評価判定未確定","記録あり・内容審査別")))))))))) | Y10: =IF(A10="","",IF(COUNTIF(EvalPlanKeys,B10)<>1,"PlanKey不正",IF(OR(T10="",T10<>IF(COUNTIF('15_評価計画・品質ゲート'!$V$4:$V$103,B10)<>1,"参照ID不正",IF(INDEX('15_評価計画・品質ゲート'!$U$4:$U$103,MATCH(B10,'15_評価計画・品質ゲート'!$V$4:$V$103,0))="","",INDEX('15_評価計画・品質ゲート'!$U$4:$U$103,MATCH(B10,'15_評価計画・品質ゲート'!$V$4:$V$103,0))))),"Manifest不一致",IF(IF(COUNTIF('15_評価計画・品質ゲート'!$V$4:$V$103,B10)<>1,"参照ID不正",IF(INDEX('15_評価計画・品質ゲート'!$W$4:$W$103,MATCH(B10,'15_評価計画・品質ゲート'!$V$4:$V$103,0))="","",INDEX('15_評価計画・品質ゲート'!$W$4:$W$103,MATCH(B10,'15_評価計画・品質ゲート'!$V$4:$V$103,0))))<>"計画記録あり","計画未承認・不足","計画・構成一致"))))
J11: =IF(A11="","",IF(COUNTIF('15_評価計画・品質ゲート'!$V$4:$V$103,B11)<>1,"参照ID不正",IF(INDEX('15_評価計画・品質ゲート'!$S$4:$S$103,MATCH(B11,'15_評価計画・品質ゲート'!$V$4:$V$103,0))="","",INDEX('15_評価計画・品質ゲート'!$S$4:$S$103,MATCH(B11,'15_評価計画・品質ゲート'!$V$4:$V$103,0))))) | S11: =IF(A11="","",IF(COUNTIF($A$4:$A$103,A11)<>1,"Run ID重複",IF(Y11<>"計画・構成一致",Y11,IF(X11<>"","無効化Run",IF(OR(OR(C11="",E11="",F11="",G11="",H11="",I11="",K11="",M11="",N11="",P11="",T11=""),LEN(L11&"")=0,COUNT(D11,R11)<2),"記録不足",IF(OR(AND(D11<>"",OR(NOT(ISNUMBER(D11)),IFERROR(D11<1,TRUE),IFERROR(INT(D11)>INT(AsOfDate),TRUE))),AND(R11<>"",OR(NOT(ISNUMBER(R11)),IFERROR(R11<1,TRUE),IFERROR(INT(R11)>INT(AsOfDate),TRUE)))),"実績日時不正",IF(R11<D11,"評価承認日時逆転",IF(OR(V11="",W11="",V11=W11),"独立確認Person不足",IF(AND(IF(COUNTIF('15_評価計画・品質ゲート'!$V$4:$V$103,B11)<>1,"参照ID不正",IF(INDEX('15_評価計画・品質ゲート'!$A$4:$A$103,MATCH(B11,'15_評価計画・品質ゲート'!$V$4:$V$103,0))="","",INDEX('15_評価計画・品質ゲート'!$A$4:$A$103,MATCH(B11,'15_評価計画・品質ゲート'!$V$4:$V$103,0))))="E05",U11=""),"Trial状態証拠不足",IF(OR(O11="",O11="未判定",O11="無効/再実行"),"評価判定未確定","記録あり・内容審査別")))))))))) | Y11: =IF(A11="","",IF(COUNTIF(EvalPlanKeys,B11)<>1,"PlanKey不正",IF(OR(T11="",T11<>IF(COUNTIF('15_評価計画・品質ゲート'!$V$4:$V$103,B11)<>1,"参照ID不正",IF(INDEX('15_評価計画・品質ゲート'!$U$4:$U$103,MATCH(B11,'15_評価計画・品質ゲート'!$V$4:$V$103,0))="","",INDEX('15_評価計画・品質ゲート'!$U$4:$U$103,MATCH(B11,'15_評価計画・品質ゲート'!$V$4:$V$103,0))))),"Manifest不一致",IF(IF(COUNTIF('15_評価計画・品質ゲート'!$V$4:$V$103,B11)<>1,"参照ID不正",IF(INDEX('15_評価計画・品質ゲート'!$W$4:$W$103,MATCH(B11,'15_評価計画・品質ゲート'!$V$4:$V$103,0))="","",INDEX('15_評価計画・品質ゲート'!$W$4:$W$103,MATCH(B11,'15_評価計画・品質ゲート'!$V$4:$V$103,0))))<>"計画記録あり","計画未承認・不足","計画・構成一致"))))
J12: =IF(A12="","",IF(COUNTIF('15_評価計画・品質ゲート'!$V$4:$V$103,B12)<>1,"参照ID不正",IF(INDEX('15_評価計画・品質ゲート'!$S$4:$S$103,MATCH(B12,'15_評価計画・品質ゲート'!$V$4:$V$103,0))="","",INDEX('15_評価計画・品質ゲート'!$S$4:$S$103,MATCH(B12,'15_評価計画・品質ゲート'!$V$4:$V$103,0))))) | S12: =IF(A12="","",IF(COUNTIF($A$4:$A$103,A12)<>1,"Run ID重複",IF(Y12<>"計画・構成一致",Y12,IF(X12<>"","無効化Run",IF(OR(OR(C12="",E12="",F12="",G12="",H12="",I12="",K12="",M12="",N12="",P12="",T12=""),LEN(L12&"")=0,COUNT(D12,R12)<2),"記録不足",IF(OR(AND(D12<>"",OR(NOT(ISNUMBER(D12)),IFERROR(D12<1,TRUE),IFERROR(INT(D12)>INT(AsOfDate),TRUE))),AND(R12<>"",OR(NOT(ISNUMBER(R12)),IFERROR(R12<1,TRUE),IFERROR(INT(R12)>INT(AsOfDate),TRUE)))),"実績日時不正",IF(R12<D12,"評価承認日時逆転",IF(OR(V12="",W12="",V12=W12),"独立確認Person不足",IF(AND(IF(COUNTIF('15_評価計画・品質ゲート'!$V$4:$V$103,B12)<>1,"参照ID不正",IF(INDEX('15_評価計画・品質ゲート'!$A$4:$A$103,MATCH(B12,'15_評価計画・品質ゲート'!$V$4:$V$103,0))="","",INDEX('15_評価計画・品質ゲート'!$A$4:$A$103,MATCH(B12,'15_評価計画・品質ゲート'!$V$4:$V$103,0))))="E05",U12=""),"Trial状態証拠不足",IF(OR(O12="",O12="未判定",O12="無効/再実行"),"評価判定未確定","記録あり・内容審査別")))))))))) | Y12: =IF(A12="","",IF(COUNTIF(EvalPlanKeys,B12)<>1,"PlanKey不正",IF(OR(T12="",T12<>IF(COUNTIF('15_評価計画・品質ゲート'!$V$4:$V$103,B12)<>1,"参照ID不正",IF(INDEX('15_評価計画・品質ゲート'!$U$4:$U$103,MATCH(B12,'15_評価計画・品質ゲート'!$V$4:$V$103,0))="","",INDEX('15_評価計画・品質ゲート'!$U$4:$U$103,MATCH(B12,'15_評価計画・品質ゲート'!$V$4:$V$103,0))))),"Manifest不一致",IF(IF(COUNTIF('15_評価計画・品質ゲート'!$V$4:$V$103,B12)<>1,"参照ID不正",IF(INDEX('15_評価計画・品質ゲート'!$W$4:$W$103,MATCH(B12,'15_評価計画・品質ゲート'!$V$4:$V$103,0))="","",INDEX('15_評価計画・品質ゲート'!$W$4:$W$103,MATCH(B12,'15_評価計画・品質ゲート'!$V$4:$V$103,0))))<>"計画記録あり","計画未承認・不足","計画・構成一致"))))
J13: =IF(A13="","",IF(COUNTIF('15_評価計画・品質ゲート'!$V$4:$V$103,B13)<>1,"参照ID不正",IF(INDEX('15_評価計画・品質ゲート'!$S$4:$S$103,MATCH(B13,'15_評価計画・品質ゲート'!$V$4:$V$103,0))="","",INDEX('15_評価計画・品質ゲート'!$S$4:$S$103,MATCH(B13,'15_評価計画・品質ゲート'!$V$4:$V$103,0))))) | S13: =IF(A13="","",IF(COUNTIF($A$4:$A$103,A13)<>1,"Run ID重複",IF(Y13<>"計画・構成一致",Y13,IF(X13<>"","無効化Run",IF(OR(OR(C13="",E13="",F13="",G13="",H13="",I13="",K13="",M13="",N13="",P13="",T13=""),LEN(L13&"")=0,COUNT(D13,R13)<2),"記録不足",IF(OR(AND(D13<>"",OR(NOT(ISNUMBER(D13)),IFERROR(D13<1,TRUE),IFERROR(INT(D13)>INT(AsOfDate),TRUE))),AND(R13<>"",OR(NOT(ISNUMBER(R13)),IFERROR(R13<1,TRUE),IFERROR(INT(R13)>INT(AsOfDate),TRUE)))),"実績日時不正",IF(R13<D13,"評価承認日時逆転",IF(OR(V13="",W13="",V13=W13),"独立確認Person不足",IF(AND(IF(COUNTIF('15_評価計画・品質ゲート'!$V$4:$V$103,B13)<>1,"参照ID不正",IF(INDEX('15_評価計画・品質ゲート'!$A$4:$A$103,MATCH(B13,'15_評価計画・品質ゲート'!$V$4:$V$103,0))="","",INDEX('15_評価計画・品質ゲート'!$A$4:$A$103,MATCH(B13,'15_評価計画・品質ゲート'!$V$4:$V$103,0))))="E05",U13=""),"Trial状態証拠不足",IF(OR(O13="",O13="未判定",O13="無効/再実行"),"評価判定未確定","記録あり・内容審査別")))))))))) | Y13: =IF(A13="","",IF(COUNTIF(EvalPlanKeys,B13)<>1,"PlanKey不正",IF(OR(T13="",T13<>IF(COUNTIF('15_評価計画・品質ゲート'!$V$4:$V$103,B13)<>1,"参照ID不正",IF(INDEX('15_評価計画・品質ゲート'!$U$4:$U$103,MATCH(B13,'15_評価計画・品質ゲート'!$V$4:$V$103,0))="","",INDEX('15_評価計画・品質ゲート'!$U$4:$U$103,MATCH(B13,'15_評価計画・品質ゲート'!$V$4:$V$103,0))))),"Manifest不一致",IF(IF(COUNTIF('15_評価計画・品質ゲート'!$V$4:$V$103,B13)<>1,"参照ID不正",IF(INDEX('15_評価計画・品質ゲート'!$W$4:$W$103,MATCH(B13,'15_評価計画・品質ゲート'!$V$4:$V$103,0))="","",INDEX('15_評価計画・品質ゲート'!$W$4:$W$103,MATCH(B13,'15_評価計画・品質ゲート'!$V$4:$V$103,0))))<>"計画記録あり","計画未承認・不足","計画・構成一致"))))
J14: =IF(A14="","",IF(COUNTIF('15_評価計画・品質ゲート'!$V$4:$V$103,B14)<>1,"参照ID不正",IF(INDEX('15_評価計画・品質ゲート'!$S$4:$S$103,MATCH(B14,'15_評価計画・品質ゲート'!$V$4:$V$103,0))="","",INDEX('15_評価計画・品質ゲート'!$S$4:$S$103,MATCH(B14,'15_評価計画・品質ゲート'!$V$4:$V$103,0))))) | S14: =IF(A14="","",IF(COUNTIF($A$4:$A$103,A14)<>1,"Run ID重複",IF(Y14<>"計画・構成一致",Y14,IF(X14<>"","無効化Run",IF(OR(OR(C14="",E14="",F14="",G14="",H14="",I14="",K14="",M14="",N14="",P14="",T14=""),LEN(L14&"")=0,COUNT(D14,R14)<2),"記録不足",IF(OR(AND(D14<>"",OR(NOT(ISNUMBER(D14)),IFERROR(D14<1,TRUE),IFERROR(INT(D14)>INT(AsOfDate),TRUE))),AND(R14<>"",OR(NOT(ISNUMBER(R14)),IFERROR(R14<1,TRUE),IFERROR(INT(R14)>INT(AsOfDate),TRUE)))),"実績日時不正",IF(R14<D14,"評価承認日時逆転",IF(OR(V14="",W14="",V14=W14),"独立確認Person不足",IF(AND(IF(COUNTIF('15_評価計画・品質ゲート'!$V$4:$V$103,B14)<>1,"参照ID不正",IF(INDEX('15_評価計画・品質ゲート'!$A$4:$A$103,MATCH(B14,'15_評価計画・品質ゲート'!$V$4:$V$103,0))="","",INDEX('15_評価計画・品質ゲート'!$A$4:$A$103,MATCH(B14,'15_評価計画・品質ゲート'!$V$4:$V$103,0))))="E05",U14=""),"Trial状態証拠不足",IF(OR(O14="",O14="未判定",O14="無効/再実行"),"評価判定未確定","記録あり・内容審査別")))))))))) | Y14: =IF(A14="","",IF(COUNTIF(EvalPlanKeys,B14)<>1,"PlanKey不正",IF(OR(T14="",T14<>IF(COUNTIF('15_評価計画・品質ゲート'!$V$4:$V$103,B14)<>1,"参照ID不正",IF(INDEX('15_評価計画・品質ゲート'!$U$4:$U$103,MATCH(B14,'15_評価計画・品質ゲート'!$V$4:$V$103,0))="","",INDEX('15_評価計画・品質ゲート'!$U$4:$U$103,MATCH(B14,'15_評価計画・品質ゲート'!$V$4:$V$103,0))))),"Manifest不一致",IF(IF(COUNTIF('15_評価計画・品質ゲート'!$V$4:$V$103,B14)<>1,"参照ID不正",IF(INDEX('15_評価計画・品質ゲート'!$W$4:$W$103,MATCH(B14,'15_評価計画・品質ゲート'!$V$4:$V$103,0))="","",INDEX('15_評価計画・品質ゲート'!$W$4:$W$103,MATCH(B14,'15_評価計画・品質ゲート'!$V$4:$V$103,0))))<>"計画記録あり","計画未承認・不足","計画・構成一致"))))
J15: =IF(A15="","",IF(COUNTIF('15_評価計画・品質ゲート'!$V$4:$V$103,B15)<>1,"参照ID不正",IF(INDEX('15_評価計画・品質ゲート'!$S$4:$S$103,MATCH(B15,'15_評価計画・品質ゲート'!$V$4:$V$103,0))="","",INDEX('15_評価計画・品質ゲート'!$S$4:$S$103,MATCH(B15,'15_評価計画・品質ゲート'!$V$4:$V$103,0))))) | S15: =IF(A15="","",IF(COUNTIF($A$4:$A$103,A15)<>1,"Run ID重複",IF(Y15<>"計画・構成一致",Y15,IF(X15<>"","無効化Run",IF(OR(OR(C15="",E15="",F15="",G15="",H15="",I15="",K15="",M15="",N15="",P15="",T15=""),LEN(L15&"")=0,COUNT(D15,R15)<2),"記録不足",IF(OR(AND(D15<>"",OR(NOT(ISNUMBER(D15)),IFERROR(D15<1,TRUE),IFERROR(INT(D15)>INT(AsOfDate),TRUE))),AND(R15<>"",OR(NOT(ISNUMBER(R15)),IFERROR(R15<1,TRUE),IFERROR(INT(R15)>INT(AsOfDate),TRUE)))),"実績日時不正",IF(R15<D15,"評価承認日時逆転",IF(OR(V15="",W15="",V15=W15),"独立確認Person不足",IF(AND(IF(COUNTIF('15_評価計画・品質ゲート'!$V$4:$V$103,B15)<>1,"参照ID不正",IF(INDEX('15_評価計画・品質ゲート'!$A$4:$A$103,MATCH(B15,'15_評価計画・品質ゲート'!$V$4:$V$103,0))="","",INDEX('15_評価計画・品質ゲート'!$A$4:$A$103,MATCH(B15,'15_評価計画・品質ゲート'!$V$4:$V$103,0))))="E05",U15=""),"Trial状態証拠不足",IF(OR(O15="",O15="未判定",O15="無効/再実行"),"評価判定未確定","記録あり・内容審査別")))))))))) | Y15: =IF(A15="","",IF(COUNTIF(EvalPlanKeys,B15)<>1,"PlanKey不正",IF(OR(T15="",T15<>IF(COUNTIF('15_評価計画・品質ゲート'!$V$4:$V$103,B15)<>1,"参照ID不正",IF(INDEX('15_評価計画・品質ゲート'!$U$4:$U$103,MATCH(B15,'15_評価計画・品質ゲート'!$V$4:$V$103,0))="","",INDEX('15_評価計画・品質ゲート'!$U$4:$U$103,MATCH(B15,'15_評価計画・品質ゲート'!$V$4:$V$103,0))))),"Manifest不一致",IF(IF(COUNTIF('15_評価計画・品質ゲート'!$V$4:$V$103,B15)<>1,"参照ID不正",IF(INDEX('15_評価計画・品質ゲート'!$W$4:$W$103,MATCH(B15,'15_評価計画・品質ゲート'!$V$4:$V$103,0))="","",INDEX('15_評価計画・品質ゲート'!$W$4:$W$103,MATCH(B15,'15_評価計画・品質ゲート'!$V$4:$V$103,0))))<>"計画記録あり","計画未承認・不足","計画・構成一致"))))
... J103: =IF(A103="","",IF(COUNTIF('15_評価計画・品質ゲート'!$V$4:$V$103,B103)<>1,"参照ID不正",IF(INDEX('15_評価計画・品質ゲート'!$S$4:$S$103,MATCH(B103,'15_評価計画・品質ゲート'!$V$4:$V$103,0))="","",INDEX('15_評価計画・品質ゲート'!$S$4:$S$103,MATCH(B103,'15_評価計画・品質ゲート'!$V$4:$V$103,0))))) | S103: =IF(A103="","",IF(COUNTIF($A$4:$A$103,A103)<>1,"Run ID重複",IF(Y103<>"計画・構成一致",Y103,IF(X103<>"","無効化Run",IF(OR(OR(C103="",E103="",F103="",G103="",H103="",I103="",K103="",M103="",N103="",P103="",T103=""),LEN(L103&"")=0,COUNT(D103,R103)<2),"記録不足",IF(OR(AND(D103<>"",OR(NOT(ISNUMBER(D103)),IFERROR(D103<1,TRUE),IFERROR(INT(D103)>INT(AsOfDate),TRUE))),AND(R103<>"",OR(NOT(ISNUMBER(R103)),IFERROR(R103<1,TRUE),IFERROR(INT(R103)>INT(AsOfDate),TRUE)))),"実績日時不正",IF(R103<D103,"評価承認日時逆転",IF(OR(V103="",W103="",V103=W103),"独立確認Person不足",IF(AND(IF(COUNTIF('15_評価計画・品質ゲート'!$V$4:$V$103,B103)<>1,"参照ID不正",IF(INDEX('15_評価計画・品質ゲート'!$A$4:$A$103,MATCH(B103,'15_評価計画・品質ゲート'!$V$4:$V$103,0))="","",INDEX('15_評価計画・品質ゲート'!$A$4:$A$103,MATCH(B103,'15_評価計画・品質ゲート'!$V$4:$V$103,0))))="E05",U103=""),"Trial状態証拠不足",IF(OR(O103="",O103="未判定",O103="無効/再実行"),"評価判定未確定","記録あり・内容審査別")))))))))) | Y103: =IF(A103="","",IF(COUNTIF(EvalPlanKeys,B103)<>1,"PlanKey不正",IF(OR(T103="",T103<>IF(COUNTIF('15_評価計画・品質ゲート'!$V$4:$V$103,B103)<>1,"参照ID不正",IF(INDEX('15_評価計画・品質ゲート'!$U$4:$U$103,MATCH(B103,'15_評価計画・品質ゲート'!$V$4:$V$103,0))="","",INDEX('15_評価計画・品質ゲート'!$U$4:$U$103,MATCH(B103,'15_評価計画・品質ゲート'!$V$4:$V$103,0))))),"Manifest不一致",IF(IF(COUNTIF('15_評価計画・品質ゲート'!$V$4:$V$103,B103)<>1,"参照ID不正",IF(INDEX('15_評価計画・品質ゲート'!$W$4:$W$103,MATCH(B103,'15_評価計画・品質ゲート'!$V$4:$V$103,0))="","",INDEX('15_評価計画・品質ゲート'!$W$4:$W$103,MATCH(B103,'15_評価計画・品質ゲート'!$V$4:$V$103,0))))<>"計画記録あり","計画未承認・不足","計画・構成一致"))))

Sheet 17_ロードマップ・案件実行管理
A1: ロードマップ・案件実行管理｜標準タスクを実行記録へ
A2: 初回標準132行。IDキー参照／実績日／依存記法を点検。反復は34。直接依存のみで、間接・循環は外部検査が必要。
A3: Task ID | B3: 工程 | C3: タスク名 | D3: Initiative/Epic/Issue | E3: 適用判定 | F3: 除外理由・代替証拠 | G3: 担当実名 | H3: 予定開始 | I3: 予定完了 | J3: 実開始 | K3: 実完了 | L3: 状態 | M3: 完了証拠URI | N3: 完了承認者 | O3: 完了承認日 | P3: 予定人時間 | Q3: 実績人時間 | R3: 阻害要因 | S3: 変更/リスクID | T3: 適用判定承認者 | U3: 適用判定日 | V3: 直接依存ID（8件まで） | W3: 完了記録点検 | X3: 前提記録点検 | Y3: 期限点検 | Z3: 総合記録点検 | AA3: 完了記録フラグ | AB3: 依存ID1 | AC3: 依存ID2 | AD3: 依存ID3 | AE3: 依存ID4 | AF3: 依存ID5 | AG3: 依存ID6 | AH3: 依存ID7 | AI3: 依存ID8 | AJ3: 依存点検1 | AK3: 依存点検2 | AL3: 依存点検3 | AM3: 依存点検4 | AN3: 依存点検5 | AO3: 依存点検6 | AP3: 依存点検7 | AQ3: 依存点検8 | AR3: 人時間差 | AS3: 承認Role（参照） | AT3: 初回TaskRun ID | AU3: 開始トリガー | AV3: 開始根拠Run／Incident | AW3: 対象ManifestHash | AX3: 次回確認日 | AY3: 依存変更理由 | AZ3: 依存変更承認者 | BA3: 依存変更承認日 | BB3: 標準依存（参照） | BC3: 依存記法点検 | BD3: 開始根拠点検 | BE3: 担当PersonID | BF3: 承認PersonID
A4: B0-01 | B4: =IF(COUNTIF('02_工程タスク'!$A$4:$A$135,A4)<>1,"参照ID不正",IF(INDEX('02_工程タスク'!$B$4:$B$135,MATCH(A4,'02_工程タスク'!$A$4:$A$135,0))="","",INDEX('02_工程タスク'!$B$4:$B$135,MATCH(A4,'02_工程タスク'!$A$4:$A$135,0)))) -> 企画 | C4: =IF(COUNTIF('02_工程タスク'!$A$4:$A$135,A4)<>1,"参照ID不正",IF(INDEX('02_工程タスク'!$D$4:$D$135,MATCH(A4,'02_工程タスク'!$A$4:$A$135,0))="","",INDEX('02_工程タスク'!$D$4:$D$135,MATCH(A4,'02_工程タスク'!$A$4:$A$135,0)))) -> 探索責任者・初期枠の設定 | E4: 未判定 | L4: 未着手 | W4: =IF(OR(COUNTIF(TaskIDs,A4)<>1,COUNTIF($A$4:$A$135,A4)<>1),"Task ID不正・重複",IF(OR(AND(P4<>"",OR(NOT(ISNUMBER(P4)),IFERROR(P4<0,TRUE))),AND(Q4<>"",OR(NOT(ISNUMBER(Q4)),IFERROR(Q4<0,TRUE)))),"人時間不正",IF(OR(AND(J4<>"",OR(NOT(ISNUMBER(J4)),IFERROR(J4<1,TRUE),IFERROR(INT(J4)>INT(AsOfDate),TRUE))),AND(K4<>"",OR(NOT(ISNUMBER(K4)),IFERROR(K4<1,TRUE),IFERROR(INT(K4)>INT(AsOfDate),TRUE))),AND(O4<>"",OR(NOT(ISNUMBER(O4)),IFERROR(O4<1,TRUE),IFERROR(INT(O4)>INT(AsOfDate),TRUE))),AND(U4<>"",OR(NOT(ISNUMBER(U4)),IFERROR(U4<1,TRUE),IFERROR(INT(U4)>INT(AsOfDate),TRUE))),AND(BA4<>"",OR(NOT(ISNUMBER(BA4)),IFERROR(BA4<1,TRUE),IFERROR(INT(BA4)>INT(AsOfDate),TRUE)))),"実績・承認日不正",IF(AND(COUNT(H4:I4)=2,H4>I4),"予定日不正",IF(E4="未判定","適用未判定",IF(E4="対象外",IF(OR(F4="",T4="",NOT(ISNUMBER(U4))),"除外承認不足","除外記録済"),IF(E4<>"適用","適用判定不正",IF(OR(T4="",NOT(ISNUMBER(U4))),"適用承認不足",IF(AND(V4<>BB4,OR(AY4="",AZ4="",NOT(ISNUMBER(BA4)))),"依存変更承認不足",IF(L4<>"完了","未完了",IF(OR(OR(G4="",M4="",N4="",BE4="",BF4=""),COUNT(J4:K4)<2,NOT(ISNUMBER(O4))),"完了証拠不足",IF(OR(J4>K4,O4<K4,U4>J4),"完了・適用日逆転",IF(BD4<>"開始根拠あり",BD4,IF(AND(AS4="R19",OR(G4=N4,BE4=BF4)),"独立承認不足","完了記録済")))))))))))))) -> 適用未判定 | X4: =IF(E4<>"適用","",IF(AND(V4<>BB4,OR(AY4="",AZ4="",NOT(ISNUMBER(BA4)))),"依存変更承認不足",IF(BC4="依存なし","なし",IF(BC4<>"記法OK",BC4,IF(COUNTIF(AJ4:AQ4,"ID不正")>0,"依存ID不正",IF(COUNTIF(AJ4:AQ4,"未充足")>0,"前提未充足","記録上充足")))))) | Y4: =IF(OR(E4<>"適用",L4="完了",I4=""),"",IF(NOT(ISNUMBER(I4)),"予定日不正",IF(I4<AsOfDate,"期限超過","期限内"))) | Z4: =IF(W4="完了記録済",IF(OR(X4="なし",X4="記録上充足"),"完了記録・前提充足",X4),W4) -> 適用未判定 | AA4: =IF(AND(E4="適用",L4="完了",W4="完了記録済",OR(X4="なし",X4="記録上充足")),1,0) -> 0 | AB4: =TRIM(MID(SUBSTITUTE($V4,",",REPT(" ",64)),1,64)) | AC4: =TRIM(MID(SUBSTITUTE($V4,",",REPT(" ",64)),65,64)) | AD4: =TRIM(MID(SUBSTITUTE($V4,",",REPT(" ",64)),129,64)) | AE4: =TRIM(MID(SUBSTITUTE($V4,",",REPT(" ",64)),193,64)) | AF4: =TRIM(MID(SUBSTITUTE($V4,",",REPT(" ",64)),257,64)) | AG4: =TRIM(MID(SUBSTITUTE($V4,",",REPT(" ",64)),321,64)) | AH4: =TRIM(MID(SUBSTITUTE($V4,",",REPT(" ",64)),385,64)) | AI4: =TRIM(MID(SUBSTITUTE($V4,",",REPT(" ",64)),449,64)) | AJ4: =IF(AB4="","",IF(OR(AB4=$A4,COUNTIF($A$4:$A$135,AB4)<>1,COUNTIF($AB4:$AI4,AB4)>1),"ID不正",IFERROR(IF(OR(INDEX($W$4:$W$135,MATCH(AB4,$A$4:$A$135,0))="完了記録済",INDEX($W$4:$W$135,MATCH(AB4,$A$4:$A$135,0))="除外記録済"),"記録充足","未充足"),"ID不正"))) | AK4: =IF(AC4="","",IF(OR(AC4=$A4,COUNTIF($A$4:$A$135,AC4)<>1,COUNTIF($AB4:$AI4,AC4)>1),"ID不正",IFERROR(IF(OR(INDEX($W$4:$W$135,MATCH(AC4,$A$4:$A$135,0))="完了記録済",INDEX($W$4:$W$135,MATCH(AC4,$A$4:$A$135,0))="除外記録済"),"記録充足","未充足"),"ID不正"))) | AL4: =IF(AD4="","",IF(OR(AD4=$A4,COUNTIF($A$4:$A$135,AD4)<>1,COUNTIF($AB4:$AI4,AD4)>1),"ID不正",IFERROR(IF(OR(INDEX($W$4:$W$135,MATCH(AD4,$A$4:$A$135,0))="完了記録済",INDEX($W$4:$W$135,MATCH(AD4,$A$4:$A$135,0))="除外記録済"),"記録充足","未充足"),"ID不正"))) | AM4: =IF(AE4="","",IF(OR(AE4=$A4,COUNTIF($A$4:$A$135,AE4)<>1,COUNTIF($AB4:$AI4,AE4)>1),"ID不正",IFERROR(IF(OR(INDEX($W$4:$W$135,MATCH(AE4,$A$4:$A$135,0))="完了記録済",INDEX($W$4:$W$135,MATCH(AE4,$A$4:$A$135,0))="除外記録済"),"記録充足","未充足"),"ID不正"))) | AN4: =IF(AF4="","",IF(OR(AF4=$A4,COUNTIF($A$4:$A$135,AF4)<>1,COUNTIF($AB4:$AI4,AF4)>1),"ID不正",IFERROR(IF(OR(INDEX($W$4:$W$135,MATCH(AF4,$A$4:$A$135,0))="完了記録済",INDEX($W$4:$W$135,MATCH(AF4,$A$4:$A$135,0))="除外記録済"),"記録充足","未充足"),"ID不正"))) | AO4: =IF(AG4="","",IF(OR(AG4=$A4,COUNTIF($A$4:$A$135,AG4)<>1,COUNTIF($AB4:$AI4,AG4)>1),"ID不正",IFERROR(IF(OR(INDEX($W$4:$W$135,MATCH(AG4,$A$4:$A$135,0))="完了記録済",INDEX($W$4:$W$135,MATCH(AG4,$A$4:$A$135,0))="除外記録済"),"記録充足","未充足"),"ID不正"))) | AP4: =IF(AH4="","",IF(OR(AH4=$A4,COUNTIF($A$4:$A$135,AH4)<>1,COUNTIF($AB4:$AI4,AH4)>1),"ID不正",IFERROR(IF(OR(INDEX($W$4:$W$135,MATCH(AH4,$A$4:$A$135,0))="完了記録済",INDEX($W$4:$W$135,MATCH(AH4,$A$4:$A$135,0))="除外記録済"),"記録充足","未充足"),"ID不正"))) | AQ4: =IF(AI4="","",IF(OR(AI4=$A4,COUNTIF($A$4:$A$135,AI4)<>1,COUNTIF($AB4:$AI4,AI4)>1),"ID不正",IFERROR(IF(OR(INDEX($W$4:$W$135,MATCH(AI4,$A$4:$A$135,0))="完了記録済",INDEX($W$4:$W$135,MATCH(AI4,$A$4:$A$135,0))="除外記録済"),"記録充足","未充足"),"ID不正"))) | AR4: =IF(COUNT(P4:Q4)<2,"",Q4-P4) | AS4: =IF(COUNTIF('02_工程タスク'!$A$4:$A$135,A4)<>1,"参照ID不正",IF(INDEX('02_工程タスク'!$H$4:$H$135,MATCH(A4,'02_工程タスク'!$A$4:$A$135,0))="","",INDEX('02_工程タスク'!$H$4:$H$135,MATCH(A4,'02_工程タスク'!$A$4:$A$135,0)))) -> R01 | AT4: =IF(A4="","","INIT-"&A4) -> INIT-B0-01 | AU4: 初回 | BB4: =IF(COUNTIF('02_工程タスク'!$A$4:$A$135,A4)<>1,"参照ID不正",IF(INDEX('02_工程タスク'!$O$4:$O$135,MATCH(A4,'02_工程タスク'!$A$4:$A$135,0))="","",INDEX('02_工程タスク'!$O$4:$O$135,MATCH(A4,'02_工程タスク'!$A$4:$A$135,0)))) | BC4: =IF(V4="","依存なし",IF(OR(LEFT(V4,1)=",",RIGHT(V4,1)=",",ISNUMBER(SEARCH(",,",SUBSTITUTE(V4," ",""))),LEN(V4)<>LEN(SUBSTITUTE(V4," ","")),ISNUMBER(SEARCH("，",V4))),"依存記法不正",IF(LEN(V4)-LEN(SUBSTITUTE(V4,",",""))>7,"依存8件超過","記法OK"))) -> 依存なし | BD4: =IF(A4="B6-01",IF(OR(AV4="",COUNTIF('29_ゲート承認記録'!$F$4:$F$83,AV4)<>1),"終了開始根拠不足",IF(IF(COUNTIF('29_ゲート承認記録'!$F$4:$F$83,AV4)<>1,"参照ID不正",IF(INDEX('29_ゲート承認記録'!$L$4:$L$83,MATCH(AV4,'29_ゲート承認記録'!$F$4:$F$83,0))="","",INDEX('29_ゲート承認記録'!$L$4:$L$83,MATCH(AV4,'29_ゲート承認記録'!$F$4:$F$83,0))))<>"Stop","Stop判断要確認","開始根拠あり")),IF(AND(A4="B5-18",AU4="事故"),IF(AV4="","事故レビュー参照不足","開始根拠あり"),"開始根拠あり")) -> 開始根拠あり
A5: B0-02 | B5: =IF(COUNTIF('02_工程タスク'!$A$4:$A$135,A5)<>1,"参照ID不正",IF(INDEX('02_工程タスク'!$B$4:$B$135,MATCH(A5,'02_工程タスク'!$A$4:$A$135,0))="","",INDEX('02_工程タスク'!$B$4:$B$135,MATCH(A5,'02_工程タスク'!$A$4:$A$135,0)))) -> 企画 | C5: =IF(COUNTIF('02_工程タスク'!$A$4:$A$135,A5)<>1,"参照ID不正",IF(INDEX('02_工程タスク'!$D$4:$D$135,MATCH(A5,'02_工程タスク'!$A$4:$A$135,0))="","",INDEX('02_工程タスク'!$D$4:$D$135,MATCH(A5,'02_工程タスク'!$A$4:$A$135,0)))) -> 市場・競合・規制候補の調査 | E5: 未判定 | L5: 未着手 | V5: B0-01 | W5: =IF(OR(COUNTIF(TaskIDs,A5)<>1,COUNTIF($A$4:$A$135,A5)<>1),"Task ID不正・重複",IF(OR(AND(P5<>"",OR(NOT(ISNUMBER(P5)),IFERROR(P5<0,TRUE))),AND(Q5<>"",OR(NOT(ISNUMBER(Q5)),IFERROR(Q5<0,TRUE)))),"人時間不正",IF(OR(AND(J5<>"",OR(NOT(ISNUMBER(J5)),IFERROR(J5<1,TRUE),IFERROR(INT(J5)>INT(AsOfDate),TRUE))),AND(K5<>"",OR(NOT(ISNUMBER(K5)),IFERROR(K5<1,TRUE),IFERROR(INT(K5)>INT(AsOfDate),TRUE))),AND(O5<>"",OR(NOT(ISNUMBER(O5)),IFERROR(O5<1,TRUE),IFERROR(INT(O5)>INT(AsOfDate),TRUE))),AND(U5<>"",OR(NOT(ISNUMBER(U5)),IFERROR(U5<1,TRUE),IFERROR(INT(U5)>INT(AsOfDate),TRUE))),AND(BA5<>"",OR(NOT(ISNUMBER(BA5)),IFERROR(BA5<1,TRUE),IFERROR(INT(BA5)>INT(AsOfDate),TRUE)))),"実績・承認日不正",IF(AND(COUNT(H5:I5)=2,H5>I5),"予定日不正",IF(E5="未判定","適用未判定",IF(E5="対象外",IF(OR(F5="",T5="",NOT(ISNUMBER(U5))),"除外承認不足","除外記録済"),IF(E5<>"適用","適用判定不正",IF(OR(T5="",NOT(ISNUMBER(U5))),"適用承認不足",IF(AND(V5<>BB5,OR(AY5="",AZ5="",NOT(ISNUMBER(BA5)))),"依存変更承認不足",IF(L5<>"完了","未完了",IF(OR(OR(G5="",M5="",N5="",BE5="",BF5=""),COUNT(J5:K5)<2,NOT(ISNUMBER(O5))),"完了証拠不足",IF(OR(J5>K5,O5<K5,U5>J5),"完了・適用日逆転",IF(BD5<>"開始根拠あり",BD5,IF(AND(AS5="R19",OR(G5=N5,BE5=BF5)),"独立承認不足","完了記録済")))))))))))))) -> 適用未判定 | X5: =IF(E5<>"適用","",IF(AND(V5<>BB5,OR(AY5="",AZ5="",NOT(ISNUMBER(BA5)))),"依存変更承認不足",IF(BC5="依存なし","なし",IF(BC5<>"記法OK",BC5,IF(COUNTIF(AJ5:AQ5,"ID不正")>0,"依存ID不正",IF(COUNTIF(AJ5:AQ5,"未充足")>0,"前提未充足","記録上充足")))))) | Y5: =IF(OR(E5<>"適用",L5="完了",I5=""),"",IF(NOT(ISNUMBER(I5)),"予定日不正",IF(I5<AsOfDate,"期限超過","期限内"))) | Z5: =IF(W5="完了記録済",IF(OR(X5="なし",X5="記録上充足"),"完了記録・前提充足",X5),W5) -> 適用未判定 | AA5: =IF(AND(E5="適用",L5="完了",W5="完了記録済",OR(X5="なし",X5="記録上充足")),1,0) -> 0 | AB5: =TRIM(MID(SUBSTITUTE($V5,",",REPT(" ",64)),1,64)) -> B0-01 | AC5: =TRIM(MID(SUBSTITUTE($V5,",",REPT(" ",64)),65,64)) | AD5: =TRIM(MID(SUBSTITUTE($V5,",",REPT(" ",64)),129,64)) | AE5: =TRIM(MID(SUBSTITUTE($V5,",",REPT(" ",64)),193,64)) | AF5: =TRIM(MID(SUBSTITUTE($V5,",",REPT(" ",64)),257,64)) | AG5: =TRIM(MID(SUBSTITUTE($V5,",",REPT(" ",64)),321,64)) | AH5: =TRIM(MID(SUBSTITUTE($V5,",",REPT(" ",64)),385,64)) | AI5: =TRIM(MID(SUBSTITUTE($V5,",",REPT(" ",64)),449,64)) | AJ5: =IF(AB5="","",IF(OR(AB5=$A5,COUNTIF($A$4:$A$135,AB5)<>1,COUNTIF($AB5:$AI5,AB5)>1),"ID不正",IFERROR(IF(OR(INDEX($W$4:$W$135,MATCH(AB5,$A$4:$A$135,0))="完了記録済",INDEX($W$4:$W$135,MATCH(AB5,$A$4:$A$135,0))="除外記録済"),"記録充足","未充足"),"ID不正"))) -> 未充足 | AK5: =IF(AC5="","",IF(OR(AC5=$A5,COUNTIF($A$4:$A$135,AC5)<>1,COUNTIF($AB5:$AI5,AC5)>1),"ID不正",IFERROR(IF(OR(INDEX($W$4:$W$135,MATCH(AC5,$A$4:$A$135,0))="完了記録済",INDEX($W$4:$W$135,MATCH(AC5,$A$4:$A$135,0))="除外記録済"),"記録充足","未充足"),"ID不正"))) | AL5: =IF(AD5="","",IF(OR(AD5=$A5,COUNTIF($A$4:$A$135,AD5)<>1,COUNTIF($AB5:$AI5,AD5)>1),"ID不正",IFERROR(IF(OR(INDEX($W$4:$W$135,MATCH(AD5,$A$4:$A$135,0))="完了記録済",INDEX($W$4:$W$135,MATCH(AD5,$A$4:$A$135,0))="除外記録済"),"記録充足","未充足"),"ID不正"))) | AM5: =IF(AE5="","",IF(OR(AE5=$A5,COUNTIF($A$4:$A$135,AE5)<>1,COUNTIF($AB5:$AI5,AE5)>1),"ID不正",IFERROR(IF(OR(INDEX($W$4:$W$135,MATCH(AE5,$A$4:$A$135,0))="完了記録済",INDEX($W$4:$W$135,MATCH(AE5,$A$4:$A$135,0))="除外記録済"),"記録充足","未充足"),"ID不正"))) | AN5: =IF(AF5="","",IF(OR(AF5=$A5,COUNTIF($A$4:$A$135,AF5)<>1,COUNTIF($AB5:$AI5,AF5)>1),"ID不正",IFERROR(IF(OR(INDEX($W$4:$W$135,MATCH(AF5,$A$4:$A$135,0))="完了記録済",INDEX($W$4:$W$135,MATCH(AF5,$A$4:$A$135,0))="除外記録済"),"記録充足","未充足"),"ID不正"))) | AO5: =IF(AG5="","",IF(OR(AG5=$A5,COUNTIF($A$4:$A$135,AG5)<>1,COUNTIF($AB5:$AI5,AG5)>1),"ID不正",IFERROR(IF(OR(INDEX($W$4:$W$135,MATCH(AG5,$A$4:$A$135,0))="完了記録済",INDEX($W$4:$W$135,MATCH(AG5,$A$4:$A$135,0))="除外記録済"),"記録充足","未充足"),"ID不正"))) | AP5: =IF(AH5="","",IF(OR(AH5=$A5,COUNTIF($A$4:$A$135,AH5)<>1,COUNTIF($AB5:$AI5,AH5)>1),"ID不正",IFERROR(IF(OR(INDEX($W$4:$W$135,MATCH(AH5,$A$4:$A$135,0))="完了記録済",INDEX($W$4:$W$135,MATCH(AH5,$A$4:$A$135,0))="除外記録済"),"記録充足","未充足"),"ID不正"))) | AQ5: =IF(AI5="","",IF(OR(AI5=$A5,COUNTIF($A$4:$A$135,AI5)<>1,COUNTIF($AB5:$AI5,AI5)>1),"ID不正",IFERROR(IF(OR(INDEX($W$4:$W$135,MATCH(AI5,$A$4:$A$135,0))="完了記録済",INDEX($W$4:$W$135,MATCH(AI5,$A$4:$A$135,0))="除外記録済"),"記録充足","未充足"),"ID不正"))) | AR5: =IF(COUNT(P5:Q5)<2,"",Q5-P5) | AS5: =IF(COUNTIF('02_工程タスク'!$A$4:$A$135,A5)<>1,"参照ID不正",IF(INDEX('02_工程タスク'!$H$4:$H$135,MATCH(A5,'02_工程タスク'!$A$4:$A$135,0))="","",INDEX('02_工程タスク'!$H$4:$H$135,MATCH(A5,'02_工程タスク'!$A$4:$A$135,0)))) -> R02 | AT5: =IF(A5="","","INIT-"&A5) -> INIT-B0-02 | AU5: 初回 | BB5: =IF(COUNTIF('02_工程タスク'!$A$4:$A$135,A5)<>1,"参照ID不正",IF(INDEX('02_工程タスク'!$O$4:$O$135,MATCH(A5,'02_工程タスク'!$A$4:$A$135,0))="","",INDEX('02_工程タスク'!$O$4:$O$135,MATCH(A5,'02_工程タスク'!$A$4:$A$135,0)))) -> B0-01 | BC5: =IF(V5="","依存なし",IF(OR(LEFT(V5,1)=",",RIGHT(V5,1)=",",ISNUMBER(SEARCH(",,",SUBSTITUTE(V5," ",""))),LEN(V5)<>LEN(SUBSTITUTE(V5," ","")),ISNUMBER(SEARCH("，",V5))),"依存記法不正",IF(LEN(V5)-LEN(SUBSTITUTE(V5,",",""))>7,"依存8件超過","記法OK"))) -> 記法OK | BD5: =IF(A5="B6-01",IF(OR(AV5="",COUNTIF('29_ゲート承認記録'!$F$4:$F$83,AV5)<>1),"終了開始根拠不足",IF(IF(COUNTIF('29_ゲート承認記録'!$F$4:$F$83,AV5)<>1,"参照ID不正",IF(INDEX('29_ゲート承認記録'!$L$4:$L$83,MATCH(AV5,'29_ゲート承認記録'!$F$4:$F$83,0))="","",INDEX('29_ゲート承認記録'!$L$4:$L$83,MATCH(AV5,'29_ゲート承認記録'!$F$4:$F$83,0))))<>"Stop","Stop判断要確認","開始根拠あり")),IF(AND(A5="B5-18",AU5="事故"),IF(AV5="","事故レビュー参照不足","開始根拠あり"),"開始根拠あり")) -> 開始根拠あり
A6: B0-03 | B6: =IF(COUNTIF('02_工程タスク'!$A$4:$A$135,A6)<>1,"参照ID不正",IF(INDEX('02_工程タスク'!$B$4:$B$135,MATCH(A6,'02_工程タスク'!$A$4:$A$135,0))="","",INDEX('02_工程タスク'!$B$4:$B$135,MATCH(A6,'02_工程タスク'!$A$4:$A$135,0)))) -> 企画 | C6: =IF(COUNTIF('02_工程タスク'!$A$4:$A$135,A6)<>1,"参照ID不正",IF(INDEX('02_工程タスク'!$D$4:$D$135,MATCH(A6,'02_工程タスク'!$A$4:$A$135,0))="","",INDEX('02_工程タスク'!$D$4:$D$135,MATCH(A6,'02_工程タスク'!$A$4:$A$135,0)))) -> 利用者・購買者の仮説分解 | E6: 未判定 | L6: 未着手 | V6: B0-02 | W6: =IF(OR(COUNTIF(TaskIDs,A6)<>1,COUNTIF($A$4:$A$135,A6)<>1),"Task ID不正・重複",IF(OR(AND(P6<>"",OR(NOT(ISNUMBER(P6)),IFERROR(P6<0,TRUE))),AND(Q6<>"",OR(NOT(ISNUMBER(Q6)),IFERROR(Q6<0,TRUE)))),"人時間不正",IF(OR(AND(J6<>"",OR(NOT(ISNUMBER(J6)),IFERROR(J6<1,TRUE),IFERROR(INT(J6)>INT(AsOfDate),TRUE))),AND(K6<>"",OR(NOT(ISNUMBER(K6)),IFERROR(K6<1,TRUE),IFERROR(INT(K6)>INT(AsOfDate),TRUE))),AND(O6<>"",OR(NOT(ISNUMBER(O6)),IFERROR(O6<1,TRUE),IFERROR(INT(O6)>INT(AsOfDate),TRUE))),AND(U6<>"",OR(NOT(ISNUMBER(U6)),IFERROR(U6<1,TRUE),IFERROR(INT(U6)>INT(AsOfDate),TRUE))),AND(BA6<>"",OR(NOT(ISNUMBER(BA6)),IFERROR(BA6<1,TRUE),IFERROR(INT(BA6)>INT(AsOfDate),TRUE)))),"実績・承認日不正",IF(AND(COUNT(H6:I6)=2,H6>I6),"予定日不正",IF(E6="未判定","適用未判定",IF(E6="対象外",IF(OR(F6="",T6="",NOT(ISNUMBER(U6))),"除外承認不足","除外記録済"),IF(E6<>"適用","適用判定不正",IF(OR(T6="",NOT(ISNUMBER(U6))),"適用承認不足",IF(AND(V6<>BB6,OR(AY6="",AZ6="",NOT(ISNUMBER(BA6)))),"依存変更承認不足",IF(L6<>"完了","未完了",IF(OR(OR(G6="",M6="",N6="",BE6="",BF6=""),COUNT(J6:K6)<2,NOT(ISNUMBER(O6))),"完了証拠不足",IF(OR(J6>K6,O6<K6,U6>J6),"完了・適用日逆転",IF(BD6<>"開始根拠あり",BD6,IF(AND(AS6="R19",OR(G6=N6,BE6=BF6)),"独立承認不足","完了記録済")))))))))))))) -> 適用未判定 | X6: =IF(E6<>"適用","",IF(AND(V6<>BB6,OR(AY6="",AZ6="",NOT(ISNUMBER(BA6)))),"依存変更承認不足",IF(BC6="依存なし","なし",IF(BC6<>"記法OK",BC6,IF(COUNTIF(AJ6:AQ6,"ID不正")>0,"依存ID不正",IF(COUNTIF(AJ6:AQ6,"未充足")>0,"前提未充足","記録上充足")))))) | Y6: =IF(OR(E6<>"適用",L6="完了",I6=""),"",IF(NOT(ISNUMBER(I6)),"予定日不正",IF(I6<AsOfDate,"期限超過","期限内"))) | Z6: =IF(W6="完了記録済",IF(OR(X6="なし",X6="記録上充足"),"完了記録・前提充足",X6),W6) -> 適用未判定 | AA6: =IF(AND(E6="適用",L6="完了",W6="完了記録済",OR(X6="なし",X6="記録上充足")),1,0) -> 0 | AB6: =TRIM(MID(SUBSTITUTE($V6,",",REPT(" ",64)),1,64)) -> B0-02 | AC6: =TRIM(MID(SUBSTITUTE($V6,",",REPT(" ",64)),65,64)) | AD6: =TRIM(MID(SUBSTITUTE($V6,",",REPT(" ",64)),129,64)) | AE6: =TRIM(MID(SUBSTITUTE($V6,",",REPT(" ",64)),193,64)) | AF6: =TRIM(MID(SUBSTITUTE($V6,",",REPT(" ",64)),257,64)) | AG6: =TRIM(MID(SUBSTITUTE($V6,",",REPT(" ",64)),321,64)) | AH6: =TRIM(MID(SUBSTITUTE($V6,",",REPT(" ",64)),385,64)) | AI6: =TRIM(MID(SUBSTITUTE($V6,",",REPT(" ",64)),449,64)) | AJ6: =IF(AB6="","",IF(OR(AB6=$A6,COUNTIF($A$4:$A$135,AB6)<>1,COUNTIF($AB6:$AI6,AB6)>1),"ID不正",IFERROR(IF(OR(INDEX($W$4:$W$135,MATCH(AB6,$A$4:$A$135,0))="完了記録済",INDEX($W$4:$W$135,MATCH(AB6,$A$4:$A$135,0))="除外記録済"),"記録充足","未充足"),"ID不正"))) -> 未充足 | AK6: =IF(AC6="","",IF(OR(AC6=$A6,COUNTIF($A$4:$A$135,AC6)<>1,COUNTIF($AB6:$AI6,AC6)>1),"ID不正",IFERROR(IF(OR(INDEX($W$4:$W$135,MATCH(AC6,$A$4:$A$135,0))="完了記録済",INDEX($W$4:$W$135,MATCH(AC6,$A$4:$A$135,0))="除外記録済"),"記録充足","未充足"),"ID不正"))) | AL6: =IF(AD6="","",IF(OR(AD6=$A6,COUNTIF($A$4:$A$135,AD6)<>1,COUNTIF($AB6:$AI6,AD6)>1),"ID不正",IFERROR(IF(OR(INDEX($W$4:$W$135,MATCH(AD6,$A$4:$A$135,0))="完了記録済",INDEX($W$4:$W$135,MATCH(AD6,$A$4:$A$135,0))="除外記録済"),"記録充足","未充足"),"ID不正"))) | AM6: =IF(AE6="","",IF(OR(AE6=$A6,COUNTIF($A$4:$A$135,AE6)<>1,COUNTIF($AB6:$AI6,AE6)>1),"ID不正",IFERROR(IF(OR(INDEX($W$4:$W$135,MATCH(AE6,$A$4:$A$135,0))="完了記録済",INDEX($W$4:$W$135,MATCH(AE6,$A$4:$A$135,0))="除外記録済"),"記録充足","未充足"),"ID不正"))) | AN6: =IF(AF6="","",IF(OR(AF6=$A6,COUNTIF($A$4:$A$135,AF6)<>1,COUNTIF($AB6:$AI6,AF6)>1),"ID不正",IFERROR(IF(OR(INDEX($W$4:$W$135,MATCH(AF6,$A$4:$A$135,0))="完了記録済",INDEX($W$4:$W$135,MATCH(AF6,$A$4:$A$135,0))="除外記録済"),"記録充足","未充足"),"ID不正"))) | AO6: =IF(AG6="","",IF(OR(AG6=$A6,COUNTIF($A$4:$A$135,AG6)<>1,COUNTIF($AB6:$AI6,AG6)>1),"ID不正",IFERROR(IF(OR(INDEX($W$4:$W$135,MATCH(AG6,$A$4:$A$135,0))="完了記録済",INDEX($W$4:$W$135,MATCH(AG6,$A$4:$A$135,0))="除外記録済"),"記録充足","未充足"),"ID不正"))) | AP6: =IF(AH6="","",IF(OR(AH6=$A6,COUNTIF($A$4:$A$135,AH6)<>1,COUNTIF($AB6:$AI6,AH6)>1),"ID不正",IFERROR(IF(OR(INDEX($W$4:$W$135,MATCH(AH6,$A$4:$A$135,0))="完了記録済",INDEX($W$4:$W$135,MATCH(AH6,$A$4:$A$135,0))="除外記録済"),"記録充足","未充足"),"ID不正"))) | AQ6: =IF(AI6="","",IF(OR(AI6=$A6,COUNTIF($A$4:$A$135,AI6)<>1,COUNTIF($AB6:$AI6,AI6)>1),"ID不正",IFERROR(IF(OR(INDEX($W$4:$W$135,MATCH(AI6,$A$4:$A$135,0))="完了記録済",INDEX($W$4:$W$135,MATCH(AI6,$A$4:$A$135,0))="除外記録済"),"記録充足","未充足"),"ID不正"))) | AR6: =IF(COUNT(P6:Q6)<2,"",Q6-P6) | AS6: =IF(COUNTIF('02_工程タスク'!$A$4:$A$135,A6)<>1,"参照ID不正",IF(INDEX('02_工程タスク'!$H$4:$H$135,MATCH(A6,'02_工程タスク'!$A$4:$A$135,0))="","",INDEX('02_工程タスク'!$H$4:$H$135,MATCH(A6,'02_工程タスク'!$A$4:$A$135,0)))) -> R02 | AT6: =IF(A6="","","INIT-"&A6) -> INIT-B0-03 | AU6: 初回 | BB6: =IF(COUNTIF('02_工程タスク'!$A$4:$A$135,A6)<>1,"参照ID不正",IF(INDEX('02_工程タスク'!$O$4:$O$135,MATCH(A6,'02_工程タスク'!$A$4:$A$135,0))="","",INDEX('02_工程タスク'!$O$4:$O$135,MATCH(A6,'02_工程タスク'!$A$4:$A$135,0)))) -> B0-02 | BC6: =IF(V6="","依存なし",IF(OR(LEFT(V6,1)=",",RIGHT(V6,1)=",",ISNUMBER(SEARCH(",,",SUBSTITUTE(V6," ",""))),LEN(V6)<>LEN(SUBSTITUTE(V6," ","")),ISNUMBER(SEARCH("，",V6))),"依存記法不正",IF(LEN(V6)-LEN(SUBSTITUTE(V6,",",""))>7,"依存8件超過","記法OK"))) -> 記法OK | BD6: =IF(A6="B6-01",IF(OR(AV6="",COUNTIF('29_ゲート承認記録'!$F$4:$F$83,AV6)<>1),"終了開始根拠不足",IF(IF(COUNTIF('29_ゲート承認記録'!$F$4:$F$83,AV6)<>1,"参照ID不正",IF(INDEX('29_ゲート承認記録'!$L$4:$L$83,MATCH(AV6,'29_ゲート承認記録'!$F$4:$F$83,0))="","",INDEX('29_ゲート承認記録'!$L$4:$L$83,MATCH(AV6,'29_ゲート承認記録'!$F$4:$F$83,0))))<>"Stop","Stop判断要確認","開始根拠あり")),IF(AND(A6="B5-18",AU6="事故"),IF(AV6="","事故レビュー参照不足","開始根拠あり"),"開始根拠あり")) -> 開始根拠あり
A7: B0-04 | B7: =IF(COUNTIF('02_工程タスク'!$A$4:$A$135,A7)<>1,"参照ID不正",IF(INDEX('02_工程タスク'!$B$4:$B$135,MATCH(A7,'02_工程タスク'!$A$4:$A$135,0))="","",INDEX('02_工程タスク'!$B$4:$B$135,MATCH(A7,'02_工程タスク'!$A$4:$A$135,0)))) -> 企画 | C7: =IF(COUNTIF('02_工程タスク'!$A$4:$A$135,A7)<>1,"参照ID不正",IF(INDEX('02_工程タスク'!$D$4:$D$135,MATCH(A7,'02_工程タスク'!$A$4:$A$135,0))="","",INDEX('02_工程タスク'!$D$4:$D$135,MATCH(A7,'02_工程タスク'!$A$4:$A$135,0)))) -> インタビュー・現場観察 | E7: 未判定 | L7: 未着手 | V7: B0-03 | W7: =IF(OR(COUNTIF(TaskIDs,A7)<>1,COUNTIF($A$4:$A$135,A7)<>1),"Task ID不正・重複",IF(OR(AND(P7<>"",OR(NOT(ISNUMBER(P7)),IFERROR(P7<0,TRUE))),AND(Q7<>"",OR(NOT(ISNUMBER(Q7)),IFERROR(Q7<0,TRUE)))),"人時間不正",IF(OR(AND(J7<>"",OR(NOT(ISNUMBER(J7)),IFERROR(J7<1,TRUE),IFERROR(INT(J7)>INT(AsOfDate),TRUE))),AND(K7<>"",OR(NOT(ISNUMBER(K7)),IFERROR(K7<1,TRUE),IFERROR(INT(K7)>INT(AsOfDate),TRUE))),AND(O7<>"",OR(NOT(ISNUMBER(O7)),IFERROR(O7<1,TRUE),IFERROR(INT(O7)>INT(AsOfDate),TRUE))),AND(U7<>"",OR(NOT(ISNUMBER(U7)),IFERROR(U7<1,TRUE),IFERROR(INT(U7)>INT(AsOfDate),TRUE))),AND(BA7<>"",OR(NOT(ISNUMBER(BA7)),IFERROR(BA7<1,TRUE),IFERROR(INT(BA7)>INT(AsOfDate),TRUE)))),"実績・承認日不正",IF(AND(COUNT(H7:I7)=2,H7>I7),"予定日不正",IF(E7="未判定","適用未判定",IF(E7="対象外",IF(OR(F7="",T7="",NOT(ISNUMBER(U7))),"除外承認不足","除外記録済"),IF(E7<>"適用","適用判定不正",IF(OR(T7="",NOT(ISNUMBER(U7))),"適用承認不足",IF(AND(V7<>BB7,OR(AY7="",AZ7="",NOT(ISNUMBER(BA7)))),"依存変更承認不足",IF(L7<>"完了","未完了",IF(OR(OR(G7="",M7="",N7="",BE7="",BF7=""),COUNT(J7:K7)<2,NOT(ISNUMBER(O7))),"完了証拠不足",IF(OR(J7>K7,O7<K7,U7>J7),"完了・適用日逆転",IF(BD7<>"開始根拠あり",BD7,IF(AND(AS7="R19",OR(G7=N7,BE7=BF7)),"独立承認不足","完了記録済")))))))))))))) -> 適用未判定 | X7: =IF(E7<>"適用","",IF(AND(V7<>BB7,OR(AY7="",AZ7="",NOT(ISNUMBER(BA7)))),"依存変更承認不足",IF(BC7="依存なし","なし",IF(BC7<>"記法OK",BC7,IF(COUNTIF(AJ7:AQ7,"ID不正")>0,"依存ID不正",IF(COUNTIF(AJ7:AQ7,"未充足")>0,"前提未充足","記録上充足")))))) | Y7: =IF(OR(E7<>"適用",L7="完了",I7=""),"",IF(NOT(ISNUMBER(I7)),"予定日不正",IF(I7<AsOfDate,"期限超過","期限内"))) | Z7: =IF(W7="完了記録済",IF(OR(X7="なし",X7="記録上充足"),"完了記録・前提充足",X7),W7) -> 適用未判定 | AA7: =IF(AND(E7="適用",L7="完了",W7="完了記録済",OR(X7="なし",X7="記録上充足")),1,0) -> 0 | AB7: =TRIM(MID(SUBSTITUTE($V7,",",REPT(" ",64)),1,64)) -> B0-03 | AC7: =TRIM(MID(SUBSTITUTE($V7,",",REPT(" ",64)),65,64)) | AD7: =TRIM(MID(SUBSTITUTE($V7,",",REPT(" ",64)),129,64)) | AE7: =TRIM(MID(SUBSTITUTE($V7,",",REPT(" ",64)),193,64)) | AF7: =TRIM(MID(SUBSTITUTE($V7,",",REPT(" ",64)),257,64)) | AG7: =TRIM(MID(SUBSTITUTE($V7,",",REPT(" ",64)),321,64)) | AH7: =TRIM(MID(SUBSTITUTE($V7,",",REPT(" ",64)),385,64)) | AI7: =TRIM(MID(SUBSTITUTE($V7,",",REPT(" ",64)),449,64)) | AJ7: =IF(AB7="","",IF(OR(AB7=$A7,COUNTIF($A$4:$A$135,AB7)<>1,COUNTIF($AB7:$AI7,AB7)>1),"ID不正",IFERROR(IF(OR(INDEX($W$4:$W$135,MATCH(AB7,$A$4:$A$135,0))="完了記録済",INDEX($W$4:$W$135,MATCH(AB7,$A$4:$A$135,0))="除外記録済"),"記録充足","未充足"),"ID不正"))) -> 未充足 | AK7: =IF(AC7="","",IF(OR(AC7=$A7,COUNTIF($A$4:$A$135,AC7)<>1,COUNTIF($AB7:$AI7,AC7)>1),"ID不正",IFERROR(IF(OR(INDEX($W$4:$W$135,MATCH(AC7,$A$4:$A$135,0))="完了記録済",INDEX($W$4:$W$135,MATCH(AC7,$A$4:$A$135,0))="除外記録済"),"記録充足","未充足"),"ID不正"))) | AL7: =IF(AD7="","",IF(OR(AD7=$A7,COUNTIF($A$4:$A$135,AD7)<>1,COUNTIF($AB7:$AI7,AD7)>1),"ID不正",IFERROR(IF(OR(INDEX($W$4:$W$135,MATCH(AD7,$A$4:$A$135,0))="完了記録済",INDEX($W$4:$W$135,MATCH(AD7,$A$4:$A$135,0))="除外記録済"),"記録充足","未充足"),"ID不正"))) | AM7: =IF(AE7="","",IF(OR(AE7=$A7,COUNTIF($A$4:$A$135,AE7)<>1,COUNTIF($AB7:$AI7,AE7)>1),"ID不正",IFERROR(IF(OR(INDEX($W$4:$W$135,MATCH(AE7,$A$4:$A$135,0))="完了記録済",INDEX($W$4:$W$135,MATCH(AE7,$A$4:$A$135,0))="除外記録済"),"記録充足","未充足"),"ID不正"))) | AN7: =IF(AF7="","",IF(OR(AF7=$A7,COUNTIF($A$4:$A$135,AF7)<>1,COUNTIF($AB7:$AI7,AF7)>1),"ID不正",IFERROR(IF(OR(INDEX($W$4:$W$135,MATCH(AF7,$A$4:$A$135,0))="完了記録済",INDEX($W$4:$W$135,MATCH(AF7,$A$4:$A$135,0))="除外記録済"),"記録充足","未充足"),"ID不正"))) | AO7: =IF(AG7="","",IF(OR(AG7=$A7,COUNTIF($A$4:$A$135,AG7)<>1,COUNTIF($AB7:$AI7,AG7)>1),"ID不正",IFERROR(IF(OR(INDEX($W$4:$W$135,MATCH(AG7,$A$4:$A$135,0))="完了記録済",INDEX($W$4:$W$135,MATCH(AG7,$A$4:$A$135,0))="除外記録済"),"記録充足","未充足"),"ID不正"))) | AP7: =IF(AH7="","",IF(OR(AH7=$A7,COUNTIF($A$4:$A$135,AH7)<>1,COUNTIF($AB7:$AI7,AH7)>1),"ID不正",IFERROR(IF(OR(INDEX($W$4:$W$135,MATCH(AH7,$A$4:$A$135,0))="完了記録済",INDEX($W$4:$W$135,MATCH(AH7,$A$4:$A$135,0))="除外記録済"),"記録充足","未充足"),"ID不正"))) | AQ7: =IF(AI7="","",IF(OR(AI7=$A7,COUNTIF($A$4:$A$135,AI7)<>1,COUNTIF($AB7:$AI7,AI7)>1),"ID不正",IFERROR(IF(OR(INDEX($W$4:$W$135,MATCH(AI7,$A$4:$A$135,0))="完了記録済",INDEX($W$4:$W$135,MATCH(AI7,$A$4:$A$135,0))="除外記録済"),"記録充足","未充足"),"ID不正"))) | AR7: =IF(COUNT(P7:Q7)<2,"",Q7-P7) | AS7: =IF(COUNTIF('02_工程タスク'!$A$4:$A$135,A7)<>1,"参照ID不正",IF(INDEX('02_工程タスク'!$H$4:$H$135,MATCH(A7,'02_工程タスク'!$A$4:$A$135,0))="","",INDEX('02_工程タスク'!$H$4:$H$135,MATCH(A7,'02_工程タスク'!$A$4:$A$135,0)))) -> R02 | AT7: =IF(A7="","","INIT-"&A7) -> INIT-B0-04 | AU7: 初回 | BB7: =IF(COUNTIF('02_工程タスク'!$A$4:$A$135,A7)<>1,"参照ID不正",IF(INDEX('02_工程タスク'!$O$4:$O$135,MATCH(A7,'02_工程タスク'!$A$4:$A$135,0))="","",INDEX('02_工程タスク'!$O$4:$O$135,MATCH(A7,'02_工程タスク'!$A$4:$A$135,0)))) -> B0-03 | BC7: =IF(V7="","依存なし",IF(OR(LEFT(V7,1)=",",RIGHT(V7,1)=",",ISNUMBER(SEARCH(",,",SUBSTITUTE(V7," ",""))),LEN(V7)<>LEN(SUBSTITUTE(V7," ","")),ISNUMBER(SEARCH("，",V7))),"依存記法不正",IF(LEN(V7)-LEN(SUBSTITUTE(V7,",",""))>7,"依存8件超過","記法OK"))) -> 記法OK | BD7: =IF(A7="B6-01",IF(OR(AV7="",COUNTIF('29_ゲート承認記録'!$F$4:$F$83,AV7)<>1),"終了開始根拠不足",IF(IF(COUNTIF('29_ゲート承認記録'!$F$4:$F$83,AV7)<>1,"参照ID不正",IF(INDEX('29_ゲート承認記録'!$L$4:$L$83,MATCH(AV7,'29_ゲート承認記録'!$F$4:$F$83,0))="","",INDEX('29_ゲート承認記録'!$L$4:$L$83,MATCH(AV7,'29_ゲート承認記録'!$F$4:$F$83,0))))<>"Stop","Stop判断要確認","開始根拠あり")),IF(AND(A7="B5-18",AU7="事故"),IF(AV7="","事故レビュー参照不足","開始根拠あり"),"開始根拠あり")) -> 開始根拠あり
